Workbook
Name Slicer_Channel: #N/A
Name Slicer_Country: #N/A
Name Slicer_OrderDate__________mmm_yyyy: #N/A
Name Slicer_ProductCategory: #N/A
Name Slicer_Region: #N/A
Name Slicer_Salesperson: #N/A

Sheet Data
A1: OrderID | B1: OrderDate | C1: RequiredDate | D1: Region | E1: Country | F1: City | G1: CustomerSegment | H1: Channel | I1: Salesperson | J1: ProductCategory | K1: SKU | L1: UnitCost | M1: UnitPrice | N1: DiscountPct | O1: Quantity
A2: ORD-2024-275203 | B2: 45362 | C2: 45388 | D2: Africa | E2: Kenya | F2: Kisumu | G2: Corporate | H2: Retail | I2: C. Otieno | J2: Components | K2: CMP-8270 | L2: 279.24 | M2: 608.9 | N2: 0.112 | O2: 9
A3: ORD-2024-358795 | B3: 45588 | C3: 45587 | D3: Africa | E3: Nigeria | F3: Port Harcourt | G3: Education | H3: Online | I3: J. Njeri | J3: Printers | K3: PRN-9322 | L3: 1084.39 | M3: 759.33 | N3: 0.237 | O3: 31
A4: ORD-2023-373538 | B4: 44985 | C4: 45010 | D4: Africa | E4: Kenya | F4: Nairobi | G4: Corporate | H4: Retail | I4: I. Johnson | J4: Networking | K4: NET-9666 | L4: 1460.76 | M4: -30.66 | N4: 0.131 | O4: 12
A5: ORD-2025-168148 | B5: 45745 | C5: 45749 | D5: Africa | E5: Nigeria | F5: Lagos | G5: Non-Profit | H5: Marketplace | I5: G. Dubois | J5: Phones | K5: PHN-4556 | L5: 259.93 | M5: 255.94 | N5: 0.072 | O5: 22
A6: ORD-2023-824839 | B6: 45266 | C6: 45291 | D6: Asia | E6: Japan | F6: Osaka | G6: Consumer | H6: Retail | I6: L. Okafor | J6: Printers | K6: PRN-8041 | L6: 663.03 | M6: 813.51 | N6: 0.102 | O6: 15
A7: ORD-2023-723587 | B7: 44928 | C7: 44931 | D7: Americas | E7: Canada | F7: Toronto | G7: Corporate | H7: Distributor | I7: B. Chen | J7: Laptops | K7: LAP-8555 | L7: 315.87 | M7: 591.68 | N7: 0 | O7: 7
A8: ORD-2024-336584 | B8: 45653 | C8: 45671 | D8: Asia | E8: India | F8: Bengaluru | G8: Small Business | H8: Marketplace | I8: E. Garcia | J8: Monitors | K8: MON-8629 | L8: 586.07 | M8: 845.97 | N8: 0.147 | O8: 4
A9: ORD-2023-112666 | B9: 44941 | C9: 44939 | D9: Africa | E9: Nigeria | F9: Abuja | G9: Education | H9: Online | I9: O. Wang | J9: Printers | K9: PRN-6276 | L9: 28.38 | M9: 47.22 | N9: 0.194 | O9: 18
A10: ORD-2024-589570 | B10: 45416 | C10: 45441 | D10: Africa | E10: Nigeria | F10: Abuja | G10: Non-Profit | H10: Marketplace | I10: O. Wang | J10: Monitors | K10: MON-6892 | L10: 1295.34 | M10: 2530.81 | N10: 0.031 | O10: 6
A11: ORD-2025-997421 | B11: 45798 | C11: 45817 | D11: Americas | E11: Brazil | F11: São Paulo | G11: Non-Profit | H11: Online | I11: A. Patel | J11: Components | K11: CMP-3731 | L11: 1331.38 | M11: 2309.56 | N11: 0.149 | O11: 31
A12: ORD-2024-210687 | B12: 45319 | C12: 45331 | D12: Europe | E12: Germany | F12: Berlin | G12: Corporate | H12: Online | I12: G. Dubois | J12: Accessories | K12: ACC-7938 | L12: 644.17 | M12: 700.12 | N12: 0.006 | O12: 23
A13: ORD-2025-515515 | B13: 45660 | C13: 45680 | D13: Asia | E13: Japan | F13: Osaka | G13: Corporate | H13: Distributor | I13: F. Müller | J13: Phones | K13: PHN-7019 | L13: 908.6 | M13: 691.37 | N13: 0.25 | O13: 20
... A34: ORD-2025-474710 | B34: 45862 | C34: 45875 | D34: Africa | E34: South Africa | F34: Johannesburg | G34: Education | H34: Marketplace | I34: D. Smith | J34: Networking | K34: NET-7966 | L34: 1463.9 | M34: 2633.02 | N34: 0.084 | O34: 4
A35: ORD-2024-629525 | B35: 45400 | C35: 45420 | D35: Europe | E35: United Kingdom | F35: London | G35: Non-Profit | I35: D. Smith | J35: Laptops | K35: LAP-9932 | L35: 645.33 | M35: 1321.85 | N35: 0 | O35: 10
A36: ORD-2024-167215 | B36: 45527 | C36: 45525 | D36: Africa | E36: South Africa | F36: Johannesburg | G36: Education | H36: Retail | I36: E. Garcia | J36: Components | K36: CMP-1559 | L36: 1432.52 | M36: 3036.87 | N36: 0 | O36: 9
A37: ORD-2023-864121 | B37: 45012 | C37: 45038 | D37: Asia | E37: India | F37: Delhi | G37: Non-Profit | H37: Marketplace | I37: J. Njeri | J37: Printers | K37: PRN-4506 | L37: 178.53 | M37: 199.37 | N37: 0.101 | O37: 37
A38: ORD-2024-692673 | B38: 45358 | C38: 45376 | D38: Europe | E38: Germany | F38: Munich | G38: Corporate | H38: Online | I38: B. Chen | J38: Components | K38: CMP-7617 | L38: 712.84 | M38: 927.51 | N38: 0.243 | O38: 27
A39: ORD-2025-718992 | B39: 45832 | C39: 45848 | D39: Asia | E39: China | F39: Shanghai | G39: Enterprise | H39: Direct | I39: N. Brown | J39: Components | K39: CMP-8390 | L39: 757.19 | M39: 1735.41 | N39: 0.136 | O39: 8
A40: ORD-2024-599522 | B40: 45401 | C40: 45418 | D40: Africa | E40: Nigeria | F40: Port Harcourt | G40: Non-Profit | H40: Online | I40: A. Patel | J40: Printers | K40: PRN-7303 | L40: 865.33 | M40: 1395.64 | N40: 0.175 | O40: 13
A41: ORD-2023-651638 | B41: 45094 | C41: 45101 | D41: Americas | E41: USA | F41: San Francisco | G41: Corporate | H41: Retail | I41: I. Johnson | J41: Printers | K41: PRN-6536 | L41: 313.99 | M41: 454.42 | N41: 0.129 | O41: 9
A42: ORD-2024-635626 | B42: 45531 | C42: 45554 | D42: Europe | E42: Germany | F42: Berlin | G42: Small Business | H42: Direct | I42: D. Smith | J42: Monitors | K42: MON-9967 | L42: 1024.01 | M42: 1580.97 | N42: 0.037 | O42: 27
A43: ORD-2024-296582 | B43: 45302 | C43: 45324 | D43: Africa | E43: South Africa | F43: Durban | G43: Consumer | H43: Online | I43: K. Singh | J43: Networking | K43: NET-1412 | L43: 1206.2 | M43: 1759.79 | N43: 0 | O43: 6
A44: ORD-2024-998320 | B44: 45590 | C44: 45610 | D44: Africa | E44: Kenya | F44: Mombasa | G44: Corporate | H44: Direct | I44: H. Kim | J44: Printers | K44: PRN-3143 | L44: 1396.48 | M44: 3204.5 | N44: 0.318 | O44: 14
A45: ORD-2025-820255 | B45: 45806 | C45: 45828 | D45: Europe | E45: Germany | F45: Berlin | G45: Corporate | H45: Direct | I45: A. Patel | J45: Printers | K45: PRN-9787 | L45: 483.47 | M45: 1135.43 | N45: 0.146 | O45: 11
A46: ORD-2024-389336 | B46: 45432 | C46: 45445 | D46: Americas | E46: Canada | F46: Vancouver | G46: Enterprise | H46: Marketplace | I46: K. Singh | J46: Components | K46: CMP-5946 | L46: 675.43 | M46: 996.36 | N46: 0.182 | O46: 22
A47: ORD-2023-308124 | B47: 45035 | C47: 45046 | D47: Asia | E47: India | F47: Delhi | G47: Small Business | H47: Retail | I47: A. Patel | J47: Networking | K47: NET-2062 | L47: 826.55 | M47: 1397.05 | N47: 0.169 | O47: 28
... A77: ORD-2023-722117 | B77: 45187 | C77: 45207 | D77: Asia | E77: India | F77: Delhi | G77: Small Business | H77: Direct | I77: B. Chen | J77: Components | K77: CMP-1009 | L77: 825.64 | M77: 1108.43 | N77: 0.114 | O77: 7
A78: ORD-2024-446699 | B78: 45532 | C78: 45560 | D78: Americas | E78: Brazil | F78: Rio de Janeiro | G78: Non-Profit | H78: Online | J78: Accessories | K78: ACC-4490 | L78: 1394.65 | M78: 3144.1 | N78: 0.134 | O78: 13
A79: ORD-2024-451005 | B79: 45473 | C79: 45471 | D79: Americas | E79: Brazil | F79: Rio de Janeiro | G79: Small Business | H79: Direct | I79: L. Okafor | J79: Accessories | K79: ACC-9162 | L79: 1112.98 | M79: 2095.73 | N79: 0.072 | O79: 17
A80: ORD-2023-290279 | B80: 45091 | C80: 45093 | D80: Europe | E80: United Kingdom | F80: Manchester | G80: Non-Profit | H80: Direct | I80: K. Singh | J80: Components | K80: CMP-5820 | L80: 357.36 | M80: 703.62 | N80: 0.257 | O80: 20
A81: ORD-2024-192263 | B81: 45617 | C81: 45647 | D81: Europe | E81: France | F81: Marseille | G81: Small Business | H81: Direct | I81: I. Johnson | J81: Monitors | K81: MON-7943 | L81: 1122.68 | M81: 1997.19 | N81: 0.186 | O81: 3
A82: ORD-2023-159379 | B82: 44965 | C82: 44968 | D82: Africa | E82: South Africa | F82: Cape Town | G82: Corporate | H82: Direct | I82: M. Rossi | J82: Networking | K82: NET-5018 | L82: 1410.05 | M82: 2763.95 | N82: 0.161 | O82: 26
A83: ORD-2023-343322 | B83: 45157 | C83: 45181 | D83: Americas | E83: Canada | F83: Vancouver | G83: Enterprise | H83: Retail | I83: I. Johnson | J83: Printers | K83: PRN-9669 | L83: 1183.95 | M83: 1503.53 | N83: 0.241 | O83: 16
A84: ORD-2025-114382 | B84: 45791 | C84: 45801 | D84: Europe | E84: France | F84: Paris | G84: Small Business | H84: Marketplace | I84: K. Singh | J84: Components | K84: CMP-2865 | L84: 170.39 | M84: 388.04 | N84: 0.084 | O84: 15
A85: ORD-2025-488349 | B85: 45770 | C85: 45769 | D85: Americas | E85: USA | F85: San Francisco | G85: Non-Profit | H85: Distributor | I85: D. Smith | J85: Monitors | K85: MON-3371 | L85: 23.24 | M85: 44.57 | N85: 0.215 | O85: 15
A86: ORD-2025-330203 | B86: 45741 | C86: 45764 | D86: Europe | E86: United Kingdom | F86: London | G86: Consumer | H86: Retail | I86: H. Kim | J86: Networking | K86: NET-7166 | L86: 1421.19 | M86: 1808.26 | N86: 0.104 | O86: 13
A87: ORD-2023-841426 | B87: 45282 | C87: 45283 | D87: Africa | E87: South Africa | F87: Cape Town | G87: Non-Profit | H87: Marketplace | I87: D. Smith | J87: Components | K87: CMP-4531 | L87: 1186.18 | M87: 1285.09 | N87: 0.07 | O87: 11
A88: ORD-2024-594592 | B88: 45388 | C88: 45407 | D88: Asia | E88: China | F88: Shanghai | G88: Corporate | H88: Retail | I88: K. Singh | J88: Components | K88: CMP-8196 | L88: 1366.48 | M88: 1678.14 | N88: 0.154 | O88: 10
A89: ORD-2025-863978 | B89: 45876 | C89: 45888 | D89: Africa | E89: Kenya | F89: Nakuru | G89: Corporate | I89: M. Rossi | J89: Components | K89: CMP-2854 | L89: 601.51 | M89: 679.35 | N89: 0.188 | O89: 3
A90: ORD-2024-604471 | B90: 45312 | C90: 45316 | D90: Asia | E90: India | F90: Delhi | G90: Consumer | H90: Direct | I90: C. Otieno | J90: Monitors | K90: MON-8973 | L90: 523.7 | M90: 1109.92 | N90: 0.03 | O90: 11
A91: ORD-2023-258768 | B91: 45106 | C91: 45109 | D91: Asia | E91: Japan | F91: Nagoya | G91: Education | H91: Marketplace | I91: F. Müller | J91: Monitors | K91: MON-2990 | L91: 55.65 | M91: 83.57 | N91: 0.066 | O91: 8
A92: ORD-2025-626047 | B92: 45775 | C92: 45792 | D92: Asia | E92: Japan | F92: Nagoya | G92: Education | H92: Direct | I92: N. Brown | J92: Networking | K92: NET-1966 | L92: 691.19 | M92: 1284.3 | N92: 0.074 | O92: 7
A93: ORD-2025-526752 | B93: 45817 | C93: 45833 | D93: Asia | E93: India | F93: Hyderabad | G93: Enterprise | H93: Distributor | I93: M. Rossi | J93: Phones | K93: PHN-3482 | L93: 527.33 | M93: 911.72 | N93: 0.144 | O93: 25
A94: ORD-2023-374486 | B94: 45101 | C94: 45100 | D94: Americas | E94: Brazil | F94: Rio de Janeiro | G94: Non-Profit | H94: Retail | I94: E. Garcia | J94: Printers | K94: PRN-6490 | L94: 804.01 | M94: 1405.07 | N94: 0.096 | O94: 8
A95: ORD-2024-997336 | B95: 45569 | C95: 45598 | D95: Africa | E95: Nigeria | F95: Abuja | G95: Corporate | H95: Distributor | I95: F. Müller | J95: Accessories | K95: ACC-9038 | L95: 412.09 | M95: 968.94 | N95: 0.099 | O95: 23
A96: ORD-2025-725646 | B96: 45910 | C96: 45930 | D96: Africa | E96: Kenya | F96: Mombasa | G96: Corporate | H96: Direct | I96: L. Okafor | J96: Phones | K96: PHN-6954 | L96: 1009.48 | M96: 1088.81 | N96: 0.16 | O96: 6
A97: ORD-2023-868734 | B97: 45022 | C97: 45043 | D97: Europe | E97: United Kingdom | F97: Manchester | G97: Enterprise | H97: Distributor | I97: I. Johnson | J97: Printers | K97: PRN-8970 | L97: 1084.79 | M97: 2484.99 | N97: 0.034 | O97: 18
A98: ORD-2025-262491 | B98: 45870 | C98: 45885 | D98: Asia | E98: India | G98: Enterprise | H98: Direct | I98: O. Wang | J98: Monitors | K98: MON-1822 | L98: 24.44 | M98: 28.69 | N98: 0.146 | O98: 6
A99: ORD-2024-638884 | B99: 45440 | C99: 45438 | D99: Africa | E99: Nigeria | F99: Abuja | G99: Enterprise | H99: Online | I99: F. Müller | J99: Accessories | K99: ACC-5177 | L99: 1227.08 | M99: 1896.62 | N99: 0 | O99: 18
A100: ORD-2025-541501 | B100: 45860 | C100: 45887 | D100: Asia | E100: China | F100: Shenzhen | G100: Non-Profit | H100: Marketplace | I100: M. Rossi | J100: Networking | K100: NET-1804 | L100: 547.32 | M100: 419.17 | N100: 0.092 | O100: 14
A101: ORD-2023-422918 | B101: 44985 | C101: 45005 | D101: Europe | E101: Germany | F101: Berlin | G101: Small Business | H101: Direct | I101: H. Kim | J101: Laptops | K101: LAP-3679 | L101: 1200.78 | M101: 2001.17 | N101: 0.292 | O101: 18
A102: ORD-2025-328504 | B102: 45684 | C102: 45703 | D102: Asia | E102: China | F102: Shenzhen | G102: Non-Profit | H102: Direct | I102: L. Okafor | J102: Phones | K102: PHN-8368 | L102: 1253.22 | M102: 3104.71 | N102: 0 | O102: 17
A103: ORD-2024-851883 | B103: 45304 | C103: 45313 | D103: Asia | E103: India | F103: Mumbai | G103: Enterprise | H103: Marketplace | I103: J. Njeri | J103: Components | K103: CMP-8141 | L103: 313.6 | M103: 334.28 | N103: 0.14 | O103: 22
A104: ORD-2025-662997 | B104: 45747 | C104: 45751 | D104: Africa | E104: Kenya | F104: Nakuru | G104: Corporate | H104: Direct | I104: C. Otieno | J104: Laptops | K104: LAP-7136 | L104: 862.08 | M104: 1952.83 | N104: 0 | O104: 7
A105: ORD-2024-478165 | B105: 45631 | C105: 45654 | D105: Americas | E105: Canada | F105: Vancouver | G105: Corporate | H105: Direct | I105: F. Müller | J105: Accessories | K105: ACC-2386 | L105: 107.03 | M105: 242.29 | N105: 0.18 | O105: 30
A106: ORD-2024-771210 | B106: 45549 | C106: 45570 | D106: Asia | E106: China | F106: Shanghai | G106: Small Business | H106: Online | I106: H. Kim | J106: Laptops | K106: LAP-5150 | L106: 1405.56 | M106: 2968.87 | N106: 0.169 | O106: 5
A107: ORD-2024-155337 | B107: 45433 | C107: 45439 | D107: Africa | E107: South Africa | F107: Johannesburg | G107: Non-Profit | H107: Online | I107: M. Rossi | J107: Components | K107: CMP-8101 | L107: 1157.51 | M107: 1394.3 | N107: 0.278 | O107: 12
A108: ORD-2023-251563 | B108: 45057 | C108: 45084 | D108: Africa | E108: Kenya | F108: Mombasa | G108: Corporate | H108: Online | I108: J. Njeri | J108: Phones | K108: PHN-8970 | L108: 12.85 | M108: 15.41 | N108: 0.137 | O108: 39
A109: ORD-2024-286833 | B109: 45518 | C109: 45539 | D109: Europe | E109: United Kingdom | F109: Manchester | G109: Non-Profit | H109: Online | I109: J. Njeri | J109: Phones | K109: PHN-2341 | L109: 1138.8 | M109: 2250.81 | N109: 0.123 | O109: 12
A110: ORD-2024-792558 | B110: 45581 | C110: 45604 | D110: Asia | E110: Japan | F110: Osaka | G110: Small Business | H110: Retail | I110: J. Njeri | J110: Networking | K110: NET-6387 | L110: 82.14 | M110: 166.04 | N110: 0 | O110: 10
... A121: ORD-2025-956101 | B121: 45847 | C121: 45856 | D121: Americas | E121: Canada | F121: Vancouver | G121: Education | H121: Distributor | I121: I. Johnson | J121: Laptops | K121: LAP-2218 | L121: 57.96 | M121: 88.51 | N121: 0.043 | O121: 7
A122: ORD-2025-184082 | B122: 45827 | C122: 45850 | D122: Europe | E122: United Kingdom | G122: Non-Profit | H122: Direct | J122: Networking | K122: NET-6370 | L122: 801.24 | M122: 1959.09 | N122: 0.123 | O122: 23
A123: ORD-2023-576840 | B123: 45249 | C123: 45273 | D123: Europe | E123: France | F123: Lyon | G123: Non-Profit | H123: Direct | I123: H. Kim | J123: Monitors | K123: MON-3745 | L123: 1297.42 | M123: 2742.97 | N123: 0.069 | O123: 9
A124: ORD-2023-178249 | B124: 45289 | C124: 45311 | D124: Africa | E124: Kenya | F124: Kisumu | G124: Corporate | H124: Direct | I124: L. Okafor | J124: Phones | K124: PHN-7924 | L124: 1395.49 | M124: 1679.42 | N124: 0.203 | O124: 12
A125: ORD-2024-588972 | B125: 45598 | C125: 45625 | D125: Americas | E125: Brazil | F125: Brasília | G125: Small Business | H125: Direct | I125: I. Johnson | J125: Networking | K125: NET-8561 | L125: 1363.51 | M125: 1433.9 | N125: 0.057 | O125: 8
A126: ORD-2023-603238 | B126: 45159 | C126: 45173 | D126: Americas | E126: Canada | F126: Montreal | G126: Education | H126: Distributor | I126: F. Müller | J126: Components | K126: CMP-2136 | L126: 178.19 | M126: 284.43 | N126: 0.089 | O126: 8
A127: ORD-2023-883066 | B127: 45150 | C127: 45175 | D127: Asia | E127: China | F127: Shanghai | G127: Small Business | H127: Retail | I127: B. Chen | J127: Components | K127: CMP-6352 | L127: 950.77 | M127: 694.78 | N127: 0.084 | O127: 14
A128: ORD-2024-584090 | B128: 45450 | C128: 45469 | D128: Europe | E128: Germany | F128: Berlin | G128: Non-Profit | H128: Marketplace | I128: M. Rossi | J128: Components | K128: CMP-2040 | L128: 1064.32 | M128: 1848.39 | N128: 0.073 | O128: 38
A129: ORD-2025-537785 | B129: 45874 | C129: 45883 | D129: Europe | E129: United Kingdom | F129: London | G129: Non-Profit | H129: Direct | I129: E. Garcia | J129: Components | K129: CMP-6346 | L129: 41.76 | M129: 45.19 | N129: 0.179 | O129: 23
A130: ORD-2024-605518 | B130: 45442 | C130: 45456 | D130: Americas | E130: USA | F130: San Francisco | G130: Small Business | H130: Retail | I130: F. Müller | J130: Phones | K130: PHN-4356 | L130: 157.78 | M130: 361.1 | N130: 0.187 | O130: 9
A131: ORD-2023-521818 | B131: 44948 | C131: 44956 | D131: Americas | E131: USA | F131: San Francisco | G131: Small Business | H131: Online | I131: A. Patel | J131: Networking | K131: NET-4155 | L131: 413.52 | M131: 1004.34 | N131: 0.111 | O131: 18
A132: ORD-2025-650719 | B132: 45700 | C132: 45716 | D132: Americas | E132: Brazil | F132: São Paulo | G132: Non-Profit | H132: Direct | I132: B. Chen | J132: Monitors | K132: MON-5179 | L132: 414.95 | M132: 1027.73 | N132: 0.063 | O132: 8
A133: ORD-2025-501927 | B133: 45719 | C133: 45740 | D133: Africa | E133: Nigeria | F133: Abuja | G133: Enterprise | H133: Direct | I133: H. Kim | J133: Accessories | K133: ACC-4056 | L133: 555.95 | M133: 468.09 | N133: 0.142 | O133: 11
A134: ORD-2023-430904 | B134: 44953 | C134: 44957 | D134: Europe | E134: United Kingdom | F134: Manchester | G134: Enterprise | H134: Online | I134: N. Brown | J134: Laptops | K134: LAP-9782 | L134: 941.2 | M134: 668.02 | N134: 0.22 | O134: 16
... A187: ORD-2023-399631 | B187: 45099 | C187: 45128 | D187: Europe | E187: France | F187: Lyon | G187: Corporate | H187: Retail | I187: J. Njeri | J187: Accessories | K187: ACC-3385 | L187: 734.34 | M187: 887.9 | N187: 0.025 | O187: 12
A188: ORD-2025-542939 | B188: 45670 | C188: 45696 | D188: Europe | E188: France | F188: Paris | G188: Non-Profit | I188: E. Garcia | J188: Monitors | K188: MON-1593 | L188: 594.74 | M188: 1020.69 | N188: 0.211 | O188: 6
A189: ORD-2023-521818 | B189: 44955 | C189: 44985 | D189: Asia | E189: India | F189: Bengaluru | G189: Non-Profit | H189: Retail | I189: B. Chen | J189: Accessories | K189: ACC-4631 | L189: 1262.1 | M189: 1395.53 | N189: 0.233 | O189: 25
A190: ORD-2023-825836 | B190: 45126 | C190: 45138 | D190: Americas | E190: Brazil | F190: Rio de Janeiro | G190: Corporate | H190: Retail | I190: C. Otieno | J190: Monitors | K190: MON-7869 | L190: 1334.64 | M190: 2273.42 | N190: 0.118 | O190: 14
A191: ORD-2024-503082 | B191: 45431 | C191: 45451 | D191: Americas | E191: Brazil | F191: Brasília | G191: Small Business | H191: Retail | I191: E. Garcia | J191: Monitors | K191: MON-4271 | L191: 1075.9 | M191: 1242.15 | N191: 0.012 | O191: 7
A192: ORD-2024-760799 | B192: 45325 | C192: 45341 | D192: Asia | E192: China | F192: Shenzhen | G192: Small Business | H192: Online | I192: H. Kim | J192: Laptops | K192: LAP-5531 | L192: 993.75 | M192: 1310.29 | N192: 0.215 | O192: 19
A193: ORD-2023-197661 | B193: 45146 | C193: 45160 | D193: Europe | E193: United Kingdom | F193: Birmingham | G193: Non-Profit | H193: Direct | I193: N. Brown | J193: Monitors | K193: MON-7511 | L193: 446.69 | M193: 967.25 | N193: 0.094 | O193: 10
A194: ORD-2024-212990 | B194: 45516 | C194: 45538 | D194: Americas | E194: USA | F194: Austin | G194: Consumer | H194: Distributor | I194: I. Johnson | J194: Laptops | K194: LAP-7979 | L194: 797.8 | M194: 886.22 | N194: 0.236 | O194: 36
A195: ORD-2023-925146 | B195: 45214 | C195: 45243 | D195: Asia | E195: China | F195: Shenzhen | G195: Non-Profit | H195: Distributor | I195: J. Njeri | J195: Printers | K195: PRN-4983 | L195: 986.44 | M195: 790.61 | N195: 0.072 | O195: 6
A196: ORD-2023-177794 | B196: 45050 | C196: 45072 | D196: Americas | E196: USA | F196: San Francisco | G196: Enterprise | H196: Online | I196: J. Njeri | J196: Networking | K196: NET-5941 | L196: 249.71 | M196: 361.33 | N196: 0.094 | O196: 12
A197: ORD-2024-444710 | B197: 45557 | C197: 45566 | D197: Americas | E197: Brazil | F197: São Paulo | G197: Non-Profit | H197: Online | I197: K. Singh | J197: Monitors | K197: MON-6341 | L197: 1378.8 | M197: 1952.04 | N197: 0.159 | O197: 19
A198: ORD-2024-668926 | B198: 45588 | C198: 45610 | D198: Asia | E198: Japan | F198: Osaka | G198: Non-Profit | H198: Direct | I198: B. Chen | J198: Phones | K198: PHN-9789 | L198: 1406.4 | M198: 1564.76 | N198: 0.185 | O198: 17
A199: ORD-2024-968374 | B199: 45333 | C199: 45354 | D199: Africa | E199: Kenya | F199: Kisumu | G199: Enterprise | H199: Online | I199: B. Chen | J199: Phones | K199: PHN-5082 | L199: 516.86 | M199: 852.54 | N199: 0.051 | O199: 14
A200: ORD-2023-575584 | B200: 44956 | C200: 44978 | D200: Europe | E200: Germany | F200: Munich | G200: Small Business | H200: Marketplace | I200: G. Dubois | J200: Networking | K200: NET-3460 | L200: 1142.88 | M200: 1465.29 | N200: 0.186 | O200: 7
... A236: ORD-2023-946143 | B236: 44999 | C236: 45015 | D236: Africa | E236: South Africa | F236: Cape Town | G236: Consumer | H236: Distributor | I236: K. Singh | J236: Components | K236: CMP-8230 | L236: 1309.77 | M236: 1589.07 | N236: 0.102 | O236: 10
A237: ORD-2024-281211 | B237: 45302 | C237: 45324 | D237: Asia | E237: Japan | F237: Nagoya | G237: Small Business | H237: Online | J237: Printers | K237: PRN-7816 | L237: 1237.68 | M237: 1432.8 | N237: 0.068 | O237: 13
A238: ORD-2024-805860 | B238: 45548 | C238: 45567 | D238: Africa | E238: Kenya | F238: Mombasa | G238: Small Business | H238: Retail | I238: M. Rossi | J238: Phones | K238: PHN-8804 | L238: 1338.99 | M238: 1765.76 | N238: 0.126 | O238: 24
A239: ORD-2025-132174 | B239: 45855 | C239: 45861 | D239: Americas | E239: Canada | F239: Vancouver | G239: Consumer | H239: Online | I239: H. Kim | J239: Components | K239: CMP-8851 | L239: 1364.89 | M239: 2757.54 | N239: 0.172 | O239: 61
A240: ORD-2023-964434 | B240: 45258 | C240: 45267 | D240: Asia | E240: India | F240: Delhi | G240: Enterprise | H240: Marketplace | I240: L. Okafor | J240: Phones | K240: PHN-2447 | L240: 699.33 | M240: 873.75 | N240: 0.235 | O240: 10
A241: ORD-2024-897622 | B241: 45381 | C241: 45406 | D241: Americas | E241: USA | F241: Austin | G241: Non-Profit | H241: Online | I241: G. Dubois | J241: Laptops | K241: LAP-2846 | L241: 160.82 | M241: 258.52 | N241: 0.13 | O241: 17
A242: ORD-2023-517216 | B242: 45188 | C242: 45207 | D242: Asia | E242: India | F242: Bengaluru | G242: Education | H242: Direct | I242: J. Njeri | J242: Printers | K242: PRN-5005 | L242: 385.32 | M242: 606.76 | N242: 0.086 | O242: 8
A243: ORD-2025-509940 | B243: 45793 | C243: 45804 | D243: Asia | E243: China | F243: Beijing | G243: Enterprise | H243: Online | I243: F. Müller | J243: Phones | K243: PHN-3800 | L243: 918.12 | M243: 1337.69 | N243: 0.095 | O243: 8
A244: ORD-2025-646342 | B244: 45871 | C244: 45877 | D244: Asia | E244: Japan | F244: Osaka | G244: Consumer | H244: Direct | I244: N. Brown | J244: Laptops | K244: LAP-4828 | L244: 1225.94 | M244: 1793.08 | N244: 0.136 | O244: 22
A245: ORD-2024-866535 | B245: 45630 | C245: 45638 | D245: Europe | E245: Germany | F245: Frankfurt | G245: Enterprise | H245: Marketplace | I245: B. Chen | J245: Printers | K245: PRN-5492 | L245: 72.06 | M245: 122.74 | N245: 0.238 | O245: 8
A246: ORD-2023-747341 | B246: 45035 | C246: 45044 | D246: Americas | E246: Brazil | F246: Rio de Janeiro | G246: Corporate | H246: Distributor | I246: M. Rossi | J246: Phones | K246: PHN-7132 | L246: 1013.54 | M246: 927.93 | N246: 0.175 | O246: 16
...

Sheet Clean
A1: Column1 | B1: OrderDate | C1: OrderDate (mmm-yyyy) | D1: Order Quarter | E1: RequiredDate | F1: Cleaned RequiredDate | G1: LeadTimeDays | H1: Cleaned LeadTimeDays | I1: Target Met (7 days) | J1: StartDate | K1: Region | L1: Country | M1: City | N1: Region hierarchy | O1: CustomerSegment | P1: Channel | Q1: Salesperson | R1: ProductCategory | S1: SKU | T1: UnitCost | U1: UnitPrice | V1: Cleaned UnitPrice | W1: PriceBand | X1: DiscountPct | Y1: Cleaned DiscountPct | Z1: Discount(>20%) | AA1: Quantity | AB1: GrossRevenue | AC1: CostOfGoods | AD1: GrossProfit | AE1: MarginPct | AF1: DiscountPct (Scenario) | AG1: Quantity (Scenario) | AH1: UnitCost (Scenario) | AI1: GrossRevenue (Scenario) | AJ1: GrossProfit(Scenario)
A2: ORD-2024-275203 | B2: 45362 | C2: 45362 | D2: ="Q"&ROUNDUP(MONTH(B2)/3,0)&"-"&YEAR(B2) -> Q1-2024 | E2: 45388 | F2: 45388 | G2: =E2-B2 -> 26 | H2: =F2-B2 -> 26 | I2: =IF(H2<=7, "Yes", "No") -> No | J2: =_xlfn.MINIFS($B$2:$B$633, $L$2:$L$633, L2) -> 44946 | K2: Africa | L2: Kenya | M2: Kisumu | N2: =_xlfn.TEXTJOIN(" - ", TRUE, K2:M2) -> Africa - Kenya - Kisumu | O2: Corporate | P2: Retail | Q2: C. Otieno | R2: Components | S2: CMP-8270 | T2: 279.24 | U2: 608.9 | V2: =ABS(U2) -> 608.9 | W2: =IF(V2 <= _xlfn.PERCENTILE.INC($V$2:$V$633, 0.33), "Low", IF(V2 <= _xlfn.PERCENTILE.INC($V$2:$V$633, 0.67), "Medium", "High")) -> Low | X2: 0.112 | Y2: =IF(X2>30%,AVERAGEIF($X$2:$X$633,"<30%"),X2) -> 0.112 | Z2: =IF(Y2>0.2, "Yes", "No") -> No | AA2: 9 | AB2: =U2*AA2*(1-Y2) -> 4866.3288 | AC2: =T2*AA2 -> 2513.16 | AD2: =AB2-AC2 -> 2353.1688 | AE2: =IF(AB2=0, 0, AD2 / AB2) -> 0.48356141 | AF2: =MIN(Y2,'Scenario Modeling'!$B$2) -> 0.112 | AG2: =ROUND(AA2 * (1 + 'Scenario Modeling'!$B$4), 0) -> 9 | AH2: =T2 * (1 + 'Scenario Modeling'!$B$3) -> 279.24 | AI2: =V2 * AG2 * (1 - AF2) -> 4866.3288 | AJ2: =AI2 - (AH2 * AG2) -> 2353.1688
A3: ORD-2024-358795 | B3: 45588 | C3: 45588 | D3: ="Q"&ROUNDUP(MONTH(B3)/3,0)&"-"&YEAR(B3) -> Q4-2024 | E3: 45587 | F3: =B3+10 -> 45598 | G3: =E3-B3 -> -1 | H3: =F3-B3 -> 10 | I3: =IF(H3<=7, "Yes", "No") -> No | J3: =_xlfn.MINIFS($B$2:$B$633, $L$2:$L$633, L3) -> 44941 | K3: Africa | L3: Nigeria | M3: Port Harcourt | N3: =_xlfn.TEXTJOIN(" - ", TRUE, K3:M3) -> Africa - Nigeria - Port Harcourt | O3: Education | P3: Online | Q3: J. Njeri | R3: Printers | S3: PRN-9322 | T3: 1084.39 | U3: 759.33 | V3: =ABS(U3) -> 759.33 | W3: =IF(V3 <= _xlfn.PERCENTILE.INC($V$2:$V$633, 0.33), "Low", IF(V3 <= _xlfn.PERCENTILE.INC($V$2:$V$633, 0.67), "Medium", "High")) -> Low | X3: 0.237 | Y3: =IF(X3>30%,AVERAGEIF($X$2:$X$633,"<30%"),X3) -> 0.237 | Z3: =IF(Y3>0.2, "Yes", "No") -> Yes | AA3: 31 | AB3: =U3*AA3*(1-Y3) -> 17960.432 | AC3: =T3*AA3 -> 33616.09 | AD3: =AB3-AC3 -> -15655.658 | AE3: =IF(AB3=0, 0, AD3 / AB3) -> -0.87167486 | AF3: =MIN(Y3,'Scenario Modeling'!$B$2) -> 0.237 | AG3: =ROUND(AA3 * (1 + 'Scenario Modeling'!$B$4), 0) -> 31 | AH3: =T3 * (1 + 'Scenario Modeling'!$B$3) -> 1084.39 | AI3: =V3 * AG3 * (1 - AF3) -> 17960.432 | AJ3: =AI3 - (AH3 * AG3) -> -15655.658
A4: ORD-2023-373538 | B4: 44985 | C4: 44985 | D4: ="Q"&ROUNDUP(MONTH(B4)/3,0)&"-"&YEAR(B4) -> Q1-2023 | E4: 45010 | F4: 45010 | G4: =E4-B4 -> 25 | H4: =F4-B4 -> 25 | I4: =IF(H4<=7, "Yes", "No") -> No | J4: =_xlfn.MINIFS($B$2:$B$633, $L$2:$L$633, L4) -> 44946 | K4: Africa | L4: Kenya | M4: Nairobi | N4: =_xlfn.TEXTJOIN(" - ", TRUE, K4:M4) -> Africa - Kenya - Nairobi | O4: Corporate | P4: Retail | Q4: I. Johnson | R4: Networking | S4: NET-9666 | T4: 1460.76 | U4: -30.66 | V4: =ABS(U4) -> 30.66 | W4: =IF(V4 <= _xlfn.PERCENTILE.INC($V$2:$V$633, 0.33), "Low", IF(V4 <= _xlfn.PERCENTILE.INC($V$2:$V$633, 0.67), "Medium", "High")) -> Low | X4: 0.131 | Y4: =IF(X4>30%,AVERAGEIF($X$2:$X$633,"<30%"),X4) -> 0.131 | Z4: =IF(Y4>0.2, "Yes", "No") -> No | AA4: 12 | AB4: =U4*AA4*(1-Y4) -> -319.72248 | AC4: =T4*AA4 -> 17529.12 | AD4: =AB4-AC4 -> -17848.842 | AE4: =IF(AB4=0, 0, AD4 / AB4) -> 55.826048 | AF4: =MIN(Y4,'Scenario Modeling'!$B$2) -> 0.131 | AG4: =ROUND(AA4 * (1 + 'Scenario Modeling'!$B$4), 0) -> 12 | AH4: =T4 * (1 + 'Scenario Modeling'!$B$3) -> 1460.76 | AI4: =V4 * AG4 * (1 - AF4) -> 319.72248 | AJ4: =AI4 - (AH4 * AG4) -> -17209.398
A5: ORD-2025-168148 | B5: 45745 | C5: 45745 | D5: ="Q"&ROUNDUP(MONTH(B5)/3,0)&"-"&YEAR(B5) -> Q1-2025 | E5: 45749 | F5: 45749 | G5: =E5-B5 -> 4 | H5: =F5-B5 -> 4 | I5: =IF(H5<=7, "Yes", "No") -> Yes | J5: =_xlfn.MINIFS($B$2:$B$633, $L$2:$L$633, L5) -> 44941 | K5: Africa | L5: Nigeria | M5: Lagos | N5: =_xlfn.TEXTJOIN(" - ", TRUE, K5:M5) -> Africa - Nigeria - Lagos | O5: Non-Profit | P5: Marketplace | Q5: G. Dubois | R5: Phones | S5: PHN-4556 | T5: 259.93 | U5: 255.94 | V5: =ABS(U5) -> 255.94 | W5: =IF(V5 <= _xlfn.PERCENTILE.INC($V$2:$V$633, 0.33), "Low", IF(V5 <= _xlfn.PERCENTILE.INC($V$2:$V$633, 0.67), "Medium", "High")) -> Low | X5: 0.072 | Y5: =IF(X5>30%,AVERAGEIF($X$2:$X$633,"<30%"),X5) -> 0.072 | Z5: =IF(Y5>0.2, "Yes", "No") -> No | AA5: 22 | AB5: =U5*AA5*(1-Y5) -> 5225.271 | AC5: =T5*AA5 -> 5718.46 | AD5: =AB5-AC5 -> -493.18896 | AE5: =IF(AB5=0, 0, AD5 / AB5) -> -0.094385335 | AF5: =MIN(Y5,'Scenario Modeling'!$B$2) -> 0.072 | AG5: =ROUND(AA5 * (1 + 'Scenario Modeling'!$B$4), 0) -> 22 | AH5: =T5 * (1 + 'Scenario Modeling'!$B$3) -> 259.93 | AI5: =V5 * AG5 * (1 - AF5) -> 5225.271 | AJ5: =AI5 - (AH5 * AG5) -> -493.18896
A6: ORD-2023-824839 | B6: 45266 | C6: 45266 | D6: ="Q"&ROUNDUP(MONTH(B6)/3,0)&"-"&YEAR(B6) -> Q4-2023 | E6: 45291 | F6: 45291 | G6: =E6-B6 -> 25 | H6: =F6-B6 -> 25 | I6: =IF(H6<=7, "Yes", "No") -> No | J6: =_xlfn.MINIFS($B$2:$B$633, $L$2:$L$633, L6) -> 44988 | K6: Asia | L6: Japan | M6: Osaka | N6: =_xlfn.TEXTJOIN(" - ", TRUE, K6:M6) -> Asia - Japan - Osaka | O6: Consumer | P6: Retail | Q6: L. Okafor | R6: Printers | S6: PRN-8041 | T6: 663.03 | U6: 813.51 | V6: =ABS(U6) -> 813.51 | W6: =IF(V6 <= _xlfn.PERCENTILE.INC($V$2:$V$633, 0.33), "Low", IF(V6 <= _xlfn.PERCENTILE.INC($V$2:$V$633, 0.67), "Medium", "High")) -> Low | X6: 0.102 | Y6: =IF(X6>30%,AVERAGEIF($X$2:$X$633,"<30%"),X6) -> 0.102 | Z6: =IF(Y6>0.2, "Yes", "No") -> No | AA6: 15 | AB6: =U6*AA6*(1-Y6) -> 10957.98 | AC6: =T6*AA6 -> 9945.45 | AD6: =AB6-AC6 -> 1012.5297 | AE6: =IF(AB6=0, 0, AD6 / AB6) -> 0.092401129 | AF6: =MIN(Y6,'Scenario Modeling'!$B$2) -> 0.102 | AG6: =ROUND(AA6 * (1 + 'Scenario Modeling'!$B$4), 0) -> 15 | AH6: =T6 * (1 + 'Scenario Modeling'!$B$3) -> 663.03 | AI6: =V6 * AG6 * (1 - AF6) -> 10957.98 | AJ6: =AI6 - (AH6 * AG6) -> 1012.5297
A7: ORD-2023-723587 | B7: 44928 | C7: 44928 | D7: ="Q"&ROUNDUP(MONTH(B7)/3,0)&"-"&YEAR(B7) -> Q1-2023 | E7: 44931 | F7: 44931 | G7: =E7-B7 -> 3 | H7: =F7-B7 -> 3 | I7: =IF(H7<=7, "Yes", "No") -> Yes | J7: =_xlfn.MINIFS($B$2:$B$633, $L$2:$L$633, L7) -> 44928 | K7: Americas | L7: Canada | M7: Toronto | N7: =_xlfn.TEXTJOIN(" - ", TRUE, K7:M7) -> Americas - Canada - Toronto | O7: Corporate | P7: Distributor | Q7: B. Chen | R7: Laptops | S7: LAP-8555 | T7: 315.87 | U7: 591.68 | V7: =ABS(U7) -> 591.68 | W7: =IF(V7 <= _xlfn.PERCENTILE.INC($V$2:$V$633, 0.33), "Low", IF(V7 <= _xlfn.PERCENTILE.INC($V$2:$V$633, 0.67), "Medium", "High")) -> Low | X7: 0 | Y7: =IF(X7>30%,AVERAGEIF($X$2:$X$633,"<30%"),X7) -> 0 | Z7: =IF(Y7>0.2, "Yes", "No") -> No | AA7: 7 | AB7: =U7*AA7*(1-Y7) -> 4141.76 | AC7: =T7*AA7 -> 2211.09 | AD7: =AB7-AC7 -> 1930.67 | AE7: =IF(AB7=0, 0, AD7 / AB7) -> 0.46614724 | AF7: =MIN(Y7,'Scenario Modeling'!$B$2) -> 0 | AG7: =ROUND(AA7 * (1 + 'Scenario Modeling'!$B$4), 0) -> 7 | AH7: =T7 * (1 + 'Scenario Modeling'!$B$3) -> 315.87 | AI7: =V7 * AG7 * (1 - AF7) -> 4141.76 | AJ7: =AI7 - (AH7 * AG7) -> 1930.67
A8: ORD-2024-336584 | B8: 45653 | C8: 45653 | D8: ="Q"&ROUNDUP(MONTH(B8)/3,0)&"-"&YEAR(B8) -> Q4-2024 | E8: 45671 | F8: 45671 | G8: =E8-B8 -> 18 | H8: =F8-B8 -> 18 | I8: =IF(H8<=7, "Yes", "No") -> No | J8: =_xlfn.MINIFS($B$2:$B$633, $L$2:$L$633, L8) -> 44955 | K8: Asia | L8: India | M8: Bengaluru | N8: =_xlfn.TEXTJOIN(" - ", TRUE, K8:M8) -> Asia - India - Bengaluru | O8: Small Business | P8: Marketplace | Q8: E. Garcia | R8: Monitors | S8: MON-8629 | T8: 586.07 | U8: 845.97 | V8: =ABS(U8) -> 845.97 | W8: =IF(V8 <= _xlfn.PERCENTILE.INC($V$2:$V$633, 0.33), "Low", IF(V8 <= _xlfn.PERCENTILE.INC($V$2:$V$633, 0.67), "Medium", "High")) -> Medium | X8: 0.147 | Y8: =IF(X8>30%,AVERAGEIF($X$2:$X$633,"<30%"),X8) -> 0.147 | Z8: =IF(Y8>0.2, "Yes", "No") -> No | AA8: 4 | AB8: =U8*AA8*(1-Y8) -> 2886.4496 | AC8: =T8*AA8 -> 2344.28 | AD8: =AB8-AC8 -> 542.16964 | AE8: =IF(AB8=0, 0, AD8 / AB8) -> 0.1878327 | AF8: =MIN(Y8,'Scenario Modeling'!$B$2) -> 0.147 | AG8: =ROUND(AA8 * (1 + 'Scenario Modeling'!$B$4), 0) -> 4 | AH8: =T8 * (1 + 'Scenario Modeling'!$B$3) -> 586.07 | AI8: =V8 * AG8 * (1 - AF8) -> 2886.4496 | AJ8: =AI8 - (AH8 * AG8) -> 542.16964
A9: ORD-2023-112666 | B9: 44941 | C9: 44941 | D9: ="Q"&ROUNDUP(MONTH(B9)/3,0)&"-"&YEAR(B9) -> Q1-2023 | E9: 44939 | F9: =B9+3 -> 44944 | G9: =E9-B9 -> -2 | H9: =F9-B9 -> 3 | I9: =IF(H9<=7, "Yes", "No") -> Yes | J9: =_xlfn.MINIFS($B$2:$B$633, $L$2:$L$633, L9) -> 44941 | K9: Africa | L9: Nigeria | M9: Abuja | N9: =_xlfn.TEXTJOIN(" - ", TRUE, K9:M9) -> Africa - Nigeria - Abuja | O9: Education | P9: Online | Q9: O. Wang | R9: Printers | S9: PRN-6276 | T9: 28.38 | U9: 47.22 | V9: =ABS(U9) -> 47.22 | W9: =IF(V9 <= _xlfn.PERCENTILE.INC($V$2:$V$633, 0.33), "Low", IF(V9 <= _xlfn.PERCENTILE.INC($V$2:$V$633, 0.67), "Medium", "High")) -> Low | X9: 0.194 | Y9: =IF(X9>30%,AVERAGEIF($X$2:$X$633,"<30%"),X9) -> 0.194 | Z9: =IF(Y9>0.2, "Yes", "No") -> No | AA9: 18 | AB9: =U9*AA9*(1-Y9) -> 685.06776 | AC9: =T9*AA9 -> 510.84 | AD9: =AB9-AC9 -> 174.22776 | AE9: =IF(AB9=0, 0, AD9 / AB9) -> 0.25432194 | AF9: =MIN(Y9,'Scenario Modeling'!$B$2) -> 0.194 | AG9: =ROUND(AA9 * (1 + 'Scenario Modeling'!$B$4), 0) -> 18 | AH9: =T9 * (1 + 'Scenario Modeling'!$B$3) -> 28.38 | AI9: =V9 * AG9 * (1 - AF9) -> 685.06776 | AJ9: =AI9 - (AH9 * AG9) -> 174.22776
A10: ORD-2024-589570 | B10: 45416 | C10: 45416 | D10: ="Q"&ROUNDUP(MONTH(B10)/3,0)&"-"&YEAR(B10) -> Q2-2024 | E10: 45441 | F10: 45441 | G10: =E10-B10 -> 25 | H10: =F10-B10 -> 25 | I10: =IF(H10<=7, "Yes", "No") -> No | J10: =_xlfn.MINIFS($B$2:$B$633, $L$2:$L$633, L10) -> 44941 | K10: Africa | L10: Nigeria | M10: Abuja | N10: =_xlfn.TEXTJOIN(" - ", TRUE, K10:M10) -> Africa - Nigeria - Abuja | O10: Non-Profit | P10: Marketplace | Q10: O. Wang | R10: Monitors | S10: MON-6892 | T10: 1295.34 | U10: 2530.81 | V10: =ABS(U10) -> 2530.81 | W10: =IF(V10 <= _xlfn.PERCENTILE.INC($V$2:$V$633, 0.33), "Low", IF(V10 <= _xlfn.PERCENTILE.INC($V$2:$V$633, 0.67), "Medium", "High")) -> High | X10: 0.031 | Y10: =IF(X10>30%,AVERAGEIF($X$2:$X$633,"<30%"),X10) -> 0.031 | Z10: =IF(Y10>0.2, "Yes", "No") -> No | AA10: 6 | AB10: =U10*AA10*(1-Y10) -> 14714.129 | AC10: =T10*AA10 -> 7772.04 | AD10: =AB10-AC10 -> 6942.0893 | AE10: =IF(AB10=0, 0, AD10 / AB10) -> 0.47179749 | AF10: =MIN(Y10,'Scenario Modeling'!$B$2) -> 0.031 | AG10: =ROUND(AA10 * (1 + 'Scenario Modeling'!$B$4), 0) -> 6 | AH10: =T10 * (1 + 'Scenario Modeling'!$B$3) -> 1295.34 | AI10: =V10 * AG10 * (1 - AF10) -> 14714.129 | AJ10: =AI10 - (AH10 * AG10) -> 6942.0893
A11: ORD-2025-997421 | B11: 45798 | C11: 45798 | D11: ="Q"&ROUNDUP(MONTH(B11)/3,0)&"-"&YEAR(B11) -> Q2-2025 | E11: 45817 | F11: 45817 | G11: =E11-B11 -> 19 | H11: =F11-B11 -> 19 | I11: =IF(H11<=7, "Yes", "No") -> No | J11: =_xlfn.MINIFS($B$2:$B$633, $L$2:$L$633, L11) -> 44955 | K11: Americas | L11: Brazil | M11: São Paulo | N11: =_xlfn.TEXTJOIN(" - ", TRUE, K11:M11) -> Americas - Brazil - São Paulo | O11: Non-Profit | P11: Online | Q11: A. Patel | R11: Components | S11: CMP-3731 | T11: 1331.38 | U11: 2309.56 | V11: =ABS(U11) -> 2309.56 | W11: =IF(V11 <= _xlfn.PERCENTILE.INC($V$2:$V$633, 0.33), "Low", IF(V11 <= _xlfn.PERCENTILE.INC($V$2:$V$633, 0.67), "Medium", "High")) -> High | X11: 0.149 | Y11: =IF(X11>30%,AVERAGEIF($X$2:$X$633,"<30%"),X11) -> 0.149 | Z11: =IF(Y11>0.2, "Yes", "No") -> No | AA11: 31 | AB11: =U11*AA11*(1-Y11) -> 60928.502 | AC11: =T11*AA11 -> 41272.78 | AD11: =AB11-AC11 -> 19655.722 | AE11: =IF(AB11=0, 0, AD11 / AB11) -> 0.32260308 | AF11: =MIN(Y11,'Scenario Modeling'!$B$2) -> 0.149 | AG11: =ROUND(AA11 * (1 + 'Scenario Modeling'!$B$4), 0) -> 31 | AH11: =T11 * (1 + 'Scenario Modeling'!$B$3) -> 1331.38 | AI11: =V11 * AG11 * (1 - AF11) -> 60928.502 | AJ11: =AI11 - (AH11 * AG11) -> 19655.722
A12: ORD-2024-210687 | B12: 45319 | C12: 45319 | D12: ="Q"&ROUNDUP(MONTH(B12)/3,0)&"-"&YEAR(B12) -> Q1-2024 | E12: 45331 | F12: 45331 | G12: =E12-B12 -> 12 | H12: =F12-B12 -> 12 | I12: =IF(H12<=7, "Yes", "No") -> No | J12: =_xlfn.MINIFS($B$2:$B$633, $L$2:$L$633, L12) -> 44948 | K12: Europe | L12: Germany | M12: Berlin | N12: =_xlfn.TEXTJOIN(" - ", TRUE, K12:M12) -> Europe - Germany - Berlin | O12: Corporate | P12: Online | Q12: G. Dubois | R12: Accessories | S12: ACC-7938 | T12: 644.17 | U12: 700.12 | V12: =ABS(U12) -> 700.12 | W12: =IF(V12 <= _xlfn.PERCENTILE.INC($V$2:$V$633, 0.33), "Low", IF(V12 <= _xlfn.PERCENTILE.INC($V$2:$V$633, 0.67), "Medium", "High")) -> Low | X12: 0.006 | Y12: =IF(X12>30%,AVERAGEIF($X$2:$X$633,"<30%"),X12) -> 0.006 | Z12: =IF(Y12>0.2, "Yes", "No") -> No | AA12: 23 | AB12: =U12*AA12*(1-Y12) -> 16006.143 | AC12: =T12*AA12 -> 14815.91 | AD12: =AB12-AC12 -> 1190.2334 | AE12: =IF(AB12=0, 0, AD12 / AB12) -> 0.074361038 | AF12: =MIN(Y12,'Scenario Modeling'!$B$2) -> 0.006 | AG12: =ROUND(AA12 * (1 + 'Scenario Modeling'!$B$4), 0) -> 23 | AH12: =T12 * (1 + 'Scenario Modeling'!$B$3) -> 644.17 | AI12: =V12 * AG12 * (1 - AF12) -> 16006.143 | AJ12: =AI12 - (AH12 * AG12) -> 1190.2334
A13: ORD-2025-515515 | B13: 45660 | C13: 45660 | D13: ="Q"&ROUNDUP(MONTH(B13)/3,0)&"-"&YEAR(B13) -> Q1-2025 | E13: 45680 | F13: 45680 | G13: =E13-B13 -> 20 | H13: =F13-B13 -> 20 | I13: =IF(H13<=7, "Yes", "No") -> No | J13: =_xlfn.MINIFS($B$2:$B$633, $L$2:$L$633, L13) -> 44988 | K13: Asia | L13: Japan | M13: Osaka | N13: =_xlfn.TEXTJOIN(" - ", TRUE, K13:M13) -> Asia - Japan - Osaka | O13: Corporate | P13: Distributor | Q13: F. Müller | R13: Phones | S13: PHN-7019 | T13: 908.6 | U13: 691.37 | V13: =ABS(U13) -> 691.37 | W13: =IF(V13 <= _xlfn.PERCENTILE.INC($V$2:$V$633, 0.33), "Low", IF(V13 <= _xlfn.PERCENTILE.INC($V$2:$V$633, 0.67), "Medium", "High")) -> Low | X13: 0.25 | Y13: =IF(X13>30%,AVERAGEIF($X$2:$X$633,"<30%"),X13) -> 0.25 | Z13: =IF(Y13>0.2, "Yes", "No") -> Yes | AA13: 20 | AB13: =U13*AA13*(1-Y13) -> 10370.55 | AC13: =T13*AA13 -> 18172 | AD13: =AB13-AC13 -> -7801.45 | AE13: =IF(AB13=0, 0, AD13 / AB13) -> -0.75226965 | AF13: =MIN(Y13,'Scenario Modeling'!$B$2) -> 0.25 | AG13: =ROUND(AA13 * (1 + 'Scenario Modeling'!$B$4), 0) -> 20 | AH13: =T13 * (1 + 'Scenario Modeling'!$B$3) -> 908.6 | AI13: =V13 * AG13 * (1 - AF13) -> 10370.55 | AJ13: =AI13 - (AH13 * AG13) -> -7801.45
A14: ORD-2025-487261 | B14: 45722 | C14: 45722 | D14: ="Q"&ROUNDUP(MONTH(B14)/3,0)&"-"&YEAR(B14) -> Q1-2025 | E14: 45747 | F14: 45747 | G14: =E14-B14 -> 25 | H14: =F14-B14 -> 25 | I14: =IF(H14<=7, "Yes", "No") -> No | J14: =_xlfn.MINIFS($B$2:$B$633, $L$2:$L$633, L14) -> 44955 | K14: Americas | L14: Brazil | M14: Brasília | N14: =_xlfn.TEXTJOIN(" - ", TRUE, K14:M14) -> Americas - Brazil - Brasília | O14: Non-Profit | P14: Online | Q14: J. Njeri | R14: Components | S14: CMP-3693 | T14: 331.57 | U14: 548.4 | V14: =ABS(U14) -> 548.4 | W14: =IF(V14 <= _xlfn.PERCENTILE.INC($V$2:$V$633, 0.33), "Low", IF(V14 <= _xlfn.PERCENTILE.INC($V$2:$V$633, 0.67), "Medium", "High")) -> Low | X14: 0.094 | Y14: =IF(X14>30%,AVERAGEIF($X$2:$X$633,"<30%"),X14) -> 0.094 | Z14: =IF(Y14>0.2, "Yes", "No") -> No | AA14: 10 | AB14: =U14*AA14*(1-Y14) -> 4968.504 | AC14: =T14*AA14 -> 3315.7 | AD14: =AB14-AC14 -> 1652.804 | AE14: =IF(AB14=0, 0, AD14 / AB14) -> 0.33265627 | AF14: =MIN(Y14,'Scenario Modeling'!$B$2) -> 0.094 | AG14: =ROUND(AA14 * (1 + 'Scenario Modeling'!$B$4), 0) -> 10 | AH14: =T14 * (1 + 'Scenario Modeling'!$B$3) -> 331.57 | AI14: =V14 * AG14 * (1 - AF14) -> 4968.504 | AJ14: =AI14 - (AH14 * AG14) -> 1652.804
A15: ORD-2024-890180 | B15: 45311 | C15: 45311 | D15: ="Q"&ROUNDUP(MONTH(B15)/3,0)&"-"&YEAR(B15) -> Q1-2024 | E15: 45335 | F15: 45335 | G15: =E15-B15 -> 24 | H15: =F15-B15 -> 24 | I15: =IF(H15<=7, "Yes", "No") -> No | J15: =_xlfn.MINIFS($B$2:$B$633, $L$2:$L$633, L15) -> 44936 | K15: Europe | L15: France | M15: Marseille | N15: =_xlfn.TEXTJOIN(" - ", TRUE, K15:M15) -> Europe - France - Marseille | O15: Corporate | P15: Retail | Q15: H. Kim | R15: Printers | S15: PRN-8392 | T15: 643.53 | U15: 1439.01 | V15: =ABS(U15) -> 1439.01 | W15: =IF(V15 <= _xlfn.PERCENTILE.INC($V$2:$V$633, 0.33), "Low", IF(V15 <= _xlfn.PERCENTILE.INC($V$2:$V$633, 0.67), "Medium", "High")) -> Medium | X15: 0 | Y15: =IF(X15>30%,AVERAGEIF($X$2:$X$633,"<30%"),X15) -> 0 | Z15: =IF(Y15>0.2, "Yes", "No") -> No | AA15: 15 | AB15: =U15*AA15*(1-Y15) -> 21585.15 | AC15: =T15*AA15 -> 9652.95 | AD15: =AB15-AC15 -> 11932.2 | AE15: =IF(AB15=0, 0, AD15 / AB15) -> 0.55279671 | AF15: =MIN(Y15,'Scenario Modeling'!$B$2) -> 0 | AG15: =ROUND(AA15 * (1 + 'Scenario Modeling'!$B$4), 0) -> 15 | AH15: =T15 * (1 + 'Scenario Modeling'!$B$3) -> 643.53 | AI15: =V15 * AG15 * (1 - AF15) -> 21585.15 | AJ15: =AI15 - (AH15 * AG15) -> 11932.2
A16: ORD-2025-840976 | B16: 45901 | C16: 45901 | D16: ="Q"&ROUNDUP(MONTH(B16)/3,0)&"-"&YEAR(B16) -> Q3-2025 | E16: 45930 | F16: 45930 | G16: =E16-B16 -> 29 | H16: =F16-B16 -> 29 | I16: =IF(H16<=7, "Yes", "No") -> No | J16: =_xlfn.MINIFS($B$2:$B$633, $L$2:$L$633, L16) -> 44955 | K16: Americas | L16: Brazil | M16: Brasília | N16: =_xlfn.TEXTJOIN(" - ", TRUE, K16:M16) -> Americas - Brazil - Brasília | O16: Education | P16: Retail | Q16: K. Singh | R16: Accessories | S16: ACC-1663 | T16: 780.59 | U16: 631.57 | V16: =ABS(U16) -> 631.57 | W16: =IF(V16 <= _xlfn.PERCENTILE.INC($V$2:$V$633, 0.33), "Low", IF(V16 <= _xlfn.PERCENTILE.INC($V$2:$V$633, 0.67), "Medium", "High")) -> Low | X16: 0 | Y16: =IF(X16>30%,AVERAGEIF($X$2:$X$633,"<30%"),X16) -> 0 | Z16: =IF(Y16>0.2, "Yes", "No") -> No | AA16: 12 | AB16: =U16*AA16*(1-Y16) -> 7578.84 | AC16: =T16*AA16 -> 9367.08 | AD16: =AB16-AC16 -> -1788.24 | AE16: =IF(AB16=0, 0, AD16 / AB16) -> -0.23595168 | AF16: =MIN(Y16,'Scenario Modeling'!$B$2) -> 0 | AG16: =ROUND(AA16 * (1 + 'Scenario Modeling'!$B$4), 0) -> 12 | AH16: =T16 * (1 + 'Scenario Modeling'!$B$3) -> 780.59 | AI16: =V16 * AG16 * (1 - AF16) -> 7578.84 | AJ16: =AI16 - (AH16 * AG16) -> -1788.24
A17: ORD-2023-937291 | B17: 45039 | C17: 45039 | D17: ="Q"&ROUNDUP(MONTH(B17)/3,0)&"-"&YEAR(B17) -> Q2-2023 | E17: 45038 | F17: =B17+11 -> 45050 | G17: =E17-B17 -> -1 | H17: =F17-B17 -> 11 | I17: =IF(H17<=7, "Yes", "No") -> No | J17: =_xlfn.MINIFS($B$2:$B$633, $L$2:$L$633, L17) -> 44946 | K17: Africa | L17: Kenya | M17: Nairobi | N17: =_xlfn.TEXTJOIN(" - ", TRUE, K17:M17) -> Africa - Kenya - Nairobi | O17: Small Business | P17: Direct | Q17: E. Garcia | R17: Laptops | S17: LAP-1698 | T17: 756.51 | U17: 850.8 | V17: =ABS(U17) -> 850.8 | W17: =IF(V17 <= _xlfn.PERCENTILE.INC($V$2:$V$633, 0.33), "Low", IF(V17 <= _xlfn.PERCENTILE.INC($V$2:$V$633, 0.67), "Medium", "High")) -> Medium | X17: 0.074 | Y17: =IF(X17>30%,AVERAGEIF($X$2:$X$633,"<30%"),X17) -> 0.074 | Z17: =IF(Y17>0.2, "Yes", "No") -> No | AA17: 9 | AB17: =U17*AA17*(1-Y17) -> 7090.5672 | AC17: =T17*AA17 -> 6808.59 | AD17: =AB17-AC17 -> 281.9772 | AE17: =IF(AB17=0, 0, AD17 / AB17) -> 0.039767933 | AF17: =MIN(Y17,'Scenario Modeling'!$B$2) -> 0.074 | AG17: =ROUND(AA17 * (1 + 'Scenario Modeling'!$B$4), 0) -> 9 | AH17: =T17 * (1 + 'Scenario Modeling'!$B$3) -> 756.51 | AI17: =V17 * AG17 * (1 - AF17) -> 7090.5672 | AJ17: =AI17 - (AH17 * AG17) -> 281.9772
A18: ORD-2024-206081 | B18: 45636 | C18: 45636 | D18: ="Q"&ROUNDUP(MONTH(B18)/3,0)&"-"&YEAR(B18) -> Q4-2024 | E18: 45665 | F18: 45665 | G18: =E18-B18 -> 29 | H18: =F18-B18 -> 29 | I18: =IF(H18<=7, "Yes", "No") -> No | J18: =_xlfn.MINIFS($B$2:$B$633, $L$2:$L$633, L18) -> 44936 | K18: Europe | L18: France | M18: Marseille | N18: =_xlfn.TEXTJOIN(" - ", TRUE, K18:M18) -> Europe - France - Marseille | O18: Small Business | P18: Retail | Q18: K. Singh | R18: Printers | S18: PRN-6791 | T18: 891.08 | U18: 1040.1 | V18: =ABS(U18) -> 1040.1 | W18: =IF(V18 <= _xlfn.PERCENTILE.INC($V$2:$V$633, 0.33), "Low", IF(V18 <= _xlfn.PERCENTILE.INC($V$2:$V$633, 0.67), "Medium", "High")) -> Medium | X18: 0.109 | Y18: =IF(X18>30%,AVERAGEIF($X$2:$X$633,"<30%"),X18) -> 0.109 | Z18: =IF(Y18>0.2, "Yes", "No") -> No | AA18: 28 | AB18: =U18*AA18*(1-Y18) -> 25948.415 | AC18: =T18*AA18 -> 24950.24 | AD18: =AB18-AC18 -> 998.1748 | AE18: =IF(AB18=0, 0, AD18 / AB18) -> 0.03846766 | AF18: =MIN(Y18,'Scenario Modeling'!$B$2) -> 0.109 | AG18: =ROUND(AA18 * (1 + 'Scenario Modeling'!$B$4), 0) -> 28 | AH18: =T18 * (1 + 'Scenario Modeling'!$B$3) -> 891.08 | AI18: =V18 * AG18 * (1 - AF18) -> 25948.415 | AJ18: =AI18 - (AH18 * AG18) -> 998.1748
A19: ORD-2025-233883 | B19: 45908 | C19: 45908 | D19: ="Q"&ROUNDUP(MONTH(B19)/3,0)&"-"&YEAR(B19) -> Q3-2025 | E19: 45916 | F19: 45916 | G19: =E19-B19 -> 8 | H19: =F19-B19 -> 8 | I19: =IF(H19<=7, "Yes", "No") -> No | J19: =_xlfn.MINIFS($B$2:$B$633, $L$2:$L$633, L19) -> 44988 | K19: Asia | L19: Japan | M19: Osaka | N19: =_xlfn.TEXTJOIN(" - ", TRUE, K19:M19) -> Asia - Japan - Osaka | O19: Corporate | P19: Distributor | Q19: C. Otieno | R19: Phones | S19: PHN-1197 | T19: 1225.57 | U19: 2705.57 | V19: =ABS(U19) -> 2705.57 | W19: =IF(V19 <= _xlfn.PERCENTILE.INC($V$2:$V$633, 0.33), "Low", IF(V19 <= _xlfn.PERCENTILE.INC($V$2:$V$633, 0.67), "Medium", "High")) -> High | X19: 0.183 | Y19: =IF(X19>30%,AVERAGEIF($X$2:$X$633,"<30%"),X19) -> 0.183 | Z19: =IF(Y19>0.2, "Yes", "No") -> No | AA19: 16 | AB19: =U19*AA19*(1-Y19) -> 35367.211 | AC19: =T19*AA19 -> 19609.12 | AD19: =AB19-AC19 -> 15758.091 | AE19: =IF(AB19=0, 0, AD19 / AB19) -> 0.44555651 | AF19: =MIN(Y19,'Scenario Modeling'!$B$2) -> 0.183 | AG19: =ROUND(AA19 * (1 + 'Scenario Modeling'!$B$4), 0) -> 16 | AH19: =T19 * (1 + 'Scenario Modeling'!$B$3) -> 1225.57 | AI19: =V19 * AG19 * (1 - AF19) -> 35367.211 | AJ19: =AI19 - (AH19 * AG19) -> 15758.091
A20: ORD-2025-843974 | B20: 45858 | C20: 45858 | D20: ="Q"&ROUNDUP(MONTH(B20)/3,0)&"-"&YEAR(B20) -> Q3-2025 | E20: 45874 | F20: 45874 | G20: =E20-B20 -> 16 | H20: =F20-B20 -> 16 | I20: =IF(H20<=7, "Yes", "No") -> No | J20: =_xlfn.MINIFS($B$2:$B$633, $L$2:$L$633, L20) -> 44955 | K20: Americas | L20: Brazil | M20: Brasília | N20: =_xlfn.TEXTJOIN(" - ", TRUE, K20:M20) -> Americas - Brazil - Brasília | O20: Enterprise | P20: Marketplace | Q20: G. Dubois | R20: Accessories | S20: ACC-8098 | T20: 1068.17 | U20: 2375.37 | V20: =ABS(U20) -> 2375.37 | W20: =IF(V20 <= _xlfn.PERCENTILE.INC($V$2:$V$633, 0.33), "Low", IF(V20 <= _xlfn.PERCENTILE.INC($V$2:$V$633, 0.67), "Medium", "High")) -> High | X20: 0.109 | Y20: =IF(X20>30%,AVERAGEIF($X$2:$X$633,"<30%"),X20) -> 0.109 | Z20: =IF(Y20>0.2, "Yes", "No") -> No | AA20: 18 | AB20: =U20*AA20*(1-Y20) -> 38096.184 | AC20: =T20*AA20 -> 19227.06 | AD20: =AB20-AC20 -> 18869.124 | AE20: =IF(AB20=0, 0, AD20 / AB20) -> 0.49530221 | AF20: =MIN(Y20,'Scenario Modeling'!$B$2) -> 0.109 | AG20: =ROUND(AA20 * (1 + 'Scenario Modeling'!$B$4), 0) -> 18 | AH20: =T20 * (1 + 'Scenario Modeling'!$B$3) -> 1068.17 | AI20: =V20 * AG20 * (1 - AF20) -> 38096.184 | AJ20: =AI20 - (AH20 * AG20) -> 18869.124
A21: ORD-2025-745263 | B21: 45798 | C21: 45798 | D21: ="Q"&ROUNDUP(MONTH(B21)/3,0)&"-"&YEAR(B21) -> Q2-2025 | E21: 45796 | F21: =B21+11 -> 45809 | G21: =E21-B21 -> -2 | H21: =F21-B21 -> 11 | I21: =IF(H21<=7, "Yes", "No") -> No | J21: =_xlfn.MINIFS($B$2:$B$633, $L$2:$L$633, L21) -> 44945 | K21: Europe | L21: United Kingdom | M21: Birmingham | N21: =_xlfn.TEXTJOIN(" - ", TRUE, K21:M21) -> Europe - United Kingdom - Birmingham | O21: Enterprise | P21: Online | Q21: M. Rossi | R21: Laptops | S21: LAP-3385 | T21: 1015.16 | U21: 2148.14 | V21: =ABS(U21) -> 2148.14 | W21: =IF(V21 <= _xlfn.PERCENTILE.INC($V$2:$V$633, 0.33), "Low", IF(V21 <= _xlfn.PERCENTILE.INC($V$2:$V$633, 0.67), "Medium", "High")) -> High | X21: 0.038 | Y21: =IF(X21>30%,AVERAGEIF($X$2:$X$633,"<30%"),X21) -> 0.038 | Z21: =IF(Y21>0.2, "Yes", "No") -> No | AA21: 19 | AB21: =U21*AA21*(1-Y21) -> 39263.703 | AC21: =T21*AA21 -> 19288.04 | AD21: =AB21-AC21 -> 19975.663 | AE21: =IF(AB21=0, 0, AD21 / AB21) -> 0.50875647 | AF21: =MIN(Y21,'Scenario Modeling'!$B$2) -> 0.038 | AG21: =ROUND(AA21 * (1 + 'Scenario Modeling'!$B$4), 0) -> 19 | AH21: =T21 * (1 + 'Scenario Modeling'!$B$3) -> 1015.16 | AI21: =V21 * AG21 * (1 - AF21) -> 39263.703 | AJ21: =AI21 - (AH21 * AG21) -> 19975.663
A22: ORD-2024-798002 | B22: 45498 | C22: 45498 | D22: ="Q"&ROUNDUP(MONTH(B22)/3,0)&"-"&YEAR(B22) -> Q3-2024 | E22: 45497 | F22: =B22+11 -> 45509 | G22: =E22-B22 -> -1 | H22: =F22-B22 -> 11 | I22: =IF(H22<=7, "Yes", "No") -> No | J22: =_xlfn.MINIFS($B$2:$B$633, $L$2:$L$633, L22) -> 44946 | K22: Africa | L22: Kenya | M22: Mombasa | N22: =_xlfn.TEXTJOIN(" - ", TRUE, K22:M22) -> Africa - Kenya - Mombasa | O22: Non-Profit | P22: Direct | Q22: J. Njeri | R22: Laptops | S22: LAP-9815 | T22: 1494.4 | U22: 3661.07 | V22: =ABS(U22) -> 3661.07 | W22: =IF(V22 <= _xlfn.PERCENTILE.INC($V$2:$V$633, 0.33), "Low", IF(V22 <= _xlfn.PERCENTILE.INC($V$2:$V$633, 0.67), "Medium", "High")) -> High | X22: 0.072 | Y22: =IF(X22>30%,AVERAGEIF($X$2:$X$633,"<30%"),X22) -> 0.072 | Z22: =IF(Y22>0.2, "Yes", "No") -> No | AA22: 7 | AB22: =U22*AA22*(1-Y22) -> 23782.311 | AC22: =T22*AA22 -> 10460.8 | AD22: =AB22-AC22 -> 13321.511 | AE22: =IF(AB22=0, 0, AD22 / AB22) -> 0.56014367 | AF22: =MIN(Y22,'Scenario Modeling'!$B$2) -> 0.072 | AG22: =ROUND(AA22 * (1 + 'Scenario Modeling'!$B$4), 0) -> 7 | AH22: =T22 * (1 + 'Scenario Modeling'!$B$3) -> 1494.4 | AI22: =V22 * AG22 * (1 - AF22) -> 23782.311 | AJ22: =AI22 - (AH22 * AG22) -> 13321.511
A23: ORD-2023-867836 | B23: 45057 | C23: 45057 | D23: ="Q"&ROUNDUP(MONTH(B23)/3,0)&"-"&YEAR(B23) -> Q2-2023 | E23: 45074 | F23: 45074 | G23: =E23-B23 -> 17 | H23: =F23-B23 -> 17 | I23: =IF(H23<=7, "Yes", "No") -> No | J23: =_xlfn.MINIFS($B$2:$B$633, $L$2:$L$633, L23) -> 44938 | K23: Asia | L23: China | M23: Shenzhen | N23: =_xlfn.TEXTJOIN(" - ", TRUE, K23:M23) -> Asia - China - Shenzhen | O23: Enterprise | P23: Marketplace | Q23: E. Garcia | R23: Networking | S23: NET-3255 | T23: 1331.19 | U23: 2903.09 | V23: =ABS(U23) -> 2903.09 | W23: =IF(V23 <= _xlfn.PERCENTILE.INC($V$2:$V$633, 0.33), "Low", IF(V23 <= _xlfn.PERCENTILE.INC($V$2:$V$633, 0.67), "Medium", "High")) -> High | X23: 0.143 | Y23: =IF(X23>30%,AVERAGEIF($X$2:$X$633,"<30%"),X23) -> 0.143 | Z23: =IF(Y23>0.2, "Yes", "No") -> No | AA23: 8 | AB23: =U23*AA23*(1-Y23) -> 19903.585 | AC23: =T23*AA23 -> 10649.52 | AD23: =AB23-AC23 -> 9254.065 | AE23: =IF(AB23=0, 0, AD23 / AB23) -> 0.46494463 | AF23: =MIN(Y23,'Scenario Modeling'!$B$2) -> 0.143 | AG23: =ROUND(AA23 * (1 + 'Scenario Modeling'!$B$4), 0) -> 8 | AH23: =T23 * (1 + 'Scenario Modeling'!$B$3) -> 1331.19 | AI23: =V23 * AG23 * (1 - AF23) -> 19903.585 | AJ23: =AI23 - (AH23 * AG23) -> 9254.065
A24: ORD-2025-580047 | B24: 45822 | C24: 45822 | D24: ="Q"&ROUNDUP(MONTH(B24)/3,0)&"-"&YEAR(B24) -> Q2-2025 | E24: 45837 | F24: 45837 | G24: =E24-B24 -> 15 | H24: =F24-B24 -> 15 | I24: =IF(H24<=7, "Yes", "No") -> No | J24: =_xlfn.MINIFS($B$2:$B$633, $L$2:$L$633, L24) -> 44941 | K24: Africa | L24: Nigeria | M24: Port Harcourt | N24: =_xlfn.TEXTJOIN(" - ", TRUE, K24:M24) -> Africa - Nigeria - Port Harcourt | O24: Consumer | P24: Marketplace | Q24: M. Rossi | R24: Accessories | S24: ACC-3961 | T24: 730.99 | U24: 1242.84 | V24: =ABS(U24) -> 1242.84 | W24: =IF(V24 <= _xlfn.PERCENTILE.INC($V$2:$V$633, 0.33), "Low", IF(V24 <= _xlfn.PERCENTILE.INC($V$2:$V$633, 0.67), "Medium", "High")) -> Medium | X24: 0.12 | Y24: =IF(X24>30%,AVERAGEIF($X$2:$X$633,"<30%"),X24) -> 0.12 | Z24: =IF(Y24>0.2, "Yes", "No") -> No | AA24: 10 | AB24: =U24*AA24*(1-Y24) -> 10936.992 | AC24: =T24*AA24 -> 7309.9 | AD24: =AB24-AC24 -> 3627.092 | AE24: =IF(AB24=0, 0, AD24 / AB24) -> 0.33163524 | AF24: =MIN(Y24,'Scenario Modeling'!$B$2) -> 0.12 | AG24: =ROUND(AA24 * (1 + 'Scenario Modeling'!$B$4), 0) -> 10 | AH24: =T24 * (1 + 'Scenario Modeling'!$B$3) -> 730.99 | AI24: =V24 * AG24 * (1 - AF24) -> 10936.992 | AJ24: =AI24 - (AH24 * AG24) -> 3627.092
A25: ORD-2024-500109 | B25: 45430 | C25: 45430 | D25: ="Q"&ROUNDUP(MONTH(B25)/3,0)&"-"&YEAR(B25) -> Q2-2024 | E25: 45435 | F25: 45435 | G25: =E25-B25 -> 5 | H25: =F25-B25 -> 5 | I25: =IF(H25<=7, "Yes", "No") -> Yes | J25: =_xlfn.MINIFS($B$2:$B$633, $L$2:$L$633, L25) -> 44939 | K25: Americas | L25: USA | M25: Chicago | N25: =_xlfn.TEXTJOIN(" - ", TRUE, K25:M25) -> Americas - USA - Chicago | O25: Enterprise | P25: Retail | Q25: H. Kim | R25: Laptops | S25: LAP-4987 | T25: 1274.59 | U25: 2553.69 | V25: =ABS(U25) -> 2553.69 | W25: =IF(V25 <= _xlfn.PERCENTILE.INC($V$2:$V$633, 0.33), "Low", IF(V25 <= _xlfn.PERCENTILE.INC($V$2:$V$633, 0.67), "Medium", "High")) -> High | X25: 0.01 | Y25: =IF(X25>30%,AVERAGEIF($X$2:$X$633,"<30%"),X25) -> 0.01 | Z25: =IF(Y25>0.2, "Yes", "No") -> No | AA25: 8 | AB25: =U25*AA25*(1-Y25) -> 20225.225 | AC25: =T25*AA25 -> 10196.72 | AD25: =AB25-AC25 -> 10028.505 | AE25: =IF(AB25=0, 0, AD25 / AB25) -> 0.49584145 | AF25: =MIN(Y25,'Scenario Modeling'!$B$2) -> 0.01 | AG25: =ROUND(AA25 * (1 + 'Scenario Modeling'!$B$4), 0) -> 8 | AH25: =T25 * (1 + 'Scenario Modeling'!$B$3) -> 1274.59 | AI25: =V25 * AG25 * (1 - AF25) -> 20225.225 | AJ25: =AI25 - (AH25 * AG25) -> 10028.505
A26: ORD-2023-271836 | B26: 44964 | C26: 44964 | D26: ="Q"&ROUNDUP(MONTH(B26)/3,0)&"-"&YEAR(B26) -> Q1-2023 | E26: 44969 | F26: 44969 | G26: =E26-B26 -> 5 | H26: =F26-B26 -> 5 | I26: =IF(H26<=7, "Yes", "No") -> Yes | J26: =_xlfn.MINIFS($B$2:$B$633, $L$2:$L$633, L26) -> 44955 | K26: Americas | L26: Brazil | M26: São Paulo | N26: =_xlfn.TEXTJOIN(" - ", TRUE, K26:M26) -> Americas - Brazil - São Paulo | O26: Education | P26: Online | Q26: N. Brown | R26: Components | S26: CMP-2693 | T26: 948.55 | U26: 2089.16 | V26: =ABS(U26) -> 2089.16 | W26: =IF(V26 <= _xlfn.PERCENTILE.INC($V$2:$V$633, 0.33), "Low", IF(V26 <= _xlfn.PERCENTILE.INC($V$2:$V$633, 0.67), "Medium", "High")) -> High | X26: 0.007 | Y26: =IF(X26>30%,AVERAGEIF($X$2:$X$633,"<30%"),X26) -> 0.007 | Z26: =IF(Y26>0.2, "Yes", "No") -> No | AA26: 12 | AB26: =U26*AA26*(1-Y26) -> 24894.431 | AC26: =T26*AA26 -> 11382.6 | AD26: =AB26-AC26 -> 13511.831 | AE26: =IF(AB26=0, 0, AD26 / AB26) -> 0.5427652 | AF26: =MIN(Y26,'Scenario Modeling'!$B$2) -> 0.007 | AG26: =ROUND(AA26 * (1 + 'Scenario Modeling'!$B$4), 0) -> 12 | AH26: =T26 * (1 + 'Scenario Modeling'!$B$3) -> 948.55 | AI26: =V26 * AG26 * (1 - AF26) -> 24894.431 | AJ26: =AI26 - (AH26 * AG26) -> 13511.831
A27: ORD-2024-215294 | B27: 45473 | C27: 45473 | D27: ="Q"&ROUNDUP(MONTH(B27)/3,0)&"-"&YEAR(B27) -> Q2-2024 | E27: 45487 | F27: 45487 | G27: =E27-B27 -> 14 | H27: =F27-B27 -> 14 | I27: =IF(H27<=7, "Yes", "No") -> No | J27: =_xlfn.MINIFS($B$2:$B$633, $L$2:$L$633, L27) -> 44955 | K27: Americas | L27: Brazil | M27: Brasília | N27: =_xlfn.TEXTJOIN(" - ", TRUE, K27:M27) -> Americas - Brazil - Brasília | O27: Education | P27: Retail | Q27: C. Otieno | R27: Accessories | S27: ACC-8683 | T27: 1491.85 | U27: 2583.02 | V27: =ABS(U27) -> 2583.02 | W27: =IF(V27 <= _xlfn.PERCENTILE.INC($V$2:$V$633, 0.33), "Low", IF(V27 <= _xlfn.PERCENTILE.INC($V$2:$V$633, 0.67), "Medium", "High")) -> High | X27: 0.168 | Y27: =IF(X27>30%,AVERAGEIF($X$2:$X$633,"<30%"),X27) -> 0.168 | Z27: =IF(Y27>0.2, "Yes", "No") -> No | AA27: 4 | AB27: =U27*AA27*(1-Y27) -> 8596.2906 | AC27: =T27*AA27 -> 5967.4 | AD27: =AB27-AC27 -> 2628.8906 | AE27: =IF(AB27=0, 0, AD27 / AB27) -> 0.30581686 | AF27: =MIN(Y27,'Scenario Modeling'!$B$2) -> 0.168 | AG27: =ROUND(AA27 * (1 + 'Scenario Modeling'!$B$4), 0) -> 4 | AH27: =T27 * (1 + 'Scenario Modeling'!$B$3) -> 1491.85 | AI27: =V27 * AG27 * (1 - AF27) -> 8596.2906 | AJ27: =AI27 - (AH27 * AG27) -> 2628.8906
A28: ORD-2024-788105 | B28: 45626 | C28: 45626 | D28: ="Q"&ROUNDUP(MONTH(B28)/3,0)&"-"&YEAR(B28) -> Q4-2024 | E28: 45656 | F28: 45656 | G28: =E28-B28 -> 30 | H28: =F28-B28 -> 30 | I28: =IF(H28<=7, "Yes", "No") -> No | J28: =_xlfn.MINIFS($B$2:$B$633, $L$2:$L$633, L28) -> 44936 | K28: Europe | L28: France | M28: Marseille | N28: =_xlfn.TEXTJOIN(" - ", TRUE, K28:M28) -> Europe - France - Marseille | O28: Consumer | P28: Marketplace | Q28: F. Müller | R28: Printers | S28: PRN-4170 | T28: 117.64 | U28: 175.67 | V28: =ABS(U28) -> 175.67 | W28: =IF(V28 <= _xlfn.PERCENTILE.INC($V$2:$V$633, 0.33), "Low", IF(V28 <= _xlfn.PERCENTILE.INC($V$2:$V$633, 0.67), "Medium", "High")) -> Low | X28: 0 | Y28: =IF(X28>30%,AVERAGEIF($X$2:$X$633,"<30%"),X28) -> 0 | Z28: =IF(Y28>0.2, "Yes", "No") -> No | AA28: 10 | AB28: =U28*AA28*(1-Y28) -> 1756.7 | AC28: =T28*AA28 -> 1176.4 | AD28: =AB28-AC28 -> 580.3 | AE28: =IF(AB28=0, 0, AD28 / AB28) -> 0.33033529 | AF28: =MIN(Y28,'Scenario Modeling'!$B$2) -> 0 | AG28: =ROUND(AA28 * (1 + 'Scenario Modeling'!$B$4), 0) -> 10 | AH28: =T28 * (1 + 'Scenario Modeling'!$B$3) -> 117.64 | AI28: =V28 * AG28 * (1 - AF28) -> 1756.7 | AJ28: =AI28 - (AH28 * AG28) -> 580.3
A29: ORD-2024-855073 | B29: 45492 | C29: 45492 | D29: ="Q"&ROUNDUP(MONTH(B29)/3,0)&"-"&YEAR(B29) -> Q3-2024 | E29: 45492 | F29: 45492 | G29: =E29-B29 -> 0 | H29: =F29-B29 -> 0 | I29: =IF(H29<=7, "Yes", "No") -> Yes | J29: =_xlfn.MINIFS($B$2:$B$633, $L$2:$L$633, L29) -> 44946 | K29: Africa | L29: Kenya | M29: Kisumu | N29: =_xlfn.TEXTJOIN(" - ", TRUE, K29:M29) -> Africa - Kenya - Kisumu | O29: Small Business | P29: Retail | Q29: A. Patel | R29: Phones | S29: PHN-6854 | T29: 857.24 | U29: 758.23 | V29: =ABS(U29) -> 758.23 | W29: =IF(V29 <= _xlfn.PERCENTILE.INC($V$2:$V$633, 0.33), "Low", IF(V29 <= _xlfn.PERCENTILE.INC($V$2:$V$633, 0.67), "Medium", "High")) -> Low | X29: 0.125 | Y29: =IF(X29>30%,AVERAGEIF($X$2:$X$633,"<30%"),X29) -> 0.125 | Z29: =IF(Y29>0.2, "Yes", "No") -> No | AA29: 6 | AB29: =U29*AA29*(1-Y29) -> 3980.7075 | AC29: =T29*AA29 -> 5143.44 | AD29: =AB29-AC29 -> -1162.7325 | AE29: =IF(AB29=0, 0, AD29 / AB29) -> -0.29209192 | AF29: =MIN(Y29,'Scenario Modeling'!$B$2) -> 0.125 | AG29: =ROUND(AA29 * (1 + 'Scenario Modeling'!$B$4), 0) -> 6 | AH29: =T29 * (1 + 'Scenario Modeling'!$B$3) -> 857.24 | AI29: =V29 * AG29 * (1 - AF29) -> 3980.7075 | AJ29: =AI29 - (AH29 * AG29) -> -1162.7325
A30: ORD-2023-897079 | B30: 45030 | C30: 45030 | D30: ="Q"&ROUNDUP(MONTH(B30)/3,0)&"-"&YEAR(B30) -> Q2-2023 | E30: 45060 | F30: 45060 | G30: =E30-B30 -> 30 | H30: =F30-B30 -> 30 | I30: =IF(H30<=7, "Yes", "No") -> No | J30: =_xlfn.MINIFS($B$2:$B$633, $L$2:$L$633, L30) -> 44946 | K30: Africa | L30: Kenya | M30: Nakuru | N30: =_xlfn.TEXTJOIN(" - ", TRUE, K30:M30) -> Africa - Kenya - Nakuru | O30: Consumer | P30: Marketplace | Q30: M. Rossi | R30: Phones | S30: PHN-1784 | T30: 209.25 | U30: 434.8 | V30: =ABS(U30) -> 434.8 | W30: =IF(V30 <= _xlfn.PERCENTILE.INC($V$2:$V$633, 0.33), "Low", IF(V30 <= _xlfn.PERCENTILE.INC($V$2:$V$633, 0.67), "Medium", "High")) -> Low | X30: 0 | Y30: =IF(X30>30%,AVERAGEIF($X$2:$X$633,"<30%"),X30) -> 0 | Z30: =IF(Y30>0.2, "Yes", "No") -> No | AA30: 9 | AB30: =U30*AA30*(1-Y30) -> 3913.2 | AC30: =T30*AA30 -> 1883.25 | AD30: =AB30-AC30 -> 2029.95 | AE30: =IF(AB30=0, 0, AD30 / AB30) -> 0.51874425 | AF30: =MIN(Y30,'Scenario Modeling'!$B$2) -> 0 | AG30: =ROUND(AA30 * (1 + 'Scenario Modeling'!$B$4), 0) -> 9 | AH30: =T30 * (1 + 'Scenario Modeling'!$B$3) -> 209.25 | AI30: =V30 * AG30 * (1 - AF30) -> 3913.2 | AJ30: =AI30 - (AH30 * AG30) -> 2029.95
A31: ORD-2025-548982 | B31: 45754 | C31: 45754 | D31: ="Q"&ROUNDUP(MONTH(B31)/3,0)&"-"&YEAR(B31) -> Q2-2025 | E31: 45758 | F31: 45758 | G31: =E31-B31 -> 4 | H31: =F31-B31 -> 4 | I31: =IF(H31<=7, "Yes", "No") -> Yes | J31: =_xlfn.MINIFS($B$2:$B$633, $L$2:$L$633, L31) -> 44936 | K31: Europe | L31: France | M31: Lyon | N31: =_xlfn.TEXTJOIN(" - ", TRUE, K31:M31) -> Europe - France - Lyon | O31: Education | P31: Retail | Q31: E. Garcia | R31: Networking | S31: NET-9716 | T31: 754.77 | U31: 1666.18 | V31: =ABS(U31) -> 1666.18 | W31: =IF(V31 <= _xlfn.PERCENTILE.INC($V$2:$V$633, 0.33), "Low", IF(V31 <= _xlfn.PERCENTILE.INC($V$2:$V$633, 0.67), "Medium", "High")) -> High | X31: 0.139 | Y31: =IF(X31>30%,AVERAGEIF($X$2:$X$633,"<30%"),X31) -> 0.139 | Z31: =IF(Y31>0.2, "Yes", "No") -> No | AA31: 14 | AB31: =U31*AA31*(1-Y31) -> 20084.134 | AC31: =T31*AA31 -> 10566.78 | AD31: =AB31-AC31 -> 9517.3537 | AE31: =IF(AB31=0, 0, AD31 / AB31) -> 0.47387425 | AF31: =MIN(Y31,'Scenario Modeling'!$B$2) -> 0.139 | AG31: =ROUND(AA31 * (1 + 'Scenario Modeling'!$B$4), 0) -> 14 | AH31: =T31 * (1 + 'Scenario Modeling'!$B$3) -> 754.77 | AI31: =V31 * AG31 * (1 - AF31) -> 20084.134 | AJ31: =AI31 - (AH31 * AG31) -> 9517.3537
A32: ORD-2024-170313 | B32: 45653 | C32: 45653 | D32: ="Q"&ROUNDUP(MONTH(B32)/3,0)&"-"&YEAR(B32) -> Q4-2024 | E32: 45672 | F32: 45672 | G32: =E32-B32 -> 19 | H32: =F32-B32 -> 19 | I32: =IF(H32<=7, "Yes", "No") -> No | J32: =_xlfn.MINIFS($B$2:$B$633, $L$2:$L$633, L32) -> 44955 | K32: Asia | L32: India | M32: Delhi | N32: =_xlfn.TEXTJOIN(" - ", TRUE, K32:M32) -> Asia - India - Delhi | O32: Non-Profit | P32: Distributor | Q32: G. Dubois | R32: Components | S32: CMP-6919 | T32: 495.59 | U32: 631.78 | V32: =ABS(U32) -> 631.78 | W32: =IF(V32 <= _xlfn.PERCENTILE.INC($V$2:$V$633, 0.33), "Low", IF(V32 <= _xlfn.PERCENTILE.INC($V$2:$V$633, 0.67), "Medium", "High")) -> Low | X32: 0.087 | Y32: =IF(X32>30%,AVERAGEIF($X$2:$X$633,"<30%"),X32) -> 0.087 | Z32: =IF(Y32>0.2, "Yes", "No") -> No | AA32: 17 | AB32: =U32*AA32*(1-Y32) -> 9805.8574 | AC32: =T32*AA32 -> 8425.03 | AD32: =AB32-AC32 -> 1380.8274 | AE32: =IF(AB32=0, 0, AD32 / AB32) -> 0.14081659 | AF32: =MIN(Y32,'Scenario Modeling'!$B$2) -> 0.087 | AG32: =ROUND(AA32 * (1 + 'Scenario Modeling'!$B$4), 0) -> 17 | AH32: =T32 * (1 + 'Scenario Modeling'!$B$3) -> 495.59 | AI32: =V32 * AG32 * (1 - AF32) -> 9805.8574 | AJ32: =AI32 - (AH32 * AG32) -> 1380.8274
A33: ORD-2023-562894 | B33: 44980 | C33: 44980 | D33: ="Q"&ROUNDUP(MONTH(B33)/3,0)&"-"&YEAR(B33) -> Q1-2023 | E33: 45010 | F33: 45010 | G33: =E33-B33 -> 30 | H33: =F33-B33 -> 30 | I33: =IF(H33<=7, "Yes", "No") -> No | J33: =_xlfn.MINIFS($B$2:$B$633, $L$2:$L$633, L33) -> 44928 | K33: Americas | L33: Canada | M33: Montreal | N33: =_xlfn.TEXTJOIN(" - ", TRUE, K33:M33) -> Americas - Canada - Montreal | O33: Enterprise | P33: Online | Q33: D. Smith | R33: Phones | S33: PHN-4854 | T33: 1242.66 | U33: 1794.07 | V33: =ABS(U33) -> 1794.07 | W33: =IF(V33 <= _xlfn.PERCENTILE.INC($V$2:$V$633, 0.33), "Low", IF(V33 <= _xlfn.PERCENTILE.INC($V$2:$V$633, 0.67), "Medium", "High")) -> High | X33: 0.089 | Y33: =IF(X33>30%,AVERAGEIF($X$2:$X$633,"<30%"),X33) -> 0.089 | Z33: =IF(Y33>0.2, "Yes", "No") -> No | AA33: 16 | AB33: =U33*AA33*(1-Y33) -> 26150.364 | AC33: =T33*AA33 -> 19882.56 | AD33: =AB33-AC33 -> 6267.8043 | AE33: =IF(AB33=0, 0, AD33 / AB33) -> 0.23968325 | AF33: =MIN(Y33,'Scenario Modeling'!$B$2) -> 0.089 | AG33: =ROUND(AA33 * (1 + 'Scenario Modeling'!$B$4), 0) -> 16 | AH33: =T33 * (1 + 'Scenario Modeling'!$B$3) -> 1242.66 | AI33: =V33 * AG33 * (1 - AF33) -> 26150.364 | AJ33: =AI33 - (AH33 * AG33) -> 6267.8043
A34: ORD-2025-474710 | B34: 45862 | C34: 45862 | D34: ="Q"&ROUNDUP(MONTH(B34)/3,0)&"-"&YEAR(B34) -> Q3-2025 | E34: 45875 | F34: 45875 | G34: =E34-B34 -> 13 | H34: =F34-B34 -> 13 | I34: =IF(H34<=7, "Yes", "No") -> No | J34: =_xlfn.MINIFS($B$2:$B$633, $L$2:$L$633, L34) -> 44933 | K34: Africa | L34: South Africa | M34: Johannesburg | N34: =_xlfn.TEXTJOIN(" - ", TRUE, K34:M34) -> Africa - South Africa - Johannesburg | O34: Education | P34: Marketplace | Q34: D. Smith | R34: Networking | S34: NET-7966 | T34: 1463.9 | U34: 2633.02 | V34: =ABS(U34) -> 2633.02 | W34: =IF(V34 <= _xlfn.PERCENTILE.INC($V$2:$V$633, 0.33), "Low", IF(V34 <= _xlfn.PERCENTILE.INC($V$2:$V$633, 0.67), "Medium", "High")) -> High | X34: 0.084 | Y34: =IF(X34>30%,AVERAGEIF($X$2:$X$633,"<30%"),X34) -> 0.084 | Z34: =IF(Y34>0.2, "Yes", "No") -> No | AA34: 4 | AB34: =U34*AA34*(1-Y34) -> 9647.3853 | AC34: =T34*AA34 -> 5855.6 | AD34: =AB34-AC34 -> 3791.7853 | AE34: =IF(AB34=0, 0, AD34 / AB34) -> 0.39303761 | AF34: =MIN(Y34,'Scenario Modeling'!$B$2) -> 0.084 | AG34: =ROUND(AA34 * (1 + 'Scenario Modeling'!$B$4), 0) -> 4 | AH34: =T34 * (1 + 'Scenario Modeling'!$B$3) -> 1463.9 | AI34: =V34 * AG34 * (1 - AF34) -> 9647.3853 | AJ34: =AI34 - (AH34 * AG34) -> 3791.7853
A35: ORD-2024-629525 | B35: 45400 | C35: 45400 | D35: ="Q"&ROUNDUP(MONTH(B35)/3,0)&"-"&YEAR(B35) -> Q2-2024 | E35: 45420 | F35: 45420 | G35: =E35-B35 -> 20 | H35: =F35-B35 -> 20 | I35: =IF(H35<=7, "Yes", "No") -> No | J35: =_xlfn.MINIFS($B$2:$B$633, $L$2:$L$633, L35) -> 44945 | K35: Europe | L35: United Kingdom | M35: London | N35: =_xlfn.TEXTJOIN(" - ", TRUE, K35:M35) -> Europe - United Kingdom - London | O35: Non-Profit | P35: Direct | Q35: D. Smith | R35: Laptops | S35: LAP-9932 | T35: 645.33 | U35: 1321.85 | V35: =ABS(U35) -> 1321.85 | W35: =IF(V35 <= _xlfn.PERCENTILE.INC($V$2:$V$633, 0.33), "Low", IF(V35 <= _xlfn.PERCENTILE.INC($V$2:$V$633, 0.67), "Medium", "High")) -> Medium | X35: 0 | Y35: =IF(X35>30%,AVERAGEIF($X$2:$X$633,"<30%"),X35) -> 0 | Z35: =IF(Y35>0.2, "Yes", "No") -> No | AA35: 10 | AB35: =U35*AA35*(1-Y35) -> 13218.5 | AC35: =T35*AA35 -> 6453.3 | AD35: =AB35-AC35 -> 6765.2 | AE35: =IF(AB35=0, 0, AD35 / AB35) -> 0.51179786 | AF35: =MIN(Y35,'Scenario Modeling'!$B$2) -> 0 | AG35: =ROUND(AA35 * (1 + 'Scenario Modeling'!$B$4), 0) -> 10 | AH35: =T35 * (1 + 'Scenario Modeling'!$B$3) -> 645.33 | AI35: =V35 * AG35 * (1 - AF35) -> 13218.5 | AJ35: =AI35 - (AH35 * AG35) -> 6765.2
A36: ORD-2024-167215 | B36: 45527 | C36: 45527 | D36: ="Q"&ROUNDUP(MONTH(B36)/3,0)&"-"&YEAR(B36) -> Q3-2024 | E36: 45525 | F36: =B36+13 -> 45540 | G36: =E36-B36 -> -2 | H36: =F36-B36 -> 13 | I36: =IF(H36<=7, "Yes", "No") -> No | J36: =_xlfn.MINIFS($B$2:$B$633, $L$2:$L$633, L36) -> 44933 | K36: Africa | L36: South Africa | M36: Johannesburg | N36: =_xlfn.TEXTJOIN(" - ", TRUE, K36:M36) -> Africa - South Africa - Johannesburg | O36: Education | P36: Retail | Q36: E. Garcia | R36: Components | S36: CMP-1559 | T36: 1432.52 | U36: 3036.87 | V36: =ABS(U36) -> 3036.87 | W36: =IF(V36 <= _xlfn.PERCENTILE.INC($V$2:$V$633, 0.33), "Low", IF(V36 <= _xlfn.PERCENTILE.INC($V$2:$V$633, 0.67), "Medium", "High")) -> High | X36: 0 | Y36: =IF(X36>30%,AVERAGEIF($X$2:$X$633,"<30%"),X36) -> 0 | Z36: =IF(Y36>0.2, "Yes", "No") -> No | AA36: 9 | AB36: =U36*AA36*(1-Y36) -> 27331.83 | AC36: =T36*AA36 -> 12892.68 | AD36: =AB36-AC36 -> 14439.15 | AE36: =IF(AB36=0, 0, AD36 / AB36) -> 0.52829064 | AF36: =MIN(Y36,'Scenario Modeling'!$B$2) -> 0 | AG36: =ROUND(AA36 * (1 + 'Scenario Modeling'!$B$4), 0) -> 9 | AH36: =T36 * (1 + 'Scenario Modeling'!$B$3) -> 1432.52 | AI36: =V36 * AG36 * (1 - AF36) -> 27331.83 | AJ36: =AI36 - (AH36 * AG36) -> 14439.15
A37: ORD-2023-864121 | B37: 45012 | C37: 45012 | D37: ="Q"&ROUNDUP(MONTH(B37)/3,0)&"-"&YEAR(B37) -> Q1-2023 | E37: 45038 | F37: 45038 | G37: =E37-B37 -> 26 | H37: =F37-B37 -> 26 | I37: =IF(H37<=7, "Yes", "No") -> No | J37: =_xlfn.MINIFS($B$2:$B$633, $L$2:$L$633, L37) -> 44955 | K37: Asia | L37: India | M37: Delhi | N37: =_xlfn.TEXTJOIN(" - ", TRUE, K37:M37) -> Asia - India - Delhi | O37: Non-Profit | P37: Marketplace | Q37: J. Njeri | R37: Printers | S37: PRN-4506 | T37: 178.53 | U37: 199.37 | V37: =ABS(U37) -> 199.37 | W37: =IF(V37 <= _xlfn.PERCENTILE.INC($V$2:$V$633, 0.33), "Low", IF(V37 <= _xlfn.PERCENTILE.INC($V$2:$V$633, 0.67), "Medium", "High")) -> Low | X37: 0.101 | Y37: =IF(X37>30%,AVERAGEIF($X$2:$X$633,"<30%"),X37) -> 0.101 | Z37: =IF(Y37>0.2, "Yes", "No") -> No | AA37: 37 | AB37: =U37*AA37*(1-Y37) -> 6631.6443 | AC37: =T37*AA37 -> 6605.61 | AD37: =AB37-AC37 -> 26.03431 | AE37: =IF(AB37=0, 0, AD37 / AB37) -> 0.00392577 | AF37: =MIN(Y37,'Scenario Modeling'!$B$2) -> 0.101 | AG37: =ROUND(AA37 * (1 + 'Scenario Modeling'!$B$4), 0) -> 37 | AH37: =T37 * (1 + 'Scenario Modeling'!$B$3) -> 178.53 | AI37: =V37 * AG37 * (1 - AF37) -> 6631.6443 | AJ37: =AI37 - (AH37 * AG37) -> 26.03431
A38: ORD-2024-692673 | B38: 45358 | C38: 45358 | D38: ="Q"&ROUNDUP(MONTH(B38)/3,0)&"-"&YEAR(B38) -> Q1-2024 | E38: 45376 | F38: 45376 | G38: =E38-B38 -> 18 | H38: =F38-B38 -> 18 | I38: =IF(H38<=7, "Yes", "No") -> No | J38: =_xlfn.MINIFS($B$2:$B$633, $L$2:$L$633, L38) -> 44948 | K38: Europe | L38: Germany | M38: Munich | N38: =_xlfn.TEXTJOIN(" - ", TRUE, K38:M38) -> Europe - Germany - Munich | O38: Corporate | P38: Online | Q38: B. Chen | R38: Components | S38: CMP-7617 | T38: 712.84 | U38: 927.51 | V38: =ABS(U38) -> 927.51 | W38: =IF(V38 <= _xlfn.PERCENTILE.INC($V$2:$V$633, 0.33), "Low", IF(V38 <= _xlfn.PERCENTILE.INC($V$2:$V$633, 0.67), "Medium", "High")) -> Medium | X38: 0.243 | Y38: =IF(X38>30%,AVERAGEIF($X$2:$X$633,"<30%"),X38) -> 0.243 | Z38: =IF(Y38>0.2, "Yes", "No") -> Yes | AA38: 27 | AB38: =U38*AA38*(1-Y38) -> 18957.377 | AC38: =T38*AA38 -> 19246.68 | AD38: =AB38-AC38 -> -289.30311 | AE38: =IF(AB38=0, 0, AD38 / AB38) -> -0.015260714 | AF38: =MIN(Y38,'Scenario Modeling'!$B$2) -> 0.243 | AG38: =ROUND(AA38 * (1 + 'Scenario Modeling'!$B$4), 0) -> 27 | AH38: =T38 * (1 + 'Scenario Modeling'!$B$3) -> 712.84 | AI38: =V38 * AG38 * (1 - AF38) -> 18957.377 | AJ38: =AI38 - (AH38 * AG38) -> -289.30311
A39: ORD-2025-718992 | B39: 45832 | C39: 45832 | D39: ="Q"&ROUNDUP(MONTH(B39)/3,0)&"-"&YEAR(B39) -> Q2-2025 | E39: 45848 | F39: 45848 | G39: =E39-B39 -> 16 | H39: =F39-B39 -> 16 | I39: =IF(H39<=7, "Yes", "No") -> No | J39: =_xlfn.MINIFS($B$2:$B$633, $L$2:$L$633, L39) -> 44938 | K39: Asia | L39: China | M39: Shanghai | N39: =_xlfn.TEXTJOIN(" - ", TRUE, K39:M39) -> Asia - China - Shanghai | O39: Enterprise | P39: Direct | Q39: N. Brown | R39: Components | S39: CMP-8390 | T39: 757.19 | U39: 1735.41 | V39: =ABS(U39) -> 1735.41 | W39: =IF(V39 <= _xlfn.PERCENTILE.INC($V$2:$V$633, 0.33), "Low", IF(V39 <= _xlfn.PERCENTILE.INC($V$2:$V$633, 0.67), "Medium", "High")) -> High | X39: 0.136 | Y39: =IF(X39>30%,AVERAGEIF($X$2:$X$633,"<30%"),X39) -> 0.136 | Z39: =IF(Y39>0.2, "Yes", "No") -> No | AA39: 8 | AB39: =U39*AA39*(1-Y39) -> 11995.154 | AC39: =T39*AA39 -> 6057.52 | AD39: =AB39-AC39 -> 5937.6339 | AE39: =IF(AB39=0, 0, AD39 / AB39) -> 0.49500273 | AF39: =MIN(Y39,'Scenario Modeling'!$B$2) -> 0.136 | AG39: =ROUND(AA39 * (1 + 'Scenario Modeling'!$B$4), 0) -> 8 | AH39: =T39 * (1 + 'Scenario Modeling'!$B$3) -> 757.19 | AI39: =V39 * AG39 * (1 - AF39) -> 11995.154 | AJ39: =AI39 - (AH39 * AG39) -> 5937.6339
A40: ORD-2024-599522 | B40: 45401 | C40: 45401 | D40: ="Q"&ROUNDUP(MONTH(B40)/3,0)&"-"&YEAR(B40) -> Q2-2024 | E40: 45418 | F40: 45418 | G40: =E40-B40 -> 17 | H40: =F40-B40 -> 17 | I40: =IF(H40<=7, "Yes", "No") -> No | J40: =_xlfn.MINIFS($B$2:$B$633, $L$2:$L$633, L40) -> 44941 | K40: Africa | L40: Nigeria | M40: Port Harcourt | N40: =_xlfn.TEXTJOIN(" - ", TRUE, K40:M40) -> Africa - Nigeria - Port Harcourt | O40: Non-Profit | P40: Online | Q40: A. Patel | R40: Printers | S40: PRN-7303 | T40: 865.33 | U40: 1395.64 | V40: =ABS(U40) -> 1395.64 | W40: =IF(V40 <= _xlfn.PERCENTILE.INC($V$2:$V$633, 0.33), "Low", IF(V40 <= _xlfn.PERCENTILE.INC($V$2:$V$633, 0.67), "Medium", "High")) -> Medium | X40: 0.175 | Y40: =IF(X40>30%,AVERAGEIF($X$2:$X$633,"<30%"),X40) -> 0.175 | Z40: =IF(Y40>0.2, "Yes", "No") -> No | AA40: 13 | AB40: =U40*AA40*(1-Y40) -> 14968.239 | AC40: =T40*AA40 -> 11249.29 | AD40: =AB40-AC40 -> 3718.949 | AE40: =IF(AB40=0, 0, AD40 / AB40) -> 0.24845601 | AF40: =MIN(Y40,'Scenario Modeling'!$B$2) -> 0.175 | AG40: =ROUND(AA40 * (1 + 'Scenario Modeling'!$B$4), 0) -> 13 | AH40: =T40 * (1 + 'Scenario Modeling'!$B$3) -> 865.33 | AI40: =V40 * AG40 * (1 - AF40) -> 14968.239 | AJ40: =AI40 - (AH40 * AG40) -> 3718.949
A41: ORD-2023-651638 | B41: 45094 | C41: 45094 | D41: ="Q"&ROUNDUP(MONTH(B41)/3,0)&"-"&YEAR(B41) -> Q2-2023 | E41: 45101 | F41: 45101 | G41: =E41-B41 -> 7 | H41: =F41-B41 -> 7 | I41: =IF(H41<=7, "Yes", "No") -> Yes | J41: =_xlfn.MINIFS($B$2:$B$633, $L$2:$L$633, L41) -> 44939 | K41: Americas | L41: USA | M41: San Francisco | N41: =_xlfn.TEXTJOIN(" - ", TRUE, K41:M41) -> Americas - USA - San Francisco | O41: Corporate | P41: Retail | Q41: I. Johnson | R41: Printers | S41: PRN-6536 | T41: 313.99 | U41: 454.42 | V41: =ABS(U41) -> 454.42 | W41: =IF(V41 <= _xlfn.PERCENTILE.INC($V$2:$V$633, 0.33), "Low", IF(V41 <= _xlfn.PERCENTILE.INC($V$2:$V$633, 0.67), "Medium", "High")) -> Low | X41: 0.129 | Y41: =IF(X41>30%,AVERAGEIF($X$2:$X$633,"<30%"),X41) -> 0.129 | Z41: =IF(Y41>0.2, "Yes", "No") -> No | AA41: 9 | AB41: =U41*AA41*(1-Y41) -> 3562.1984 | AC41: =T41*AA41 -> 2825.91 | AD41: =AB41-AC41 -> 736.28838 | AE41: =IF(AB41=0, 0, AD41 / AB41) -> 0.20669494 | AF41: =MIN(Y41,'Scenario Modeling'!$B$2) -> 0.129 | AG41: =ROUND(AA41 * (1 + 'Scenario Modeling'!$B$4), 0) -> 9 | AH41: =T41 * (1 + 'Scenario Modeling'!$B$3) -> 313.99 | AI41: =V41 * AG41 * (1 - AF41) -> 3562.1984 | AJ41: =AI41 - (AH41 * AG41) -> 736.28838
A42: ORD-2024-635626 | B42: 45531 | C42: 45531 | D42: ="Q"&ROUNDUP(MONTH(B42)/3,0)&"-"&YEAR(B42) -> Q3-2024 | E42: 45554 | F42: 45554 | G42: =E42-B42 -> 23 | H42: =F42-B42 -> 23 | I42: =IF(H42<=7, "Yes", "No") -> No | J42: =_xlfn.MINIFS($B$2:$B$633, $L$2:$L$633, L42) -> 44948 | K42: Europe | L42: Germany | M42: Berlin | N42: =_xlfn.TEXTJOIN(" - ", TRUE, K42:M42) -> Europe - Germany - Berlin | O42: Small Business | P42: Direct | Q42: D. Smith | R42: Monitors | S42: MON-9967 | T42: 1024.01 | U42: 1580.97 | V42: =ABS(U42) -> 1580.97 | W42: =IF(V42 <= _xlfn.PERCENTILE.INC($V$2:$V$633, 0.33), "Low", IF(V42 <= _xlfn.PERCENTILE.INC($V$2:$V$633, 0.67), "Medium", "High")) -> Medium | X42: 0.037 | Y42: =IF(X42>30%,AVERAGEIF($X$2:$X$633,"<30%"),X42) -> 0.037 | Z42: =IF(Y42>0.2, "Yes", "No") -> No | AA42: 27 | AB42: =U42*AA42*(1-Y42) -> 41106.801 | AC42: =T42*AA42 -> 27648.27 | AD42: =AB42-AC42 -> 13458.531 | AE42: =IF(AB42=0, 0, AD42 / AB42) -> 0.327404 | AF42: =MIN(Y42,'Scenario Modeling'!$B$2) -> 0.037 | AG42: =ROUND(AA42 * (1 + 'Scenario Modeling'!$B$4), 0) -> 27 | AH42: =T42 * (1 + 'Scenario Modeling'!$B$3) -> 1024.01 | AI42: =V42 * AG42 * (1 - AF42) -> 41106.801 | AJ42: =AI42 - (AH42 * AG42) -> 13458.531
A43: ORD-2024-296582 | B43: 45302 | C43: 45302 | D43: ="Q"&ROUNDUP(MONTH(B43)/3,0)&"-"&YEAR(B43) -> Q1-2024 | E43: 45324 | F43: 45324 | G43: =E43-B43 -> 22 | H43: =F43-B43 -> 22 | I43: =IF(H43<=7, "Yes", "No") -> No | J43: =_xlfn.MINIFS($B$2:$B$633, $L$2:$L$633, L43) -> 44933 | K43: Africa | L43: South Africa | M43: Durban | N43: =_xlfn.TEXTJOIN(" - ", TRUE, K43:M43) -> Africa - South Africa - Durban | O43: Consumer | P43: Online | Q43: K. Singh | R43: Networking | S43: NET-1412 | T43: 1206.2 | U43: 1759.79 | V43: =ABS(U43) -> 1759.79 | W43: =IF(V43 <= _xlfn.PERCENTILE.INC($V$2:$V$633, 0.33), "Low", IF(V43 <= _xlfn.PERCENTILE.INC($V$2:$V$633, 0.67), "Medium", "High")) -> High | X43: 0 | Y43: =IF(X43>30%,AVERAGEIF($X$2:$X$633,"<30%"),X43) -> 0 | Z43: =IF(Y43>0.2, "Yes", "No") -> No | AA43: 6 | AB43: =U43*AA43*(1-Y43) -> 10558.74 | AC43: =T43*AA43 -> 7237.2 | AD43: =AB43-AC43 -> 3321.54 | AE43: =IF(AB43=0, 0, AD43 / AB43) -> 0.31457731 | AF43: =MIN(Y43,'Scenario Modeling'!$B$2) -> 0 | AG43: =ROUND(AA43 * (1 + 'Scenario Modeling'!$B$4), 0) -> 6 | AH43: =T43 * (1 + 'Scenario Modeling'!$B$3) -> 1206.2 | AI43: =V43 * AG43 * (1 - AF43) -> 10558.74 | AJ43: =AI43 - (AH43 * AG43) -> 3321.54
A44: ORD-2024-998320 | B44: 45590 | C44: 45590 | D44: ="Q"&ROUNDUP(MONTH(B44)/3,0)&"-"&YEAR(B44) -> Q4-2024 | E44: 45610 | F44: 45610 | G44: =E44-B44 -> 20 | H44: =F44-B44 -> 20 | I44: =IF(H44<=7, "Yes", "No") -> No | J44: =_xlfn.MINIFS($B$2:$B$633, $L$2:$L$633, L44) -> 44946 | K44: Africa | L44: Kenya | M44: Mombasa | N44: =_xlfn.TEXTJOIN(" - ", TRUE, K44:M44) -> Africa - Kenya - Mombasa | O44: Corporate | P44: Direct | Q44: H. Kim | R44: Printers | S44: PRN-3143 | T44: 1396.48 | U44: 3204.5 | V44: =ABS(U44) -> 3204.5 | W44: =IF(V44 <= _xlfn.PERCENTILE.INC($V$2:$V$633, 0.33), "Low", IF(V44 <= _xlfn.PERCENTILE.INC($V$2:$V$633, 0.67), "Medium", "High")) -> High | X44: 0.318 | Y44: =IF(X44>30%,AVERAGEIF($X$2:$X$633,"<30%"),X44) -> 0.1186144 | Z44: =IF(Y44>0.2, "Yes", "No") -> No | AA44: 14 | AB44: =U44*AA44*(1-Y44) -> 39541.602 | AC44: =T44*AA44 -> 19550.72 | AD44: =AB44-AC44 -> 19990.882 | AE44: =IF(AB44=0, 0, AD44 / AB44) -> 0.50556581 | AF44: =MIN(Y44,'Scenario Modeling'!$B$2) -> 0.1186144 | AG44: =ROUND(AA44 * (1 + 'Scenario Modeling'!$B$4), 0) -> 14 | AH44: =T44 * (1 + 'Scenario Modeling'!$B$3) -> 1396.48 | AI44: =V44 * AG44 * (1 - AF44) -> 39541.602 | AJ44: =AI44 - (AH44 * AG44) -> 19990.882
A45: ORD-2025-820255 | B45: 45806 | C45: 45806 | D45: ="Q"&ROUNDUP(MONTH(B45)/3,0)&"-"&YEAR(B45) -> Q2-2025 | E45: 45828 | F45: 45828 | G45: =E45-B45 -> 22 | H45: =F45-B45 -> 22 | I45: =IF(H45<=7, "Yes", "No") -> No | J45: =_xlfn.MINIFS($B$2:$B$633, $L$2:$L$633, L45) -> 44948 | K45: Europe | L45: Germany | M45: Berlin | N45: =_xlfn.TEXTJOIN(" - ", TRUE, K45:M45) -> Europe - Germany - Berlin | O45: Corporate | P45: Direct | Q45: A. Patel | R45: Printers | S45: PRN-9787 | T45: 483.47 | U45: 1135.43 | V45: =ABS(U45) -> 1135.43 | W45: =IF(V45 <= _xlfn.PERCENTILE.INC($V$2:$V$633, 0.33), "Low", IF(V45 <= _xlfn.PERCENTILE.INC($V$2:$V$633, 0.67), "Medium", "High")) -> Medium | X45: 0.146 | Y45: =IF(X45>30%,AVERAGEIF($X$2:$X$633,"<30%"),X45) -> 0.146 | Z45: =IF(Y45>0.2, "Yes", "No") -> No | AA45: 11 | AB45: =U45*AA45*(1-Y45) -> 10666.229 | AC45: =T45*AA45 -> 5318.17 | AD45: =AB45-AC45 -> 5348.0594 | AE45: =IF(AB45=0, 0, AD45 / AB45) -> 0.50140112 | AF45: =MIN(Y45,'Scenario Modeling'!$B$2) -> 0.146 | AG45: =ROUND(AA45 * (1 + 'Scenario Modeling'!$B$4), 0) -> 11 | AH45: =T45 * (1 + 'Scenario Modeling'!$B$3) -> 483.47 | AI45: =V45 * AG45 * (1 - AF45) -> 10666.229 | AJ45: =AI45 - (AH45 * AG45) -> 5348.0594
A46: ORD-2024-389336 | B46: 45432 | C46: 45432 | D46: ="Q"&ROUNDUP(MONTH(B46)/3,0)&"-"&YEAR(B46) -> Q2-2024 | E46: 45445 | F46: 45445 | G46: =E46-B46 -> 13 | H46: =F46-B46 -> 13 | I46: =IF(H46<=7, "Yes", "No") -> No | J46: =_xlfn.MINIFS($B$2:$B$633, $L$2:$L$633, L46) -> 44928 | K46: Americas | L46: Canada | M46: Vancouver | N46: =_xlfn.TEXTJOIN(" - ", TRUE, K46:M46) -> Americas - Canada - Vancouver | O46: Enterprise | P46: Marketplace | Q46: K. Singh | R46: Components | S46: CMP-5946 | T46: 675.43 | U46: 996.36 | V46: =ABS(U46) -> 996.36 | W46: =IF(V46 <= _xlfn.PERCENTILE.INC($V$2:$V$633, 0.33), "Low", IF(V46 <= _xlfn.PERCENTILE.INC($V$2:$V$633, 0.67), "Medium", "High")) -> Medium | X46: 0.182 | Y46: =IF(X46>30%,AVERAGEIF($X$2:$X$633,"<30%"),X46) -> 0.182 | Z46: =IF(Y46>0.2, "Yes", "No") -> No | AA46: 22 | AB46: =U46*AA46*(1-Y46) -> 17930.495 | AC46: =T46*AA46 -> 14859.46 | AD46: =AB46-AC46 -> 3071.0346 | AE46: =IF(AB46=0, 0, AD46 / AB46) -> 0.17127439 | AF46: =MIN(Y46,'Scenario Modeling'!$B$2) -> 0.182 | AG46: =ROUND(AA46 * (1 + 'Scenario Modeling'!$B$4), 0) -> 22 | AH46: =T46 * (1 + 'Scenario Modeling'!$B$3) -> 675.43 | AI46: =V46 * AG46 * (1 - AF46) -> 17930.495 | AJ46: =AI46 - (AH46 * AG46) -> 3071.0346
A47: ORD-2023-308124 | B47: 45035 | C47: 45035 | D47: ="Q"&ROUNDUP(MONTH(B47)/3,0)&"-"&YEAR(B47) -> Q2-2023 | E47: 45046 | F47: 45046 | G47: =E47-B47 -> 11 | H47: =F47-B47 -> 11 | I47: =IF(H47<=7, "Yes", "No") -> No | J47: =_xlfn.MINIFS($B$2:$B$633, $L$2:$L$633, L47) -> 44955 | K47: Asia | L47: India | M47: Delhi | N47: =_xlfn.TEXTJOIN(" - ", TRUE, K47:M47) -> Asia - India - Delhi | O47: Small Business | P47: Retail | Q47: A. Patel | R47: Networking | S47: NET-2062 | T47: 826.55 | U47: 1397.05 | V47: =ABS(U47) -> 1397.05 | W47: =IF(V47 <= _xlfn.PERCENTILE.INC($V$2:$V$633, 0.33), "Low", IF(V47 <= _xlfn.PERCENTILE.INC($V$2:$V$633, 0.67), "Medium", "High")) -> Medium | X47: 0.169 | Y47: =IF(X47>30%,AVERAGEIF($X$2:$X$633,"<30%"),X47) -> 0.169 | Z47: =IF(Y47>0.2, "Yes", "No") -> No | AA47: 28 | AB47: =U47*AA47*(1-Y47) -> 32506.559 | AC47: =T47*AA47 -> 23143.4 | AD47: =AB47-AC47 -> 9363.1594 | AE47: =IF(AB47=0, 0, AD47 / AB47) -> 0.28803908 | AF47: =MIN(Y47,'Scenario Modeling'!$B$2) -> 0.169 | AG47: =ROUND(AA47 * (1 + 'Scenario Modeling'!$B$4), 0) -> 28 | AH47: =T47 * (1 + 'Scenario Modeling'!$B$3) -> 826.55 | AI47: =V47 * AG47 * (1 - AF47) -> 32506.559 | AJ47: =AI47 - (AH47 * AG47) -> 9363.1594
A48: ORD-2023-128295 | B48: 45100 | C48: 45100 | D48: ="Q"&ROUNDUP(MONTH(B48)/3,0)&"-"&YEAR(B48) -> Q2-2023 | E48: 45110 | F48: 45110 | G48: =E48-B48 -> 10 | H48: =F48-B48 -> 10 | I48: =IF(H48<=7, "Yes", "No") -> No | J48: =_xlfn.MINIFS($B$2:$B$633, $L$2:$L$633, L48) -> 44941 | K48: Africa | L48: Nigeria | M48: Abuja | N48: =_xlfn.TEXTJOIN(" - ", TRUE, K48:M48) -> Africa - Nigeria - Abuja | O48: Consumer | P48: Online | Q48: J. Njeri | R48: Printers | S48: PRN-2542 | T48: 337.75 | U48: 548.89 | V48: =ABS(U48) -> 548.89 | W48: =IF(V48 <= _xlfn.PERCENTILE.INC($V$2:$V$633, 0.33), "Low", IF(V48 <= _xlfn.PERCENTILE.INC($V$2:$V$633, 0.67), "Medium", "High")) -> Low | X48: 0 | Y48: =IF(X48>30%,AVERAGEIF($X$2:$X$633,"<30%"),X48) -> 0 | Z48: =IF(Y48>0.2, "Yes", "No") -> No | AA48: 13 | AB48: =U48*AA48*(1-Y48) -> 7135.57 | AC48: =T48*AA48 -> 4390.75 | AD48: =AB48-AC48 -> 2744.82 | AE48: =IF(AB48=0, 0, AD48 / AB48) -> 0.38466724 | AF48: =MIN(Y48,'Scenario Modeling'!$B$2) -> 0 | AG48: =ROUND(AA48 * (1 + 'Scenario Modeling'!$B$4), 0) -> 13 | AH48: =T48 * (1 + 'Scenario Modeling'!$B$3) -> 337.75 | AI48: =V48 * AG48 * (1 - AF48) -> 7135.57 | AJ48: =AI48 - (AH48 * AG48) -> 2744.82
... A75: ORD-2024-800947 | B75: 45641 | C75: 45641 | D75: ="Q"&ROUNDUP(MONTH(B75)/3,0)&"-"&YEAR(B75) -> Q4-2024 | E75: 45646 | F75: 45646 | G75: =E75-B75 -> 5 | H75: =F75-B75 -> 5 | I75: =IF(H75<=7, "Yes", "No") -> Yes | J75: =_xlfn.MINIFS($B$2:$B$633, $L$2:$L$633, L75) -> 44938 | K75: Asia | L75: China | M75: Shenzhen | N75: =_xlfn.TEXTJOIN(" - ", TRUE, K75:M75) -> Asia - China - Shenzhen | O75: Small Business | P75: Direct | Q75: J. Njeri | R75: Networking | S75: NET-1846 | T75: 717.55 | U75: 546.43 | V75: =ABS(U75) -> 546.43 | W75: =IF(V75 <= _xlfn.PERCENTILE.INC($V$2:$V$633, 0.33), "Low", IF(V75 <= _xlfn.PERCENTILE.INC($V$2:$V$633, 0.67), "Medium", "High")) -> Low | X75: 0.047 | Y75: =IF(X75>30%,AVERAGEIF($X$2:$X$633,"<30%"),X75) -> 0.047 | Z75: =IF(Y75>0.2, "Yes", "No") -> No | AA75: 18 | AB75: =U75*AA75*(1-Y75) -> 9373.4602 | AC75: =T75*AA75 -> 12915.9 | AD75: =AB75-AC75 -> -3542.4398 | AE75: =IF(AB75=0, 0, AD75 / AB75) -> -0.37792231 | AF75: =MIN(Y75,'Scenario Modeling'!$B$2) -> 0.047 | AG75: =ROUND(AA75 * (1 + 'Scenario Modeling'!$B$4), 0) -> 18 | AH75: =T75 * (1 + 'Scenario Modeling'!$B$3) -> 717.55 | AI75: =V75 * AG75 * (1 - AF75) -> 9373.4602 | AJ75: =AI75 - (AH75 * AG75) -> -3542.4398
A76: ORD-2023-382272 | B76: 45066 | C76: 45066 | D76: ="Q"&ROUNDUP(MONTH(B76)/3,0)&"-"&YEAR(B76) -> Q2-2023 | E76: 45064 | F76: =B76+11 -> 45077 | G76: =E76-B76 -> -2 | H76: =F76-B76 -> 11 | I76: =IF(H76<=7, "Yes", "No") -> No | J76: =_xlfn.MINIFS($B$2:$B$633, $L$2:$L$633, L76) -> 44933 | K76: Africa | L76: South Africa | M76: Durban | N76: =_xlfn.TEXTJOIN(" - ", TRUE, K76:M76) -> Africa - South Africa - Durban | O76: Corporate | P76: Distributor | Q76: A. Patel | R76: Components | S76: CMP-5208 | T76: 917.88 | U76: 1347.92 | V76: =ABS(U76) -> 1347.92 | W76: =IF(V76 <= _xlfn.PERCENTILE.INC($V$2:$V$633, 0.33), "Low", IF(V76 <= _xlfn.PERCENTILE.INC($V$2:$V$633, 0.67), "Medium", "High")) -> Medium | X76: 0.343 | Y76: =IF(X76>30%,AVERAGEIF($X$2:$X$633,"<30%"),X76) -> 0.1186144 | Z76: =IF(Y76>0.2, "Yes", "No") -> No | AA76: 5 | AB76: =U76*AA76*(1-Y76) -> 5940.1864 | AC76: =T76*AA76 -> 4589.4 | AD76: =AB76-AC76 -> 1350.7864 | AE76: =IF(AB76=0, 0, AD76 / AB76) -> 0.22739798 | AF76: =MIN(Y76,'Scenario Modeling'!$B$2) -> 0.1186144 | AG76: =ROUND(AA76 * (1 + 'Scenario Modeling'!$B$4), 0) -> 5 | AH76: =T76 * (1 + 'Scenario Modeling'!$B$3) -> 917.88 | AI76: =V76 * AG76 * (1 - AF76) -> 5940.1864 | AJ76: =AI76 - (AH76 * AG76) -> 1350.7864
A77: ORD-2023-722117 | B77: 45187 | C77: 45187 | D77: ="Q"&ROUNDUP(MONTH(B77)/3,0)&"-"&YEAR(B77) -> Q3-2023 | E77: 45207 | F77: 45207 | G77: =E77-B77 -> 20 | H77: =F77-B77 -> 20 | I77: =IF(H77<=7, "Yes", "No") -> No | J77: =_xlfn.MINIFS($B$2:$B$633, $L$2:$L$633, L77) -> 44955 | K77: Asia | L77: India | M77: Delhi | N77: =_xlfn.TEXTJOIN(" - ", TRUE, K77:M77) -> Asia - India - Delhi | O77: Small Business | P77: Direct | Q77: B. Chen | R77: Components | S77: CMP-1009 | T77: 825.64 | U77: 1108.43 | V77: =ABS(U77) -> 1108.43 | W77: =IF(V77 <= _xlfn.PERCENTILE.INC($V$2:$V$633, 0.33), "Low", IF(V77 <= _xlfn.PERCENTILE.INC($V$2:$V$633, 0.67), "Medium", "High")) -> Medium | X77: 0.114 | Y77: =IF(X77>30%,AVERAGEIF($X$2:$X$633,"<30%"),X77) -> 0.114 | Z77: =IF(Y77>0.2, "Yes", "No") -> No | AA77: 7 | AB77: =U77*AA77*(1-Y77) -> 6874.4829 | AC77: =T77*AA77 -> 5779.48 | AD77: =AB77-AC77 -> 1095.0029 | AE77: =IF(AB77=0, 0, AD77 / AB77) -> 0.15928512 | AF77: =MIN(Y77,'Scenario Modeling'!$B$2) -> 0.114 | AG77: =ROUND(AA77 * (1 + 'Scenario Modeling'!$B$4), 0) -> 7 | AH77: =T77 * (1 + 'Scenario Modeling'!$B$3) -> 825.64 | AI77: =V77 * AG77 * (1 - AF77) -> 6874.4829 | AJ77: =AI77 - (AH77 * AG77) -> 1095.0029
A78: ORD-2024-446699 | B78: 45532 | C78: 45532 | D78: ="Q"&ROUNDUP(MONTH(B78)/3,0)&"-"&YEAR(B78) -> Q3-2024 | E78: 45560 | F78: 45560 | G78: =E78-B78 -> 28 | H78: =F78-B78 -> 28 | I78: =IF(H78<=7, "Yes", "No") -> No | J78: =_xlfn.MINIFS($B$2:$B$633, $L$2:$L$633, L78) -> 44955 | K78: Americas | L78: Brazil | M78: Rio de Janeiro | N78: =_xlfn.TEXTJOIN(" - ", TRUE, K78:M78) -> Americas - Brazil - Rio de Janeiro | O78: Non-Profit | P78: Online | Q78: M. Rossi | R78: Accessories | S78: ACC-4490 | T78: 1394.65 | U78: 3144.1 | V78: =ABS(U78) -> 3144.1 | W78: =IF(V78 <= _xlfn.PERCENTILE.INC($V$2:$V$633, 0.33), "Low", IF(V78 <= _xlfn.PERCENTILE.INC($V$2:$V$633, 0.67), "Medium", "High")) -> High | X78: 0.134 | Y78: =IF(X78>30%,AVERAGEIF($X$2:$X$633,"<30%"),X78) -> 0.134 | Z78: =IF(Y78>0.2, "Yes", "No") -> No | AA78: 13 | AB78: =U78*AA78*(1-Y78) -> 35396.278 | AC78: =T78*AA78 -> 18130.45 | AD78: =AB78-AC78 -> 17265.828 | AE78: =IF(AB78=0, 0, AD78 / AB78) -> 0.48778654 | AF78: =MIN(Y78,'Scenario Modeling'!$B$2) -> 0.134 | AG78: =ROUND(AA78 * (1 + 'Scenario Modeling'!$B$4), 0) -> 13 | AH78: =T78 * (1 + 'Scenario Modeling'!$B$3) -> 1394.65 | AI78: =V78 * AG78 * (1 - AF78) -> 35396.278 | AJ78: =AI78 - (AH78 * AG78) -> 17265.828
A79: ORD-2024-451005 | B79: 45473 | C79: 45473 | D79: ="Q"&ROUNDUP(MONTH(B79)/3,0)&"-"&YEAR(B79) -> Q2-2024 | E79: 45471 | F79: =B79+4 -> 45477 | G79: =E79-B79 -> -2 | H79: =F79-B79 -> 4 | I79: =IF(H79<=7, "Yes", "No") -> Yes | J79: =_xlfn.MINIFS($B$2:$B$633, $L$2:$L$633, L79) -> 44955 | K79: Americas | L79: Brazil | M79: Rio de Janeiro | N79: =_xlfn.TEXTJOIN(" - ", TRUE, K79:M79) -> Americas - Brazil - Rio de Janeiro | O79: Small Business | P79: Direct | Q79: L. Okafor | R79: Accessories | S79: ACC-9162 | T79: 1112.98 | U79: 2095.73 | V79: =ABS(U79) -> 2095.73 | W79: =IF(V79 <= _xlfn.PERCENTILE.INC($V$2:$V$633, 0.33), "Low", IF(V79 <= _xlfn.PERCENTILE.INC($V$2:$V$633, 0.67), "Medium", "High")) -> High | X79: 0.072 | Y79: =IF(X79>30%,AVERAGEIF($X$2:$X$633,"<30%"),X79) -> 0.072 | Z79: =IF(Y79>0.2, "Yes", "No") -> No | AA79: 17 | AB79: =U79*AA79*(1-Y79) -> 33062.236 | AC79: =T79*AA79 -> 18920.66 | AD79: =AB79-AC79 -> 14141.576 | AE79: =IF(AB79=0, 0, AD79 / AB79) -> 0.42772595 | AF79: =MIN(Y79,'Scenario Modeling'!$B$2) -> 0.072 | AG79: =ROUND(AA79 * (1 + 'Scenario Modeling'!$B$4), 0) -> 17 | AH79: =T79 * (1 + 'Scenario Modeling'!$B$3) -> 1112.98 | AI79: =V79 * AG79 * (1 - AF79) -> 33062.236 | AJ79: =AI79 - (AH79 * AG79) -> 14141.576
A80: ORD-2023-290279 | B80: 45091 | C80: 45091 | D80: ="Q"&ROUNDUP(MONTH(B80)/3,0)&"-"&YEAR(B80) -> Q2-2023 | E80: 45093 | F80: 45093 | G80: =E80-B80 -> 2 | H80: =F80-B80 -> 2 | I80: =IF(H80<=7, "Yes", "No") -> Yes | J80: =_xlfn.MINIFS($B$2:$B$633, $L$2:$L$633, L80) -> 44945 | K80: Europe | L80: United Kingdom | M80: Manchester | N80: =_xlfn.TEXTJOIN(" - ", TRUE, K80:M80) -> Europe - United Kingdom - Manchester | O80: Non-Profit | P80: Direct | Q80: K. Singh | R80: Components | S80: CMP-5820 | T80: 357.36 | U80: 703.62 | V80: =ABS(U80) -> 703.62 | W80: =IF(V80 <= _xlfn.PERCENTILE.INC($V$2:$V$633, 0.33), "Low", IF(V80 <= _xlfn.PERCENTILE.INC($V$2:$V$633, 0.67), "Medium", "High")) -> Low | X80: 0.257 | Y80: =IF(X80>30%,AVERAGEIF($X$2:$X$633,"<30%"),X80) -> 0.257 | Z80: =IF(Y80>0.2, "Yes", "No") -> Yes | AA80: 20 | AB80: =U80*AA80*(1-Y80) -> 10455.793 | AC80: =T80*AA80 -> 7147.2 | AD80: =AB80-AC80 -> 3308.5932 | AE80: =IF(AB80=0, 0, AD80 / AB80) -> 0.31643637 | AF80: =MIN(Y80,'Scenario Modeling'!$B$2) -> 0.25 | AG80: =ROUND(AA80 * (1 + 'Scenario Modeling'!$B$4), 0) -> 20 | AH80: =T80 * (1 + 'Scenario Modeling'!$B$3) -> 357.36 | AI80: =V80 * AG80 * (1 - AF80) -> 10554.3 | AJ80: =AI80 - (AH80 * AG80) -> 3407.1
A81: ORD-2024-192263 | B81: 45617 | C81: 45617 | D81: ="Q"&ROUNDUP(MONTH(B81)/3,0)&"-"&YEAR(B81) -> Q4-2024 | E81: 45647 | F81: 45647 | G81: =E81-B81 -> 30 | H81: =F81-B81 -> 30 | I81: =IF(H81<=7, "Yes", "No") -> No | J81: =_xlfn.MINIFS($B$2:$B$633, $L$2:$L$633, L81) -> 44936 | K81: Europe | L81: France | M81: Marseille | N81: =_xlfn.TEXTJOIN(" - ", TRUE, K81:M81) -> Europe - France - Marseille | O81: Small Business | P81: Direct | Q81: I. Johnson | R81: Monitors | S81: MON-7943 | T81: 1122.68 | U81: 1997.19 | V81: =ABS(U81) -> 1997.19 | W81: =IF(V81 <= _xlfn.PERCENTILE.INC($V$2:$V$633, 0.33), "Low", IF(V81 <= _xlfn.PERCENTILE.INC($V$2:$V$633, 0.67), "Medium", "High")) -> High | X81: 0.186 | Y81: =IF(X81>30%,AVERAGEIF($X$2:$X$633,"<30%"),X81) -> 0.186 | Z81: =IF(Y81>0.2, "Yes", "No") -> No | AA81: 3 | AB81: =U81*AA81*(1-Y81) -> 4877.138 | AC81: =T81*AA81 -> 3368.04 | AD81: =AB81-AC81 -> 1509.098 | AE81: =IF(AB81=0, 0, AD81 / AB81) -> 0.30942286 | AF81: =MIN(Y81,'Scenario Modeling'!$B$2) -> 0.186 | AG81: =ROUND(AA81 * (1 + 'Scenario Modeling'!$B$4), 0) -> 3 | AH81: =T81 * (1 + 'Scenario Modeling'!$B$3) -> 1122.68 | AI81: =V81 * AG81 * (1 - AF81) -> 4877.138 | AJ81: =AI81 - (AH81 * AG81) -> 1509.098
A82: ORD-2023-159379 | B82: 44965 | C82: 44965 | D82: ="Q"&ROUNDUP(MONTH(B82)/3,0)&"-"&YEAR(B82) -> Q1-2023 | E82: 44968 | F82: 44968 | G82: =E82-B82 -> 3 | H82: =F82-B82 -> 3 | I82: =IF(H82<=7, "Yes", "No") -> Yes | J82: =_xlfn.MINIFS($B$2:$B$633, $L$2:$L$633, L82) -> 44933 | K82: Africa | L82: South Africa | M82: Cape Town | N82: =_xlfn.TEXTJOIN(" - ", TRUE, K82:M82) -> Africa - South Africa - Cape Town | O82: Corporate | P82: Direct | Q82: M. Rossi | R82: Networking | S82: NET-5018 | T82: 1410.05 | U82: 2763.95 | V82: =ABS(U82) -> 2763.95 | W82: =IF(V82 <= _xlfn.PERCENTILE.INC($V$2:$V$633, 0.33), "Low", IF(V82 <= _xlfn.PERCENTILE.INC($V$2:$V$633, 0.67), "Medium", "High")) -> High | X82: 0.161 | Y82: =IF(X82>30%,AVERAGEIF($X$2:$X$633,"<30%"),X82) -> 0.161 | Z82: =IF(Y82>0.2, "Yes", "No") -> No | AA82: 26 | AB82: =U82*AA82*(1-Y82) -> 60292.805 | AC82: =T82*AA82 -> 36661.3 | AD82: =AB82-AC82 -> 23631.505 | AE82: =IF(AB82=0, 0, AD82 / AB82) -> 0.39194569 | AF82: =MIN(Y82,'Scenario Modeling'!$B$2) -> 0.161 | AG82: =ROUND(AA82 * (1 + 'Scenario Modeling'!$B$4), 0) -> 26 | AH82: =T82 * (1 + 'Scenario Modeling'!$B$3) -> 1410.05 | AI82: =V82 * AG82 * (1 - AF82) -> 60292.805 | AJ82: =AI82 - (AH82 * AG82) -> 23631.505
A83: ORD-2023-343322 | B83: 45157 | C83: 45157 | D83: ="Q"&ROUNDUP(MONTH(B83)/3,0)&"-"&YEAR(B83) -> Q3-2023 | E83: 45181 | F83: 45181 | G83: =E83-B83 -> 24 | H83: =F83-B83 -> 24 | I83: =IF(H83<=7, "Yes", "No") -> No | J83: =_xlfn.MINIFS($B$2:$B$633, $L$2:$L$633, L83) -> 44928 | K83: Americas | L83: Canada | M83: Vancouver | N83: =_xlfn.TEXTJOIN(" - ", TRUE, K83:M83) -> Americas - Canada - Vancouver | O83: Enterprise | P83: Retail | Q83: I. Johnson | R83: Printers | S83: PRN-9669 | T83: 1183.95 | U83: 1503.53 | V83: =ABS(U83) -> 1503.53 | W83: =IF(V83 <= _xlfn.PERCENTILE.INC($V$2:$V$633, 0.33), "Low", IF(V83 <= _xlfn.PERCENTILE.INC($V$2:$V$633, 0.67), "Medium", "High")) -> Medium | X83: 0.241 | Y83: =IF(X83>30%,AVERAGEIF($X$2:$X$633,"<30%"),X83) -> 0.241 | Z83: =IF(Y83>0.2, "Yes", "No") -> Yes | AA83: 16 | AB83: =U83*AA83*(1-Y83) -> 18258.868 | AC83: =T83*AA83 -> 18943.2 | AD83: =AB83-AC83 -> -684.33168 | AE83: =IF(AB83=0, 0, AD83 / AB83) -> -0.037479414 | AF83: =MIN(Y83,'Scenario Modeling'!$B$2) -> 0.241 | AG83: =ROUND(AA83 * (1 + 'Scenario Modeling'!$B$4), 0) -> 16 | AH83: =T83 * (1 + 'Scenario Modeling'!$B$3) -> 1183.95 | AI83: =V83 * AG83 * (1 - AF83) -> 18258.868 | AJ83: =AI83 - (AH83 * AG83) -> -684.33168
A84: ORD-2025-114382 | B84: 45791 | C84: 45791 | D84: ="Q"&ROUNDUP(MONTH(B84)/3,0)&"-"&YEAR(B84) -> Q2-2025 | E84: 45801 | F84: 45801 | G84: =E84-B84 -> 10 | H84: =F84-B84 -> 10 | I84: =IF(H84<=7, "Yes", "No") -> No | J84: =_xlfn.MINIFS($B$2:$B$633, $L$2:$L$633, L84) -> 44936 | K84: Europe | L84: France | M84: Paris | N84: =_xlfn.TEXTJOIN(" - ", TRUE, K84:M84) -> Europe - France - Paris | O84: Small Business | P84: Marketplace | Q84: K. Singh | R84: Components | S84: CMP-2865 | T84: 170.39 | U84: 388.04 | V84: =ABS(U84) -> 388.04 | W84: =IF(V84 <= _xlfn.PERCENTILE.INC($V$2:$V$633, 0.33), "Low", IF(V84 <= _xlfn.PERCENTILE.INC($V$2:$V$633, 0.67), "Medium", "High")) -> Low | X84: 0.084 | Y84: =IF(X84>30%,AVERAGEIF($X$2:$X$633,"<30%"),X84) -> 0.084 | Z84: =IF(Y84>0.2, "Yes", "No") -> No | AA84: 15 | AB84: =U84*AA84*(1-Y84) -> 5331.6696 | AC84: =T84*AA84 -> 2555.85 | AD84: =AB84-AC84 -> 2775.8196 | AE84: =IF(AB84=0, 0, AD84 / AB84) -> 0.52062859 | AF84: =MIN(Y84,'Scenario Modeling'!$B$2) -> 0.084 | AG84: =ROUND(AA84 * (1 + 'Scenario Modeling'!$B$4), 0) -> 15 | AH84: =T84 * (1 + 'Scenario Modeling'!$B$3) -> 170.39 | AI84: =V84 * AG84 * (1 - AF84) -> 5331.6696 | AJ84: =AI84 - (AH84 * AG84) -> 2775.8196
A85: ORD-2025-488349 | B85: 45770 | C85: 45770 | D85: ="Q"&ROUNDUP(MONTH(B85)/3,0)&"-"&YEAR(B85) -> Q2-2025 | E85: 45769 | F85: =B85+11 -> 45781 | G85: =E85-B85 -> -1 | H85: =F85-B85 -> 11 | I85: =IF(H85<=7, "Yes", "No") -> No | J85: =_xlfn.MINIFS($B$2:$B$633, $L$2:$L$633, L85) -> 44939 | K85: Americas | L85: USA | M85: San Francisco | N85: =_xlfn.TEXTJOIN(" - ", TRUE, K85:M85) -> Americas - USA - San Francisco | O85: Non-Profit | P85: Distributor | Q85: D. Smith | R85: Monitors | S85: MON-3371 | T85: 23.24 | U85: 44.57 | V85: =ABS(U85) -> 44.57 | W85: =IF(V85 <= _xlfn.PERCENTILE.INC($V$2:$V$633, 0.33), "Low", IF(V85 <= _xlfn.PERCENTILE.INC($V$2:$V$633, 0.67), "Medium", "High")) -> Low | X85: 0.215 | Y85: =IF(X85>30%,AVERAGEIF($X$2:$X$633,"<30%"),X85) -> 0.215 | Z85: =IF(Y85>0.2, "Yes", "No") -> Yes | AA85: 15 | AB85: =U85*AA85*(1-Y85) -> 524.81175 | AC85: =T85*AA85 -> 348.6 | AD85: =AB85-AC85 -> 176.21175 | AE85: =IF(AB85=0, 0, AD85 / AB85) -> 0.33576182 | AF85: =MIN(Y85,'Scenario Modeling'!$B$2) -> 0.215 | AG85: =ROUND(AA85 * (1 + 'Scenario Modeling'!$B$4), 0) -> 15 | AH85: =T85 * (1 + 'Scenario Modeling'!$B$3) -> 23.24 | AI85: =V85 * AG85 * (1 - AF85) -> 524.81175 | AJ85: =AI85 - (AH85 * AG85) -> 176.21175
A86: ORD-2025-330203 | B86: 45741 | C86: 45741 | D86: ="Q"&ROUNDUP(MONTH(B86)/3,0)&"-"&YEAR(B86) -> Q1-2025 | E86: 45764 | F86: 45764 | G86: =E86-B86 -> 23 | H86: =F86-B86 -> 23 | I86: =IF(H86<=7, "Yes", "No") -> No | J86: =_xlfn.MINIFS($B$2:$B$633, $L$2:$L$633, L86) -> 44945 | K86: Europe | L86: United Kingdom | M86: London | N86: =_xlfn.TEXTJOIN(" - ", TRUE, K86:M86) -> Europe - United Kingdom - London | O86: Consumer | P86: Retail | Q86: H. Kim | R86: Networking | S86: NET-7166 | T86: 1421.19 | U86: 1808.26 | V86: =ABS(U86) -> 1808.26 | W86: =IF(V86 <= _xlfn.PERCENTILE.INC($V$2:$V$633, 0.33), "Low", IF(V86 <= _xlfn.PERCENTILE.INC($V$2:$V$633, 0.67), "Medium", "High")) -> High | X86: 0.104 | Y86: =IF(X86>30%,AVERAGEIF($X$2:$X$633,"<30%"),X86) -> 0.104 | Z86: =IF(Y86>0.2, "Yes", "No") -> No | AA86: 13 | AB86: =U86*AA86*(1-Y86) -> 21062.612 | AC86: =T86*AA86 -> 18475.47 | AD86: =AB86-AC86 -> 2587.1425 | AE86: =IF(AB86=0, 0, AD86 / AB86) -> 0.12283103 | AF86: =MIN(Y86,'Scenario Modeling'!$B$2) -> 0.104 | AG86: =ROUND(AA86 * (1 + 'Scenario Modeling'!$B$4), 0) -> 13 | AH86: =T86 * (1 + 'Scenario Modeling'!$B$3) -> 1421.19 | AI86: =V86 * AG86 * (1 - AF86) -> 21062.612 | AJ86: =AI86 - (AH86 * AG86) -> 2587.1425
A87: ORD-2023-841426 | B87: 45282 | C87: 45282 | D87: ="Q"&ROUNDUP(MONTH(B87)/3,0)&"-"&YEAR(B87) -> Q4-2023 | E87: 45283 | F87: 45283 | G87: =E87-B87 -> 1 | H87: =F87-B87 -> 1 | I87: =IF(H87<=7, "Yes", "No") -> Yes | J87: =_xlfn.MINIFS($B$2:$B$633, $L$2:$L$633, L87) -> 44933 | K87: Africa | L87: South Africa | M87: Cape Town | N87: =_xlfn.TEXTJOIN(" - ", TRUE, K87:M87) -> Africa - South Africa - Cape Town | O87: Non-Profit | P87: Marketplace | Q87: D. Smith | R87: Components | S87: CMP-4531 | T87: 1186.18 | U87: 1285.09 | V87: =ABS(U87) -> 1285.09 | W87: =IF(V87 <= _xlfn.PERCENTILE.INC($V$2:$V$633, 0.33), "Low", IF(V87 <= _xlfn.PERCENTILE.INC($V$2:$V$633, 0.67), "Medium", "High")) -> Medium | X87: 0.07 | Y87: =IF(X87>30%,AVERAGEIF($X$2:$X$633,"<30%"),X87) -> 0.07 | Z87: =IF(Y87>0.2, "Yes", "No") -> No | AA87: 11 | AB87: =U87*AA87*(1-Y87) -> 13146.471 | AC87: =T87*AA87 -> 13047.98 | AD87: =AB87-AC87 -> 98.4907 | AE87: =IF(AB87=0, 0, AD87 / AB87) -> 0.0074917978 | AF87: =MIN(Y87,'Scenario Modeling'!$B$2) -> 0.07 | AG87: =ROUND(AA87 * (1 + 'Scenario Modeling'!$B$4), 0) -> 11 | AH87: =T87 * (1 + 'Scenario Modeling'!$B$3) -> 1186.18 | AI87: =V87 * AG87 * (1 - AF87) -> 13146.471 | AJ87: =AI87 - (AH87 * AG87) -> 98.4907
A88: ORD-2024-594592 | B88: 45388 | C88: 45388 | D88: ="Q"&ROUNDUP(MONTH(B88)/3,0)&"-"&YEAR(B88) -> Q2-2024 | E88: 45407 | F88: 45407 | G88: =E88-B88 -> 19 | H88: =F88-B88 -> 19 | I88: =IF(H88<=7, "Yes", "No") -> No | J88: =_xlfn.MINIFS($B$2:$B$633, $L$2:$L$633, L88) -> 44938 | K88: Asia | L88: China | M88: Shanghai | N88: =_xlfn.TEXTJOIN(" - ", TRUE, K88:M88) -> Asia - China - Shanghai | O88: Corporate | P88: Retail | Q88: K. Singh | R88: Components | S88: CMP-8196 | T88: 1366.48 | U88: 1678.14 | V88: =ABS(U88) -> 1678.14 | W88: =IF(V88 <= _xlfn.PERCENTILE.INC($V$2:$V$633, 0.33), "Low", IF(V88 <= _xlfn.PERCENTILE.INC($V$2:$V$633, 0.67), "Medium", "High")) -> High | X88: 0.154 | Y88: =IF(X88>30%,AVERAGEIF($X$2:$X$633,"<30%"),X88) -> 0.154 | Z88: =IF(Y88>0.2, "Yes", "No") -> No | AA88: 10 | AB88: =U88*AA88*(1-Y88) -> 14197.064 | AC88: =T88*AA88 -> 13664.8 | AD88: =AB88-AC88 -> 532.2644 | AE88: =IF(AB88=0, 0, AD88 / AB88) -> 0.037491159 | AF88: =MIN(Y88,'Scenario Modeling'!$B$2) -> 0.154 | AG88: =ROUND(AA88 * (1 + 'Scenario Modeling'!$B$4), 0) -> 10 | AH88: =T88 * (1 + 'Scenario Modeling'!$B$3) -> 1366.48 | AI88: =V88 * AG88 * (1 - AF88) -> 14197.064 | AJ88: =AI88 - (AH88 * AG88) -> 532.2644
A89: ORD-2025-863978 | B89: 45876 | C89: 45876 | D89: ="Q"&ROUNDUP(MONTH(B89)/3,0)&"-"&YEAR(B89) -> Q3-2025 | E89: 45888 | F89: 45888 | G89: =E89-B89 -> 12 | H89: =F89-B89 -> 12 | I89: =IF(H89<=7, "Yes", "No") -> No | J89: =_xlfn.MINIFS($B$2:$B$633, $L$2:$L$633, L89) -> 44946 | K89: Africa | L89: Kenya | M89: Nakuru | N89: =_xlfn.TEXTJOIN(" - ", TRUE, K89:M89) -> Africa - Kenya - Nakuru | O89: Corporate | P89: Direct | Q89: M. Rossi | R89: Components | S89: CMP-2854 | T89: 601.51 | U89: 679.35 | V89: =ABS(U89) -> 679.35 | W89: =IF(V89 <= _xlfn.PERCENTILE.INC($V$2:$V$633, 0.33), "Low", IF(V89 <= _xlfn.PERCENTILE.INC($V$2:$V$633, 0.67), "Medium", "High")) -> Low | X89: 0.188 | Y89: =IF(X89>30%,AVERAGEIF($X$2:$X$633,"<30%"),X89) -> 0.188 | Z89: =IF(Y89>0.2, "Yes", "No") -> No | AA89: 3 | AB89: =U89*AA89*(1-Y89) -> 1654.8966 | AC89: =T89*AA89 -> 1804.53 | AD89: =AB89-AC89 -> -149.6334 | AE89: =IF(AB89=0, 0, AD89 / AB89) -> -0.09041858 | AF89: =MIN(Y89,'Scenario Modeling'!$B$2) -> 0.188 | AG89: =ROUND(AA89 * (1 + 'Scenario Modeling'!$B$4), 0) -> 3 | AH89: =T89 * (1 + 'Scenario Modeling'!$B$3) -> 601.51 | AI89: =V89 * AG89 * (1 - AF89) -> 1654.8966 | AJ89: =AI89 - (AH89 * AG89) -> -149.6334
A90: ORD-2024-604471 | B90: 45312 | C90: 45312 | D90: ="Q"&ROUNDUP(MONTH(B90)/3,0)&"-"&YEAR(B90) -> Q1-2024 | E90: 45316 | F90: 45316 | G90: =E90-B90 -> 4 | H90: =F90-B90 -> 4 | I90: =IF(H90<=7, "Yes", "No") -> Yes | J90: =_xlfn.MINIFS($B$2:$B$633, $L$2:$L$633, L90) -> 44955 | K90: Asia | L90: India | M90: Delhi | N90: =_xlfn.TEXTJOIN(" - ", TRUE, K90:M90) -> Asia - India - Delhi | O90: Consumer | P90: Direct | Q90: C. Otieno | R90: Monitors | S90: MON-8973 | T90: 523.7 | U90: 1109.92 | V90: =ABS(U90) -> 1109.92 | W90: =IF(V90 <= _xlfn.PERCENTILE.INC($V$2:$V$633, 0.33), "Low", IF(V90 <= _xlfn.PERCENTILE.INC($V$2:$V$633, 0.67), "Medium", "High")) -> Medium | X90: 0.03 | Y90: =IF(X90>30%,AVERAGEIF($X$2:$X$633,"<30%"),X90) -> 0.03 | Z90: =IF(Y90>0.2, "Yes", "No") -> No | AA90: 11 | AB90: =U90*AA90*(1-Y90) -> 11842.846 | AC90: =T90*AA90 -> 5760.7 | AD90: =AB90-AC90 -> 6082.1464 | AE90: =IF(AB90=0, 0, AD90 / AB90) -> 0.51357133 | AF90: =MIN(Y90,'Scenario Modeling'!$B$2) -> 0.03 | AG90: =ROUND(AA90 * (1 + 'Scenario Modeling'!$B$4), 0) -> 11 | AH90: =T90 * (1 + 'Scenario Modeling'!$B$3) -> 523.7 | AI90: =V90 * AG90 * (1 - AF90) -> 11842.846 | AJ90: =AI90 - (AH90 * AG90) -> 6082.1464
A91: ORD-2023-258768 | B91: 45106 | C91: 45106 | D91: ="Q"&ROUNDUP(MONTH(B91)/3,0)&"-"&YEAR(B91) -> Q2-2023 | E91: 45109 | F91: 45109 | G91: =E91-B91 -> 3 | H91: =F91-B91 -> 3 | I91: =IF(H91<=7, "Yes", "No") -> Yes | J91: =_xlfn.MINIFS($B$2:$B$633, $L$2:$L$633, L91) -> 44988 | K91: Asia | L91: Japan | M91: Nagoya | N91: =_xlfn.TEXTJOIN(" - ", TRUE, K91:M91) -> Asia - Japan - Nagoya | O91: Education | P91: Marketplace | Q91: F. Müller | R91: Monitors | S91: MON-2990 | T91: 55.65 | U91: 83.57 | V91: =ABS(U91) -> 83.57 | W91: =IF(V91 <= _xlfn.PERCENTILE.INC($V$2:$V$633, 0.33), "Low", IF(V91 <= _xlfn.PERCENTILE.INC($V$2:$V$633, 0.67), "Medium", "High")) -> Low | X91: 0.066 | Y91: =IF(X91>30%,AVERAGEIF($X$2:$X$633,"<30%"),X91) -> 0.066 | Z91: =IF(Y91>0.2, "Yes", "No") -> No | AA91: 8 | AB91: =U91*AA91*(1-Y91) -> 624.43504 | AC91: =T91*AA91 -> 445.2 | AD91: =AB91-AC91 -> 179.23504 | AE91: =IF(AB91=0, 0, AD91 / AB91) -> 0.28703553 | AF91: =MIN(Y91,'Scenario Modeling'!$B$2) -> 0.066 | AG91: =ROUND(AA91 * (1 + 'Scenario Modeling'!$B$4), 0) -> 8 | AH91: =T91 * (1 + 'Scenario Modeling'!$B$3) -> 55.65 | AI91: =V91 * AG91 * (1 - AF91) -> 624.43504 | AJ91: =AI91 - (AH91 * AG91) -> 179.23504
A92: ORD-2025-626047 | B92: 45775 | C92: 45775 | D92: ="Q"&ROUNDUP(MONTH(B92)/3,0)&"-"&YEAR(B92) -> Q2-2025 | E92: 45792 | F92: 45792 | G92: =E92-B92 -> 17 | H92: =F92-B92 -> 17 | I92: =IF(H92<=7, "Yes", "No") -> No | J92: =_xlfn.MINIFS($B$2:$B$633, $L$2:$L$633, L92) -> 44988 | K92: Asia | L92: Japan | M92: Nagoya | N92: =_xlfn.TEXTJOIN(" - ", TRUE, K92:M92) -> Asia - Japan - Nagoya | O92: Education | P92: Direct | Q92: N. Brown | R92: Networking | S92: NET-1966 | T92: 691.19 | U92: 1284.3 | V92: =ABS(U92) -> 1284.3 | W92: =IF(V92 <= _xlfn.PERCENTILE.INC($V$2:$V$633, 0.33), "Low", IF(V92 <= _xlfn.PERCENTILE.INC($V$2:$V$633, 0.67), "Medium", "High")) -> Medium | X92: 0.074 | Y92: =IF(X92>30%,AVERAGEIF($X$2:$X$633,"<30%"),X92) -> 0.074 | Z92: =IF(Y92>0.2, "Yes", "No") -> No | AA92: 7 | AB92: =U92*AA92*(1-Y92) -> 8324.8326 | AC92: =T92*AA92 -> 4838.33 | AD92: =AB92-AC92 -> 3486.5026 | AE92: =IF(AB92=0, 0, AD92 / AB92) -> 0.41880753 | AF92: =MIN(Y92,'Scenario Modeling'!$B$2) -> 0.074 | AG92: =ROUND(AA92 * (1 + 'Scenario Modeling'!$B$4), 0) -> 7 | AH92: =T92 * (1 + 'Scenario Modeling'!$B$3) -> 691.19 | AI92: =V92 * AG92 * (1 - AF92) -> 8324.8326 | AJ92: =AI92 - (AH92 * AG92) -> 3486.5026
A93: ORD-2025-526752 | B93: 45817 | C93: 45817 | D93: ="Q"&ROUNDUP(MONTH(B93)/3,0)&"-"&YEAR(B93) -> Q2-2025 | E93: 45833 | F93: 45833 | G93: =E93-B93 -> 16 | H93: =F93-B93 -> 16 | I93: =IF(H93<=7, "Yes", "No") -> No | J93: =_xlfn.MINIFS($B$2:$B$633, $L$2:$L$633, L93) -> 44955 | K93: Asia | L93: India | M93: Hyderabad | N93: =_xlfn.TEXTJOIN(" - ", TRUE, K93:M93) -> Asia - India - Hyderabad | O93: Enterprise | P93: Distributor | Q93: M. Rossi | R93: Phones | S93: PHN-3482 | T93: 527.33 | U93: 911.72 | V93: =ABS(U93) -> 911.72 | W93: =IF(V93 <= _xlfn.PERCENTILE.INC($V$2:$V$633, 0.33), "Low", IF(V93 <= _xlfn.PERCENTILE.INC($V$2:$V$633, 0.67), "Medium", "High")) -> Medium | X93: 0.144 | Y93: =IF(X93>30%,AVERAGEIF($X$2:$X$633,"<30%"),X93) -> 0.144 | Z93: =IF(Y93>0.2, "Yes", "No") -> No | AA93: 25 | AB93: =U93*AA93*(1-Y93) -> 19510.808 | AC93: =T93*AA93 -> 13183.25 | AD93: =AB93-AC93 -> 6327.558 | AE93: =IF(AB93=0, 0, AD93 / AB93) -> 0.3243104 | AF93: =MIN(Y93,'Scenario Modeling'!$B$2) -> 0.144 | AG93: =ROUND(AA93 * (1 + 'Scenario Modeling'!$B$4), 0) -> 25 | AH93: =T93 * (1 + 'Scenario Modeling'!$B$3) -> 527.33 | AI93: =V93 * AG93 * (1 - AF93) -> 19510.808 | AJ93: =AI93 - (AH93 * AG93) -> 6327.558
A94: ORD-2023-374486 | B94: 45101 | C94: 45101 | D94: ="Q"&ROUNDUP(MONTH(B94)/3,0)&"-"&YEAR(B94) -> Q2-2023 | E94: 45100 | F94: =B94+13 -> 45114 | G94: =E94-B94 -> -1 | H94: =F94-B94 -> 13 | I94: =IF(H94<=7, "Yes", "No") -> No | J94: =_xlfn.MINIFS($B$2:$B$633, $L$2:$L$633, L94) -> 44955 | K94: Americas | L94: Brazil | M94: Rio de Janeiro | N94: =_xlfn.TEXTJOIN(" - ", TRUE, K94:M94) -> Americas - Brazil - Rio de Janeiro | O94: Non-Profit | P94: Retail | Q94: E. Garcia | R94: Printers | S94: PRN-6490 | T94: 804.01 | U94: 1405.07 | V94: =ABS(U94) -> 1405.07 | W94: =IF(V94 <= _xlfn.PERCENTILE.INC($V$2:$V$633, 0.33), "Low", IF(V94 <= _xlfn.PERCENTILE.INC($V$2:$V$633, 0.67), "Medium", "High")) -> Medium | X94: 0.096 | Y94: =IF(X94>30%,AVERAGEIF($X$2:$X$633,"<30%"),X94) -> 0.096 | Z94: =IF(Y94>0.2, "Yes", "No") -> No | AA94: 8 | AB94: =U94*AA94*(1-Y94) -> 10161.466 | AC94: =T94*AA94 -> 6432.08 | AD94: =AB94-AC94 -> 3729.3862 | AE94: =IF(AB94=0, 0, AD94 / AB94) -> 0.36701261 | AF94: =MIN(Y94,'Scenario Modeling'!$B$2) -> 0.096 | AG94: =ROUND(AA94 * (1 + 'Scenario Modeling'!$B$4), 0) -> 8 | AH94: =T94 * (1 + 'Scenario Modeling'!$B$3) -> 804.01 | AI94: =V94 * AG94 * (1 - AF94) -> 10161.466 | AJ94: =AI94 - (AH94 * AG94) -> 3729.3862
A95: ORD-2024-997336 | B95: 45569 | C95: 45569 | D95: ="Q"&ROUNDUP(MONTH(B95)/3,0)&"-"&YEAR(B95) -> Q4-2024 | E95: 45598 | F95: 45598 | G95: =E95-B95 -> 29 | H95: =F95-B95 -> 29 | I95: =IF(H95<=7, "Yes", "No") -> No | J95: =_xlfn.MINIFS($B$2:$B$633, $L$2:$L$633, L95) -> 44941 | K95: Africa | L95: Nigeria | M95: Abuja | N95: =_xlfn.TEXTJOIN(" - ", TRUE, K95:M95) -> Africa - Nigeria - Abuja | O95: Corporate | P95: Distributor | Q95: F. Müller | R95: Accessories | S95: ACC-9038 | T95: 412.09 | U95: 968.94 | V95: =ABS(U95) -> 968.94 | W95: =IF(V95 <= _xlfn.PERCENTILE.INC($V$2:$V$633, 0.33), "Low", IF(V95 <= _xlfn.PERCENTILE.INC($V$2:$V$633, 0.67), "Medium", "High")) -> Medium | X95: 0.099 | Y95: =IF(X95>30%,AVERAGEIF($X$2:$X$633,"<30%"),X95) -> 0.099 | Z95: =IF(Y95>0.2, "Yes", "No") -> No | AA95: 23 | AB95: =U95*AA95*(1-Y95) -> 20079.344 | AC95: =T95*AA95 -> 9478.07 | AD95: =AB95-AC95 -> 10601.274 | AE95: =IF(AB95=0, 0, AD95 / AB95) -> 0.52796913 | AF95: =MIN(Y95,'Scenario Modeling'!$B$2) -> 0.099 | AG95: =ROUND(AA95 * (1 + 'Scenario Modeling'!$B$4), 0) -> 23 | AH95: =T95 * (1 + 'Scenario Modeling'!$B$3) -> 412.09 | AI95: =V95 * AG95 * (1 - AF95) -> 20079.344 | AJ95: =AI95 - (AH95 * AG95) -> 10601.274
A96: ORD-2025-725646 | B96: 45910 | C96: 45910 | D96: ="Q"&ROUNDUP(MONTH(B96)/3,0)&"-"&YEAR(B96) -> Q3-2025 | E96: 45930 | F96: 45930 | G96: =E96-B96 -> 20 | H96: =F96-B96 -> 20 | I96: =IF(H96<=7, "Yes", "No") -> No | J96: =_xlfn.MINIFS($B$2:$B$633, $L$2:$L$633, L96) -> 44946 | K96: Africa | L96: Kenya | M96: Mombasa | N96: =_xlfn.TEXTJOIN(" - ", TRUE, K96:M96) -> Africa - Kenya - Mombasa | O96: Corporate | P96: Direct | Q96: L. Okafor | R96: Phones | S96: PHN-6954 | T96: 1009.48 | U96: 1088.81 | V96: =ABS(U96) -> 1088.81 | W96: =IF(V96 <= _xlfn.PERCENTILE.INC($V$2:$V$633, 0.33), "Low", IF(V96 <= _xlfn.PERCENTILE.INC($V$2:$V$633, 0.67), "Medium", "High")) -> Medium | X96: 0.16 | Y96: =IF(X96>30%,AVERAGEIF($X$2:$X$633,"<30%"),X96) -> 0.16 | Z96: =IF(Y96>0.2, "Yes", "No") -> No | AA96: 6 | AB96: =U96*AA96*(1-Y96) -> 5487.6024 | AC96: =T96*AA96 -> 6056.88 | AD96: =AB96-AC96 -> -569.2776 | AE96: =IF(AB96=0, 0, AD96 / AB96) -> -0.10373886 | AF96: =MIN(Y96,'Scenario Modeling'!$B$2) -> 0.16 | AG96: =ROUND(AA96 * (1 + 'Scenario Modeling'!$B$4), 0) -> 6 | AH96: =T96 * (1 + 'Scenario Modeling'!$B$3) -> 1009.48 | AI96: =V96 * AG96 * (1 - AF96) -> 5487.6024 | AJ96: =AI96 - (AH96 * AG96) -> -569.2776
A97: ORD-2023-868734 | B97: 45022 | C97: 45022 | D97: ="Q"&ROUNDUP(MONTH(B97)/3,0)&"-"&YEAR(B97) -> Q2-2023 | E97: 45043 | F97: 45043 | G97: =E97-B97 -> 21 | H97: =F97-B97 -> 21 | I97: =IF(H97<=7, "Yes", "No") -> No | J97: =_xlfn.MINIFS($B$2:$B$633, $L$2:$L$633, L97) -> 44945 | K97: Europe | L97: United Kingdom | M97: Manchester | N97: =_xlfn.TEXTJOIN(" - ", TRUE, K97:M97) -> Europe - United Kingdom - Manchester | O97: Enterprise | P97: Distributor | Q97: I. Johnson | R97: Printers | S97: PRN-8970 | T97: 1084.79 | U97: 2484.99 | V97: =ABS(U97) -> 2484.99 | W97: =IF(V97 <= _xlfn.PERCENTILE.INC($V$2:$V$633, 0.33), "Low", IF(V97 <= _xlfn.PERCENTILE.INC($V$2:$V$633, 0.67), "Medium", "High")) -> High | X97: 0.034 | Y97: =IF(X97>30%,AVERAGEIF($X$2:$X$633,"<30%"),X97) -> 0.034 | Z97: =IF(Y97>0.2, "Yes", "No") -> No | AA97: 18 | AB97: =U97*AA97*(1-Y97) -> 43209.006 | AC97: =T97*AA97 -> 19526.22 | AD97: =AB97-AC97 -> 23682.786 | AE97: =IF(AB97=0, 0, AD97 / AB97) -> 0.54809838 | AF97: =MIN(Y97,'Scenario Modeling'!$B$2) -> 0.034 | AG97: =ROUND(AA97 * (1 + 'Scenario Modeling'!$B$4), 0) -> 18 | AH97: =T97 * (1 + 'Scenario Modeling'!$B$3) -> 1084.79 | AI97: =V97 * AG97 * (1 - AF97) -> 43209.006 | AJ97: =AI97 - (AH97 * AG97) -> 23682.786
A98: ORD-2025-262491 | B98: 45870 | C98: 45870 | D98: ="Q"&ROUNDUP(MONTH(B98)/3,0)&"-"&YEAR(B98) -> Q3-2025 | E98: 45885 | F98: 45885 | G98: =E98-B98 -> 15 | H98: =F98-B98 -> 15 | I98: =IF(H98<=7, "Yes", "No") -> No | J98: =_xlfn.MINIFS($B$2:$B$633, $L$2:$L$633, L98) -> 44955 | K98: Asia | L98: India | M98: Delhi | N98: =_xlfn.TEXTJOIN(" - ", TRUE, K98:M98) -> Asia - India - Delhi | O98: Enterprise | P98: Direct | Q98: O. Wang | R98: Monitors | S98: MON-1822 | T98: 24.44 | U98: 28.69 | V98: =ABS(U98) -> 28.69 | W98: =IF(V98 <= _xlfn.PERCENTILE.INC($V$2:$V$633, 0.33), "Low", IF(V98 <= _xlfn.PERCENTILE.INC($V$2:$V$633, 0.67), "Medium", "High")) -> Low | X98: 0.146 | Y98: =IF(X98>30%,AVERAGEIF($X$2:$X$633,"<30%"),X98) -> 0.146 | Z98: =IF(Y98>0.2, "Yes", "No") -> No | AA98: 6 | AB98: =U98*AA98*(1-Y98) -> 147.00756 | AC98: =T98*AA98 -> 146.64 | AD98: =AB98-AC98 -> 0.36756 | AE98: =IF(AB98=0, 0, AD98 / AB98) -> 0.0025002796 | AF98: =MIN(Y98,'Scenario Modeling'!$B$2) -> 0.146 | AG98: =ROUND(AA98 * (1 + 'Scenario Modeling'!$B$4), 0) -> 6 | AH98: =T98 * (1 + 'Scenario Modeling'!$B$3) -> 24.44 | AI98: =V98 * AG98 * (1 - AF98) -> 147.00756 | AJ98: =AI98 - (AH98 * AG98) -> 0.36756
A99: ORD-2024-638884 | B99: 45440 | C99: 45440 | D99: ="Q"&ROUNDUP(MONTH(B99)/3,0)&"-"&YEAR(B99) -> Q2-2024 | E99: 45438 | F99: =B99+3 -> 45443 | G99: =E99-B99 -> -2 | H99: =F99-B99 -> 3 | I99: =IF(H99<=7, "Yes", "No") -> Yes | J99: =_xlfn.MINIFS($B$2:$B$633, $L$2:$L$633, L99) -> 44941 | K99: Africa | L99: Nigeria | M99: Abuja | N99: =_xlfn.TEXTJOIN(" - ", TRUE, K99:M99) -> Africa - Nigeria - Abuja | O99: Enterprise | P99: Online | Q99: F. Müller | R99: Accessories | S99: ACC-5177 | T99: 1227.08 | U99: 1896.62 | V99: =ABS(U99) -> 1896.62 | W99: =IF(V99 <= _xlfn.PERCENTILE.INC($V$2:$V$633, 0.33), "Low", IF(V99 <= _xlfn.PERCENTILE.INC($V$2:$V$633, 0.67), "Medium", "High")) -> High | X99: 0 | Y99: =IF(X99>30%,AVERAGEIF($X$2:$X$633,"<30%"),X99) -> 0 | Z99: =IF(Y99>0.2, "Yes", "No") -> No | AA99: 18 | AB99: =U99*AA99*(1-Y99) -> 34139.16 | AC99: =T99*AA99 -> 22087.44 | AD99: =AB99-AC99 -> 12051.72 | AE99: =IF(AB99=0, 0, AD99 / AB99) -> 0.35301747 | AF99: =MIN(Y99,'Scenario Modeling'!$B$2) -> 0 | AG99: =ROUND(AA99 * (1 + 'Scenario Modeling'!$B$4), 0) -> 18 | AH99: =T99 * (1 + 'Scenario Modeling'!$B$3) -> 1227.08 | AI99: =V99 * AG99 * (1 - AF99) -> 34139.16 | AJ99: =AI99 - (AH99 * AG99) -> 12051.72
A100: ORD-2025-541501 | B100: 45860 | C100: 45860 | D100: ="Q"&ROUNDUP(MONTH(B100)/3,0)&"-"&YEAR(B100) -> Q3-2025 | E100: 45887 | F100: 45887 | G100: =E100-B100 -> 27 | H100: =F100-B100 -> 27 | I100: =IF(H100<=7, "Yes", "No") -> No | J100: =_xlfn.MINIFS($B$2:$B$633, $L$2:$L$633, L100) -> 44938 | K100: Asia | L100: China | M100: Shenzhen | N100: =_xlfn.TEXTJOIN(" - ", TRUE, K100:M100) -> Asia - China - Shenzhen | O100: Non-Profit | P100: Marketplace | Q100: M. Rossi | R100: Networking | S100: NET-1804 | T100: 547.32 | U100: 419.17 | V100: =ABS(U100) -> 419.17 | W100: =IF(V100 <= _xlfn.PERCENTILE.INC($V$2:$V$633, 0.33), "Low", IF(V100 <= _xlfn.PERCENTILE.INC($V$2:$V$633, 0.67), "Medium", "High")) -> Low | X100: 0.092 | Y100: =IF(X100>30%,AVERAGEIF($X$2:$X$633,"<30%"),X100) -> 0.092 | Z100: =IF(Y100>0.2, "Yes", "No") -> No | AA100: 14 | AB100: =U100*AA100*(1-Y100) -> 5328.489 | AC100: =T100*AA100 -> 7662.48 | AD100: =AB100-AC100 -> -2333.991 | AE100: =IF(AB100=0, 0, AD100 / AB100) -> -0.43802116 | AF100: =MIN(Y100,'Scenario Modeling'!$B$2) -> 0.092 | AG100: =ROUND(AA100 * (1 + 'Scenario Modeling'!$B$4), 0) -> 14 | AH100: =T100 * (1 + 'Scenario Modeling'!$B$3) -> 547.32 | AI100: =V100 * AG100 * (1 - AF100) -> 5328.489 | AJ100: =AI100 - (AH100 * AG100) -> -2333.991
A101: ORD-2023-422918 | B101: 44985 | C101: 44985 | D101: ="Q"&ROUNDUP(MONTH(B101)/3,0)&"-"&YEAR(B101) -> Q1-2023 | E101: 45005 | F101: 45005 | G101: =E101-B101 -> 20 | H101: =F101-B101 -> 20 | I101: =IF(H101<=7, "Yes", "No") -> No | J101: =_xlfn.MINIFS($B$2:$B$633, $L$2:$L$633, L101) -> 44948 | K101: Europe | L101: Germany | M101: Berlin | N101: =_xlfn.TEXTJOIN(" - ", TRUE, K101:M101) -> Europe - Germany - Berlin | O101: Small Business | P101: Direct | Q101: H. Kim | R101: Laptops | S101: LAP-3679 | T101: 1200.78 | U101: 2001.17 | V101: =ABS(U101) -> 2001.17 | W101: =IF(V101 <= _xlfn.PERCENTILE.INC($V$2:$V$633, 0.33), "Low", IF(V101 <= _xlfn.PERCENTILE.INC($V$2:$V$633, 0.67), "Medium", "High")) -> High | X101: 0.292 | Y101: =IF(X101>30%,AVERAGEIF($X$2:$X$633,"<30%"),X101) -> 0.292 | Z101: =IF(Y101>0.2, "Yes", "No") -> Yes | AA101: 18 | AB101: =U101*AA101*(1-Y101) -> 25502.91 | AC101: =T101*AA101 -> 21614.04 | AD101: =AB101-AC101 -> 3888.8705 | AE101: =IF(AB101=0, 0, AD101 / AB101) -> 0.15248732 | AF101: =MIN(Y101,'Scenario Modeling'!$B$2) -> 0.25 | AG101: =ROUND(AA101 * (1 + 'Scenario Modeling'!$B$4), 0) -> 18 | AH101: =T101 * (1 + 'Scenario Modeling'!$B$3) -> 1200.78 | AI101: =V101 * AG101 * (1 - AF101) -> 27015.795 | AJ101: =AI101 - (AH101 * AG101) -> 5401.755
A102: ORD-2025-328504 | B102: 45684 | C102: 45684 | D102: ="Q"&ROUNDUP(MONTH(B102)/3,0)&"-"&YEAR(B102) -> Q1-2025 | E102: 45703 | F102: 45703 | G102: =E102-B102 -> 19 | H102: =F102-B102 -> 19 | I102: =IF(H102<=7, "Yes", "No") -> No | J102: =_xlfn.MINIFS($B$2:$B$633, $L$2:$L$633, L102) -> 44938 | K102: Asia | L102: China | M102: Shenzhen | N102: =_xlfn.TEXTJOIN(" - ", TRUE, K102:M102) -> Asia - China - Shenzhen | O102: Non-Profit | P102: Direct | Q102: L. Okafor | R102: Phones | S102: PHN-8368 | T102: 1253.22 | U102: 3104.71 | V102: =ABS(U102) -> 3104.71 | W102: =IF(V102 <= _xlfn.PERCENTILE.INC($V$2:$V$633, 0.33), "Low", IF(V102 <= _xlfn.PERCENTILE.INC($V$2:$V$633, 0.67), "Medium", "High")) -> High | X102: 0 | Y102: =IF(X102>30%,AVERAGEIF($X$2:$X$633,"<30%"),X102) -> 0 | Z102: =IF(Y102>0.2, "Yes", "No") -> No | AA102: 17 | AB102: =U102*AA102*(1-Y102) -> 52780.07 | AC102: =T102*AA102 -> 21304.74 | AD102: =AB102-AC102 -> 31475.33 | AE102: =IF(AB102=0, 0, AD102 / AB102) -> 0.59634877 | AF102: =MIN(Y102,'Scenario Modeling'!$B$2) -> 0 | AG102: =ROUND(AA102 * (1 + 'Scenario Modeling'!$B$4), 0) -> 17 | AH102: =T102 * (1 + 'Scenario Modeling'!$B$3) -> 1253.22 | AI102: =V102 * AG102 * (1 - AF102) -> 52780.07 | AJ102: =AI102 - (AH102 * AG102) -> 31475.33
A103: ORD-2024-851883 | B103: 45304 | C103: 45304 | D103: ="Q"&ROUNDUP(MONTH(B103)/3,0)&"-"&YEAR(B103) -> Q1-2024 | E103: 45313 | F103: 45313 | G103: =E103-B103 -> 9 | H103: =F103-B103 -> 9 | I103: =IF(H103<=7, "Yes", "No") -> No | J103: =_xlfn.MINIFS($B$2:$B$633, $L$2:$L$633, L103) -> 44955 | K103: Asia | L103: India | M103: Mumbai | N103: =_xlfn.TEXTJOIN(" - ", TRUE, K103:M103) -> Asia - India - Mumbai | O103: Enterprise | P103: Marketplace | Q103: J. Njeri | R103: Components | S103: CMP-8141 | T103: 313.6 | U103: 334.28 | V103: =ABS(U103) -> 334.28 | W103: =IF(V103 <= _xlfn.PERCENTILE.INC($V$2:$V$633, 0.33), "Low", IF(V103 <= _xlfn.PERCENTILE.INC($V$2:$V$633, 0.67), "Medium", "High")) -> Low | X103: 0.14 | Y103: =IF(X103>30%,AVERAGEIF($X$2:$X$633,"<30%"),X103) -> 0.14 | Z103: =IF(Y103>0.2, "Yes", "No") -> No | AA103: 22 | AB103: =U103*AA103*(1-Y103) -> 6324.5776 | AC103: =T103*AA103 -> 6899.2 | AD103: =AB103-AC103 -> -574.6224 | AE103: =IF(AB103=0, 0, AD103 / AB103) -> -0.090855459 | AF103: =MIN(Y103,'Scenario Modeling'!$B$2) -> 0.14 | AG103: =ROUND(AA103 * (1 + 'Scenario Modeling'!$B$4), 0) -> 22 | AH103: =T103 * (1 + 'Scenario Modeling'!$B$3) -> 313.6 | AI103: =V103 * AG103 * (1 - AF103) -> 6324.5776 | AJ103: =AI103 - (AH103 * AG103) -> -574.6224
A104: ORD-2025-662997 | B104: 45747 | C104: 45747 | D104: ="Q"&ROUNDUP(MONTH(B104)/3,0)&"-"&YEAR(B104) -> Q1-2025 | E104: 45751 | F104: 45751 | G104: =E104-B104 -> 4 | H104: =F104-B104 -> 4 | I104: =IF(H104<=7, "Yes", "No") -> Yes | J104: =_xlfn.MINIFS($B$2:$B$633, $L$2:$L$633, L104) -> 44946 | K104: Africa | L104: Kenya | M104: Nakuru | N104: =_xlfn.TEXTJOIN(" - ", TRUE, K104:M104) -> Africa - Kenya - Nakuru | O104: Corporate | P104: Direct | Q104: C. Otieno | R104: Laptops | S104: LAP-7136 | T104: 862.08 | U104: 1952.83 | V104: =ABS(U104) -> 1952.83 | W104: =IF(V104 <= _xlfn.PERCENTILE.INC($V$2:$V$633, 0.33), "Low", IF(V104 <= _xlfn.PERCENTILE.INC($V$2:$V$633, 0.67), "Medium", "High")) -> High | X104: 0 | Y104: =IF(X104>30%,AVERAGEIF($X$2:$X$633,"<30%"),X104) -> 0 | Z104: =IF(Y104>0.2, "Yes", "No") -> No | AA104: 7 | AB104: =U104*AA104*(1-Y104) -> 13669.81 | AC104: =T104*AA104 -> 6034.56 | AD104: =AB104-AC104 -> 7635.25 | AE104: =IF(AB104=0, 0, AD104 / AB104) -> 0.55854836 | AF104: =MIN(Y104,'Scenario Modeling'!$B$2) -> 0 | AG104: =ROUND(AA104 * (1 + 'Scenario Modeling'!$B$4), 0) -> 7 | AH104: =T104 * (1 + 'Scenario Modeling'!$B$3) -> 862.08 | AI104: =V104 * AG104 * (1 - AF104) -> 13669.81 | AJ104: =AI104 - (AH104 * AG104) -> 7635.25
A105: ORD-2024-478165 | B105: 45631 | C105: 45631 | D105: ="Q"&ROUNDUP(MONTH(B105)/3,0)&"-"&YEAR(B105) -> Q4-2024 | E105: 45654 | F105: 45654 | G105: =E105-B105 -> 23 | H105: =F105-B105 -> 23 | I105: =IF(H105<=7, "Yes", "No") -> No | J105: =_xlfn.MINIFS($B$2:$B$633, $L$2:$L$633, L105) -> 44928 | K105: Americas | L105: Canada | M105: Vancouver | N105: =_xlfn.TEXTJOIN(" - ", TRUE, K105:M105) -> Americas - Canada - Vancouver | O105: Corporate | P105: Direct | Q105: F. Müller | R105: Accessories | S105: ACC-2386 | T105: 107.03 | U105: 242.29 | V105: =ABS(U105) -> 242.29 | W105: =IF(V105 <= _xlfn.PERCENTILE.INC($V$2:$V$633, 0.33), "Low", IF(V105 <= _xlfn.PERCENTILE.INC($V$2:$V$633, 0.67), "Medium", "High")) -> Low | X105: 0.18 | Y105: =IF(X105>30%,AVERAGEIF($X$2:$X$633,"<30%"),X105) -> 0.18 | Z105: =IF(Y105>0.2, "Yes", "No") -> No | AA105: 30 | AB105: =U105*AA105*(1-Y105) -> 5960.334 | AC105: =T105*AA105 -> 3210.9 | AD105: =AB105-AC105 -> 2749.434 | AE105: =IF(AB105=0, 0, AD105 / AB105) -> 0.46128858 | AF105: =MIN(Y105,'Scenario Modeling'!$B$2) -> 0.18 | AG105: =ROUND(AA105 * (1 + 'Scenario Modeling'!$B$4), 0) -> 30 | AH105: =T105 * (1 + 'Scenario Modeling'!$B$3) -> 107.03 | AI105: =V105 * AG105 * (1 - AF105) -> 5960.334 | AJ105: =AI105 - (AH105 * AG105) -> 2749.434
A106: ORD-2024-771210 | B106: 45549 | C106: 45549 | D106: ="Q"&ROUNDUP(MONTH(B106)/3,0)&"-"&YEAR(B106) -> Q3-2024 | E106: 45570 | F106: 45570 | G106: =E106-B106 -> 21 | H106: =F106-B106 -> 21 | I106: =IF(H106<=7, "Yes", "No") -> No | J106: =_xlfn.MINIFS($B$2:$B$633, $L$2:$L$633, L106) -> 44938 | K106: Asia | L106: China | M106: Shanghai | N106: =_xlfn.TEXTJOIN(" - ", TRUE, K106:M106) -> Asia - China - Shanghai | O106: Small Business | P106: Online | Q106: H. Kim | R106: Laptops | S106: LAP-5150 | T106: 1405.56 | U106: 2968.87 | V106: =ABS(U106) -> 2968.87 | W106: =IF(V106 <= _xlfn.PERCENTILE.INC($V$2:$V$633, 0.33), "Low", IF(V106 <= _xlfn.PERCENTILE.INC($V$2:$V$633, 0.67), "Medium", "High")) -> High | X106: 0.169 | Y106: =IF(X106>30%,AVERAGEIF($X$2:$X$633,"<30%"),X106) -> 0.169 | Z106: =IF(Y106>0.2, "Yes", "No") -> No | AA106: 5 | AB106: =U106*AA106*(1-Y106) -> 12335.655 | AC106: =T106*AA106 -> 7027.8 | AD106: =AB106-AC106 -> 5307.8548 | AE106: =IF(AB106=0, 0, AD106 / AB106) -> 0.43028562 | AF106: =MIN(Y106,'Scenario Modeling'!$B$2) -> 0.169 | AG106: =ROUND(AA106 * (1 + 'Scenario Modeling'!$B$4), 0) -> 5 | AH106: =T106 * (1 + 'Scenario Modeling'!$B$3) -> 1405.56 | AI106: =V106 * AG106 * (1 - AF106) -> 12335.655 | AJ106: =AI106 - (AH106 * AG106) -> 5307.8548
A107: ORD-2024-155337 | B107: 45433 | C107: 45433 | D107: ="Q"&ROUNDUP(MONTH(B107)/3,0)&"-"&YEAR(B107) -> Q2-2024 | E107: 45439 | F107: 45439 | G107: =E107-B107 -> 6 | H107: =F107-B107 -> 6 | I107: =IF(H107<=7, "Yes", "No") -> Yes | J107: =_xlfn.MINIFS($B$2:$B$633, $L$2:$L$633, L107) -> 44933 | K107: Africa | L107: South Africa | M107: Johannesburg | N107: =_xlfn.TEXTJOIN(" - ", TRUE, K107:M107) -> Africa - South Africa - Johannesburg | O107: Non-Profit | P107: Online | Q107: M. Rossi | R107: Components | S107: CMP-8101 | T107: 1157.51 | U107: 1394.3 | V107: =ABS(U107) -> 1394.3 | W107: =IF(V107 <= _xlfn.PERCENTILE.INC($V$2:$V$633, 0.33), "Low", IF(V107 <= _xlfn.PERCENTILE.INC($V$2:$V$633, 0.67), "Medium", "High")) -> Medium | X107: 0.278 | Y107: =IF(X107>30%,AVERAGEIF($X$2:$X$633,"<30%"),X107) -> 0.278 | Z107: =IF(Y107>0.2, "Yes", "No") -> Yes | AA107: 12 | AB107: =U107*AA107*(1-Y107) -> 12080.215 | AC107: =T107*AA107 -> 13890.12 | AD107: =AB107-AC107 -> -1809.9048 | AE107: =IF(AB107=0, 0, AD107 / AB107) -> -0.14982389 | AF107: =MIN(Y107,'Scenario Modeling'!$B$2) -> 0.25 | AG107: =ROUND(AA107 * (1 + 'Scenario Modeling'!$B$4), 0) -> 12 | AH107: =T107 * (1 + 'Scenario Modeling'!$B$3) -> 1157.51 | AI107: =V107 * AG107 * (1 - AF107) -> 12548.7 | AJ107: =AI107 - (AH107 * AG107) -> -1341.42
A108: ORD-2023-251563 | B108: 45057 | C108: 45057 | D108: ="Q"&ROUNDUP(MONTH(B108)/3,0)&"-"&YEAR(B108) -> Q2-2023 | E108: 45084 | F108: 45084 | G108: =E108-B108 -> 27 | H108: =F108-B108 -> 27 | I108: =IF(H108<=7, "Yes", "No") -> No | J108: =_xlfn.MINIFS($B$2:$B$633, $L$2:$L$633, L108) -> 44946 | K108: Africa | L108: Kenya | M108: Mombasa | N108: =_xlfn.TEXTJOIN(" - ", TRUE, K108:M108) -> Africa - Kenya - Mombasa | O108: Corporate | P108: Online | Q108: J. Njeri | R108: Phones | S108: PHN-8970 | T108: 12.85 | U108: 15.41 | V108: =ABS(U108) -> 15.41 | W108: =IF(V108 <= _xlfn.PERCENTILE.INC($V$2:$V$633, 0.33), "Low", IF(V108 <= _xlfn.PERCENTILE.INC($V$2:$V$633, 0.67), "Medium", "High")) -> Low | X108: 0.137 | Y108: =IF(X108>30%,AVERAGEIF($X$2:$X$633,"<30%"),X108) -> 0.137 | Z108: =IF(Y108>0.2, "Yes", "No") -> No | AA108: 39 | AB108: =U108*AA108*(1-Y108) -> 518.65437 | AC108: =T108*AA108 -> 501.15 | AD108: =AB108-AC108 -> 17.50437 | AE108: =IF(AB108=0, 0, AD108 / AB108) -> 0.033749585 | AF108: =MIN(Y108,'Scenario Modeling'!$B$2) -> 0.137 | AG108: =ROUND(AA108 * (1 + 'Scenario Modeling'!$B$4), 0) -> 39 | AH108: =T108 * (1 + 'Scenario Modeling'!$B$3) -> 12.85 | AI108: =V108 * AG108 * (1 - AF108) -> 518.65437 | AJ108: =AI108 - (AH108 * AG108) -> 17.50437
A109: ORD-2024-286833 | B109: 45518 | C109: 45518 | D109: ="Q"&ROUNDUP(MONTH(B109)/3,0)&"-"&YEAR(B109) -> Q3-2024 | E109: 45539 | F109: 45539 | G109: =E109-B109 -> 21 | H109: =F109-B109 -> 21 | I109: =IF(H109<=7, "Yes", "No") -> No | J109: =_xlfn.MINIFS($B$2:$B$633, $L$2:$L$633, L109) -> 44945 | K109: Europe | L109: United Kingdom | M109: Manchester | N109: =_xlfn.TEXTJOIN(" - ", TRUE, K109:M109) -> Europe - United Kingdom - Manchester | O109: Non-Profit | P109: Online | Q109: J. Njeri | R109: Phones | S109: PHN-2341 | T109: 1138.8 | U109: 2250.81 | V109: =ABS(U109) -> 2250.81 | W109: =IF(V109 <= _xlfn.PERCENTILE.INC($V$2:$V$633, 0.33), "Low", IF(V109 <= _xlfn.PERCENTILE.INC($V$2:$V$633, 0.67), "Medium", "High")) -> High | X109: 0.123 | Y109: =IF(X109>30%,AVERAGEIF($X$2:$X$633,"<30%"),X109) -> 0.123 | Z109: =IF(Y109>0.2, "Yes", "No") -> No | AA109: 12 | AB109: =U109*AA109*(1-Y109) -> 23687.524 | AC109: =T109*AA109 -> 13665.6 | AD109: =AB109-AC109 -> 10021.924 | AE109: =IF(AB109=0, 0, AD109 / AB109) -> 0.42308872 | AF109: =MIN(Y109,'Scenario Modeling'!$B$2) -> 0.123 | AG109: =ROUND(AA109 * (1 + 'Scenario Modeling'!$B$4), 0) -> 12 | AH109: =T109 * (1 + 'Scenario Modeling'!$B$3) -> 1138.8 | AI109: =V109 * AG109 * (1 - AF109) -> 23687.524 | AJ109: =AI109 - (AH109 * AG109) -> 10021.924
A110: ORD-2024-792558 | B110: 45581 | C110: 45581 | D110: ="Q"&ROUNDUP(MONTH(B110)/3,0)&"-"&YEAR(B110) -> Q4-2024 | E110: 45604 | F110: 45604 | G110: =E110-B110 -> 23 | H110: =F110-B110 -> 23 | I110: =IF(H110<=7, "Yes", "No") -> No | J110: =_xlfn.MINIFS($B$2:$B$633, $L$2:$L$633, L110) -> 44988 | K110: Asia | L110: Japan | M110: Osaka | N110: =_xlfn.TEXTJOIN(" - ", TRUE, K110:M110) -> Asia - Japan - Osaka | O110: Small Business | P110: Retail | Q110: J. Njeri | R110: Networking | S110: NET-6387 | T110: 82.14 | U110: 166.04 | V110: =ABS(U110) -> 166.04 | W110: =IF(V110 <= _xlfn.PERCENTILE.INC($V$2:$V$633, 0.33), "Low", IF(V110 <= _xlfn.PERCENTILE.INC($V$2:$V$633, 0.67), "Medium", "High")) -> Low | X110: 0 | Y110: =IF(X110>30%,AVERAGEIF($X$2:$X$633,"<30%"),X110) -> 0 | Z110: =IF(Y110>0.2, "Yes", "No") -> No | AA110: 10 | AB110: =U110*AA110*(1-Y110) -> 1660.4 | AC110: =T110*AA110 -> 821.4 | AD110: =AB110-AC110 -> 839 | AE110: =IF(AB110=0, 0, AD110 / AB110) -> 0.50529993 | AF110: =MIN(Y110,'Scenario Modeling'!$B$2) -> 0 | AG110: =ROUND(AA110 * (1 + 'Scenario Modeling'!$B$4), 0) -> 10 | AH110: =T110 * (1 + 'Scenario Modeling'!$B$3) -> 82.14 | AI110: =V110 * AG110 * (1 - AF110) -> 1660.4 | AJ110: =AI110 - (AH110 * AG110) -> 839
A111: ORD-2024-166150 | B111: 45445 | C111: 45445 | D111: ="Q"&ROUNDUP(MONTH(B111)/3,0)&"-"&YEAR(B111) -> Q2-2024 | E111: 45451 | F111: 45451 | G111: =E111-B111 -> 6 | H111: =F111-B111 -> 6 | I111: =IF(H111<=7, "Yes", "No") -> Yes | J111: =_xlfn.MINIFS($B$2:$B$633, $L$2:$L$633, L111) -> 44946 | K111: Africa | L111: Kenya | M111: Kisumu | N111: =_xlfn.TEXTJOIN(" - ", TRUE, K111:M111) -> Africa - Kenya - Kisumu | O111: Consumer | P111: Marketplace | Q111: A. Patel | R111: Accessories | S111: ACC-9820 | T111: 292.94 | U111: 356.55 | V111: =ABS(U111) -> 356.55 | W111: =IF(V111 <= _xlfn.PERCENTILE.INC($V$2:$V$633, 0.33), "Low", IF(V111 <= _xlfn.PERCENTILE.INC($V$2:$V$633, 0.67), "Medium", "High")) -> Low | X111: 0.229 | Y111: =IF(X111>30%,AVERAGEIF($X$2:$X$633,"<30%"),X111) -> 0.229 | Z111: =IF(Y111>0.2, "Yes", "No") -> Yes | AA111: 2 | AB111: =U111*AA111*(1-Y111) -> 549.8001 | AC111: =T111*AA111 -> 585.88 | AD111: =AB111-AC111 -> -36.0799 | AE111: =IF(AB111=0, 0, AD111 / AB111) -> -0.065623669 | AF111: =MIN(Y111,'Scenario Modeling'!$B$2) -> 0.229 | AG111: =ROUND(AA111 * (1 + 'Scenario Modeling'!$B$4), 0) -> 2 | AH111: =T111 * (1 + 'Scenario Modeling'!$B$3) -> 292.94 | AI111: =V111 * AG111 * (1 - AF111) -> 549.8001 | AJ111: =AI111 - (AH111 * AG111) -> -36.0799
... A146: ORD-2023-309373 | B146: 45112 | C146: 45112 | D146: ="Q"&ROUNDUP(MONTH(B146)/3,0)&"-"&YEAR(B146) -> Q3-2023 | E146: 45121 | F146: 45121 | G146: =E146-B146 -> 9 | H146: =F146-B146 -> 9 | I146: =IF(H146<=7, "Yes", "No") -> No | J146: =_xlfn.MINIFS($B$2:$B$633, $L$2:$L$633, L146) -> 44955 | K146: Americas | L146: Brazil | M146: Brasília | N146: =_xlfn.TEXTJOIN(" - ", TRUE, K146:M146) -> Americas - Brazil - Brasília | O146: Enterprise | P146: Direct | Q146: B. Chen | R146: Networking | S146: NET-2394 | T146: 578.85 | U146: 998.76 | V146: =ABS(U146) -> 998.76 | W146: =IF(V146 <= _xlfn.PERCENTILE.INC($V$2:$V$633, 0.33), "Low", IF(V146 <= _xlfn.PERCENTILE.INC($V$2:$V$633, 0.67), "Medium", "High")) -> Medium | X146: 0.082 | Y146: =IF(X146>30%,AVERAGEIF($X$2:$X$633,"<30%"),X146) -> 0.082 | Z146: =IF(Y146>0.2, "Yes", "No") -> No | AA146: 28 | AB146: =U146*AA146*(1-Y146) -> 25672.127 | AC146: =T146*AA146 -> 16207.8 | AD146: =AB146-AC146 -> 9464.327 | AE146: =IF(AB146=0, 0, AD146 / AB146) -> 0.36866158 | AF146: =MIN(Y146,'Scenario Modeling'!$B$2) -> 0.082 | AG146: =ROUND(AA146 * (1 + 'Scenario Modeling'!$B$4), 0) -> 28 | AH146: =T146 * (1 + 'Scenario Modeling'!$B$3) -> 578.85 | AI146: =V146 * AG146 * (1 - AF146) -> 25672.127 | AJ146: =AI146 - (AH146 * AG146) -> 9464.327
A147: ORD-2023-825495 | B147: 45260 | C147: 45260 | D147: ="Q"&ROUNDUP(MONTH(B147)/3,0)&"-"&YEAR(B147) -> Q4-2023 | E147: 45259 | F147: =B147+17 -> 45277 | G147: =E147-B147 -> -1 | H147: =F147-B147 -> 17 | I147: =IF(H147<=7, "Yes", "No") -> No | J147: =_xlfn.MINIFS($B$2:$B$633, $L$2:$L$633, L147) -> 44933 | K147: Africa | L147: South Africa | M147: Durban | N147: =_xlfn.TEXTJOIN(" - ", TRUE, K147:M147) -> Africa - South Africa - Durban | O147: Small Business | P147: Marketplace | Q147: E. Garcia | R147: Laptops | S147: LAP-1525 | T147: 275.56 | U147: 630.72 | V147: =ABS(U147) -> 630.72 | W147: =IF(V147 <= _xlfn.PERCENTILE.INC($V$2:$V$633, 0.33), "Low", IF(V147 <= _xlfn.PERCENTILE.INC($V$2:$V$633, 0.67), "Medium", "High")) -> Low | X147: 0.107 | Y147: =IF(X147>30%,AVERAGEIF($X$2:$X$633,"<30%"),X147) -> 0.107 | Z147: =IF(Y147>0.2, "Yes", "No") -> No | AA147: 23 | AB147: =U147*AA147*(1-Y147) -> 12954.358 | AC147: =T147*AA147 -> 6337.88 | AD147: =AB147-AC147 -> 6616.4781 | AE147: =IF(AB147=0, 0, AD147 / AB147) -> 0.51075306 | AF147: =MIN(Y147,'Scenario Modeling'!$B$2) -> 0.107 | AG147: =ROUND(AA147 * (1 + 'Scenario Modeling'!$B$4), 0) -> 23 | AH147: =T147 * (1 + 'Scenario Modeling'!$B$3) -> 275.56 | AI147: =V147 * AG147 * (1 - AF147) -> 12954.358 | AJ147: =AI147 - (AH147 * AG147) -> 6616.4781
A148: ORD-2025-244832 | B148: 45911 | C148: 45911 | D148: ="Q"&ROUNDUP(MONTH(B148)/3,0)&"-"&YEAR(B148) -> Q3-2025 | E148: 45928 | F148: 45928 | G148: =E148-B148 -> 17 | H148: =F148-B148 -> 17 | I148: =IF(H148<=7, "Yes", "No") -> No | J148: =_xlfn.MINIFS($B$2:$B$633, $L$2:$L$633, L148) -> 44946 | K148: Africa | L148: Kenya | M148: Nairobi | N148: =_xlfn.TEXTJOIN(" - ", TRUE, K148:M148) -> Africa - Kenya - Nairobi | O148: Non-Profit | P148: Distributor | Q148: J. Njeri | R148: Laptops | S148: LAP-3278 | T148: 891.46 | U148: 728.61 | V148: =ABS(U148) -> 728.61 | W148: =IF(V148 <= _xlfn.PERCENTILE.INC($V$2:$V$633, 0.33), "Low", IF(V148 <= _xlfn.PERCENTILE.INC($V$2:$V$633, 0.67), "Medium", "High")) -> Low | X148: 0.185 | Y148: =IF(X148>30%,AVERAGEIF($X$2:$X$633,"<30%"),X148) -> 0.185 | Z148: =IF(Y148>0.2, "Yes", "No") -> No | AA148: 6 | AB148: =U148*AA148*(1-Y148) -> 3562.9029 | AC148: =T148*AA148 -> 5348.76 | AD148: =AB148-AC148 -> -1785.8571 | AE148: =IF(AB148=0, 0, AD148 / AB148) -> -0.50123653 | AF148: =MIN(Y148,'Scenario Modeling'!$B$2) -> 0.185 | AG148: =ROUND(AA148 * (1 + 'Scenario Modeling'!$B$4), 0) -> 6 | AH148: =T148 * (1 + 'Scenario Modeling'!$B$3) -> 891.46 | AI148: =V148 * AG148 * (1 - AF148) -> 3562.9029 | AJ148: =AI148 - (AH148 * AG148) -> -1785.8571
A149: ORD-2024-211453 | B149: 45386 | C149: 45386 | D149: ="Q"&ROUNDUP(MONTH(B149)/3,0)&"-"&YEAR(B149) -> Q2-2024 | E149: 45406 | F149: 45406 | G149: =E149-B149 -> 20 | H149: =F149-B149 -> 20 | I149: =IF(H149<=7, "Yes", "No") -> No | J149: =_xlfn.MINIFS($B$2:$B$633, $L$2:$L$633, L149) -> 44948 | K149: Europe | L149: Germany | M149: Frankfurt | N149: =_xlfn.TEXTJOIN(" - ", TRUE, K149:M149) -> Europe - Germany - Frankfurt | O149: Non-Profit | P149: Direct | Q149: O. Wang | R149: Accessories | S149: ACC-6543 | T149: 683.42 | U149: 951.51 | V149: =ABS(U149) -> 951.51 | W149: =IF(V149 <= _xlfn.PERCENTILE.INC($V$2:$V$633, 0.33), "Low", IF(V149 <= _xlfn.PERCENTILE.INC($V$2:$V$633, 0.67), "Medium", "High")) -> Medium | X149: 0 | Y149: =IF(X149>30%,AVERAGEIF($X$2:$X$633,"<30%"),X149) -> 0 | Z149: =IF(Y149>0.2, "Yes", "No") -> No | AA149: 14 | AB149: =U149*AA149*(1-Y149) -> 13321.14 | AC149: =T149*AA149 -> 9567.88 | AD149: =AB149-AC149 -> 3753.26 | AE149: =IF(AB149=0, 0, AD149 / AB149) -> 0.28175216 | AF149: =MIN(Y149,'Scenario Modeling'!$B$2) -> 0 | AG149: =ROUND(AA149 * (1 + 'Scenario Modeling'!$B$4), 0) -> 14 | AH149: =T149 * (1 + 'Scenario Modeling'!$B$3) -> 683.42 | AI149: =V149 * AG149 * (1 - AF149) -> 13321.14 | AJ149: =AI149 - (AH149 * AG149) -> 3753.26
A150: ORD-2023-192324 | B150: 45183 | C150: 45183 | D150: ="Q"&ROUNDUP(MONTH(B150)/3,0)&"-"&YEAR(B150) -> Q3-2023 | E150: 45185 | F150: 45185 | G150: =E150-B150 -> 2 | H150: =F150-B150 -> 2 | I150: =IF(H150<=7, "Yes", "No") -> Yes | J150: =_xlfn.MINIFS($B$2:$B$633, $L$2:$L$633, L150) -> 44936 | K150: Europe | L150: France | M150: Lyon | N150: =_xlfn.TEXTJOIN(" - ", TRUE, K150:M150) -> Europe - France - Lyon | O150: Non-Profit | P150: Direct | Q150: B. Chen | R150: Printers | S150: PRN-4432 | T150: 376.83 | U150: 732.88 | V150: =ABS(U150) -> 732.88 | W150: =IF(V150 <= _xlfn.PERCENTILE.INC($V$2:$V$633, 0.33), "Low", IF(V150 <= _xlfn.PERCENTILE.INC($V$2:$V$633, 0.67), "Medium", "High")) -> Low | X150: 0.188 | Y150: =IF(X150>30%,AVERAGEIF($X$2:$X$633,"<30%"),X150) -> 0.188 | Z150: =IF(Y150>0.2, "Yes", "No") -> No | AA150: 25 | AB150: =U150*AA150*(1-Y150) -> 14877.464 | AC150: =T150*AA150 -> 9420.75 | AD150: =AB150-AC150 -> 5456.714 | AE150: =IF(AB150=0, 0, AD150 / AB150) -> 0.36677716 | AF150: =MIN(Y150,'Scenario Modeling'!$B$2) -> 0.188 | AG150: =ROUND(AA150 * (1 + 'Scenario Modeling'!$B$4), 0) -> 25 | AH150: =T150 * (1 + 'Scenario Modeling'!$B$3) -> 376.83 | AI150: =V150 * AG150 * (1 - AF150) -> 14877.464 | AJ150: =AI150 - (AH150 * AG150) -> 5456.714
A151: ORD-2024-438404 | B151: 45558 | C151: 45558 | D151: ="Q"&ROUNDUP(MONTH(B151)/3,0)&"-"&YEAR(B151) -> Q3-2024 | E151: 45583 | F151: 45583 | G151: =E151-B151 -> 25 | H151: =F151-B151 -> 25 | I151: =IF(H151<=7, "Yes", "No") -> No | J151: =_xlfn.MINIFS($B$2:$B$633, $L$2:$L$633, L151) -> 44928 | K151: Americas | L151: Canada | M151: Vancouver | N151: =_xlfn.TEXTJOIN(" - ", TRUE, K151:M151) -> Americas - Canada - Vancouver | O151: Small Business | P151: Online | Q151: N. Brown | R151: Phones | S151: PHN-4568 | T151: 1297 | U151: 2411.52 | V151: =ABS(U151) -> 2411.52 | W151: =IF(V151 <= _xlfn.PERCENTILE.INC($V$2:$V$633, 0.33), "Low", IF(V151 <= _xlfn.PERCENTILE.INC($V$2:$V$633, 0.67), "Medium", "High")) -> High | X151: 0.021 | Y151: =IF(X151>30%,AVERAGEIF($X$2:$X$633,"<30%"),X151) -> 0.021 | Z151: =IF(Y151>0.2, "Yes", "No") -> No | AA151: 18 | AB151: =U151*AA151*(1-Y151) -> 42495.805 | AC151: =T151*AA151 -> 23346 | AD151: =AB151-AC151 -> 19149.805 | AE151: =IF(AB151=0, 0, AD151 / AB151) -> 0.45062813 | AF151: =MIN(Y151,'Scenario Modeling'!$B$2) -> 0.021 | AG151: =ROUND(AA151 * (1 + 'Scenario Modeling'!$B$4), 0) -> 18 | AH151: =T151 * (1 + 'Scenario Modeling'!$B$3) -> 1297 | AI151: =V151 * AG151 * (1 - AF151) -> 42495.805 | AJ151: =AI151 - (AH151 * AG151) -> 19149.805
A152: ORD-2025-246470 | B152: 45763 | C152: 45763 | D152: ="Q"&ROUNDUP(MONTH(B152)/3,0)&"-"&YEAR(B152) -> Q2-2025 | E152: 45793 | F152: 45793 | G152: =E152-B152 -> 30 | H152: =F152-B152 -> 30 | I152: =IF(H152<=7, "Yes", "No") -> No | J152: =_xlfn.MINIFS($B$2:$B$633, $L$2:$L$633, L152) -> 44928 | K152: Americas | L152: Canada | M152: Montreal | N152: =_xlfn.TEXTJOIN(" - ", TRUE, K152:M152) -> Americas - Canada - Montreal | O152: Enterprise | P152: Distributor | Q152: K. Singh | R152: Printers | S152: PRN-6178 | T152: 763.32 | U152: 568.29 | V152: =ABS(U152) -> 568.29 | W152: =IF(V152 <= _xlfn.PERCENTILE.INC($V$2:$V$633, 0.33), "Low", IF(V152 <= _xlfn.PERCENTILE.INC($V$2:$V$633, 0.67), "Medium", "High")) -> Low | X152: 0.131 | Y152: =IF(X152>30%,AVERAGEIF($X$2:$X$633,"<30%"),X152) -> 0.131 | Z152: =IF(Y152>0.2, "Yes", "No") -> No | AA152: 16 | AB152: =U152*AA152*(1-Y152) -> 7901.5042 | AC152: =T152*AA152 -> 12213.12 | AD152: =AB152-AC152 -> -4311.6158 | AE152: =IF(AB152=0, 0, AD152 / AB152) -> -0.54567026 | AF152: =MIN(Y152,'Scenario Modeling'!$B$2) -> 0.131 | AG152: =ROUND(AA152 * (1 + 'Scenario Modeling'!$B$4), 0) -> 16 | AH152: =T152 * (1 + 'Scenario Modeling'!$B$3) -> 763.32 | AI152: =V152 * AG152 * (1 - AF152) -> 7901.5042 | AJ152: =AI152 - (AH152 * AG152) -> -4311.6158
A153: ORD-2023-497686 | B153: 45110 | C153: 45110 | D153: ="Q"&ROUNDUP(MONTH(B153)/3,0)&"-"&YEAR(B153) -> Q3-2023 | E153: 45130 | F153: 45130 | G153: =E153-B153 -> 20 | H153: =F153-B153 -> 20 | I153: =IF(H153<=7, "Yes", "No") -> No | J153: =_xlfn.MINIFS($B$2:$B$633, $L$2:$L$633, L153) -> 44933 | K153: Africa | L153: South Africa | M153: Johannesburg | N153: =_xlfn.TEXTJOIN(" - ", TRUE, K153:M153) -> Africa - South Africa - Johannesburg | O153: Small Business | P153: Distributor | Q153: F. Müller | R153: Laptops | S153: LAP-6342 | T153: 1001.96 | U153: 1254.95 | V153: =ABS(U153) -> 1254.95 | W153: =IF(V153 <= _xlfn.PERCENTILE.INC($V$2:$V$633, 0.33), "Low", IF(V153 <= _xlfn.PERCENTILE.INC($V$2:$V$633, 0.67), "Medium", "High")) -> Medium | X153: 0.045 | Y153: =IF(X153>30%,AVERAGEIF($X$2:$X$633,"<30%"),X153) -> 0.045 | Z153: =IF(Y153>0.2, "Yes", "No") -> No | AA153: 18 | AB153: =U153*AA153*(1-Y153) -> 21572.591 | AC153: =T153*AA153 -> 18035.28 | AD153: =AB153-AC153 -> 3537.3105 | AE153: =IF(AB153=0, 0, AD153 / AB153) -> 0.16397245 | AF153: =MIN(Y153,'Scenario Modeling'!$B$2) -> 0.045 | AG153: =ROUND(AA153 * (1 + 'Scenario Modeling'!$B$4), 0) -> 18 | AH153: =T153 * (1 + 'Scenario Modeling'!$B$3) -> 1001.96 | AI153: =V153 * AG153 * (1 - AF153) -> 21572.591 | AJ153: =AI153 - (AH153 * AG153) -> 3537.3105
A154: ORD-2023-596758 | B154: 45267 | C154: 45267 | D154: ="Q"&ROUNDUP(MONTH(B154)/3,0)&"-"&YEAR(B154) -> Q4-2023 | E154: 45265 | F154: =B154+8 -> 45275 | G154: =E154-B154 -> -2 | H154: =F154-B154 -> 8 | I154: =IF(H154<=7, "Yes", "No") -> No | J154: =_xlfn.MINIFS($B$2:$B$633, $L$2:$L$633, L154) -> 44988 | K154: Asia | L154: Japan | M154: Tokyo | N154: =_xlfn.TEXTJOIN(" - ", TRUE, K154:M154) -> Asia - Japan - Tokyo | O154: Non-Profit | P154: Marketplace | Q154: H. Kim | R154: Printers | S154: PRN-8175 | T154: 1097.59 | U154: 845.55 | V154: =ABS(U154) -> 845.55 | W154: =IF(V154 <= _xlfn.PERCENTILE.INC($V$2:$V$633, 0.33), "Low", IF(V154 <= _xlfn.PERCENTILE.INC($V$2:$V$633, 0.67), "Medium", "High")) -> Medium | X154: 0.184 | Y154: =IF(X154>30%,AVERAGEIF($X$2:$X$633,"<30%"),X154) -> 0.184 | Z154: =IF(Y154>0.2, "Yes", "No") -> No | AA154: 6 | AB154: =U154*AA154*(1-Y154) -> 4139.8128 | AC154: =T154*AA154 -> 6585.54 | AD154: =AB154-AC154 -> -2445.7272 | AE154: =IF(AB154=0, 0, AD154 / AB154) -> -0.59078208 | AF154: =MIN(Y154,'Scenario Modeling'!$B$2) -> 0.184 | AG154: =ROUND(AA154 * (1 + 'Scenario Modeling'!$B$4), 0) -> 6 | AH154: =T154 * (1 + 'Scenario Modeling'!$B$3) -> 1097.59 | AI154: =V154 * AG154 * (1 - AF154) -> 4139.8128 | AJ154: =AI154 - (AH154 * AG154) -> -2445.7272
A155: ORD-2024-201376 | B155: 45340 | C155: 45340 | D155: ="Q"&ROUNDUP(MONTH(B155)/3,0)&"-"&YEAR(B155) -> Q1-2024 | E155: 45355 | F155: 45355 | G155: =E155-B155 -> 15 | H155: =F155-B155 -> 15 | I155: =IF(H155<=7, "Yes", "No") -> No | J155: =_xlfn.MINIFS($B$2:$B$633, $L$2:$L$633, L155) -> 44946 | K155: Africa | L155: Kenya | M155: Kisumu | N155: =_xlfn.TEXTJOIN(" - ", TRUE, K155:M155) -> Africa - Kenya - Kisumu | O155: Education | P155: Direct | Q155: K. Singh | R155: Printers | S155: PRN-7089 | T155: 928.68 | U155: 2145.17 | V155: =ABS(U155) -> 2145.17 | W155: =IF(V155 <= _xlfn.PERCENTILE.INC($V$2:$V$633, 0.33), "Low", IF(V155 <= _xlfn.PERCENTILE.INC($V$2:$V$633, 0.67), "Medium", "High")) -> High | X155: 0.136 | Y155: =IF(X155>30%,AVERAGEIF($X$2:$X$633,"<30%"),X155) -> 0.136 | Z155: =IF(Y155>0.2, "Yes", "No") -> No | AA155: 16 | AB155: =U155*AA155*(1-Y155) -> 29654.83 | AC155: =T155*AA155 -> 14858.88 | AD155: =AB155-AC155 -> 14795.95 | AE155: =IF(AB155=0, 0, AD155 / AB155) -> 0.49893896 | AF155: =MIN(Y155,'Scenario Modeling'!$B$2) -> 0.136 | AG155: =ROUND(AA155 * (1 + 'Scenario Modeling'!$B$4), 0) -> 16 | AH155: =T155 * (1 + 'Scenario Modeling'!$B$3) -> 928.68 | AI155: =V155 * AG155 * (1 - AF155) -> 29654.83 | AJ155: =AI155 - (AH155 * AG155) -> 14795.95
A156: ORD-2023-842488 | B156: 45230 | C156: 45230 | D156: ="Q"&ROUNDUP(MONTH(B156)/3,0)&"-"&YEAR(B156) -> Q4-2023 | E156: 45232 | F156: 45232 | G156: =E156-B156 -> 2 | H156: =F156-B156 -> 2 | I156: =IF(H156<=7, "Yes", "No") -> Yes | J156: =_xlfn.MINIFS($B$2:$B$633, $L$2:$L$633, L156) -> 44946 | K156: Africa | L156: Kenya | M156: Kisumu | N156: =_xlfn.TEXTJOIN(" - ", TRUE, K156:M156) -> Africa - Kenya - Kisumu | O156: Education | P156: Retail | Q156: O. Wang | R156: Accessories | S156: ACC-4124 | T156: 867.89 | U156: 1349.94 | V156: =ABS(U156) -> 1349.94 | W156: =IF(V156 <= _xlfn.PERCENTILE.INC($V$2:$V$633, 0.33), "Low", IF(V156 <= _xlfn.PERCENTILE.INC($V$2:$V$633, 0.67), "Medium", "High")) -> Medium | X156: 0.184 | Y156: =IF(X156>30%,AVERAGEIF($X$2:$X$633,"<30%"),X156) -> 0.184 | Z156: =IF(Y156>0.2, "Yes", "No") -> No | AA156: 10 | AB156: =U156*AA156*(1-Y156) -> 11015.51 | AC156: =T156*AA156 -> 8678.9 | AD156: =AB156-AC156 -> 2336.6104 | AE156: =IF(AB156=0, 0, AD156 / AB156) -> 0.21212003 | AF156: =MIN(Y156,'Scenario Modeling'!$B$2) -> 0.184 | AG156: =ROUND(AA156 * (1 + 'Scenario Modeling'!$B$4), 0) -> 10 | AH156: =T156 * (1 + 'Scenario Modeling'!$B$3) -> 867.89 | AI156: =V156 * AG156 * (1 - AF156) -> 11015.51 | AJ156: =AI156 - (AH156 * AG156) -> 2336.6104
A157: ORD-2024-136321 | B157: 45511 | C157: 45511 | D157: ="Q"&ROUNDUP(MONTH(B157)/3,0)&"-"&YEAR(B157) -> Q3-2024 | E157: 45521 | F157: 45521 | G157: =E157-B157 -> 10 | H157: =F157-B157 -> 10 | I157: =IF(H157<=7, "Yes", "No") -> No | J157: =_xlfn.MINIFS($B$2:$B$633, $L$2:$L$633, L157) -> 44988 | K157: Asia | L157: Japan | M157: Osaka | N157: =_xlfn.TEXTJOIN(" - ", TRUE, K157:M157) -> Asia - Japan - Osaka | O157: Consumer | P157: Online | Q157: K. Singh | R157: Networking | S157: NET-7924 | T157: 436.58 | U157: 527.48 | V157: =ABS(U157) -> 527.48 | W157: =IF(V157 <= _xlfn.PERCENTILE.INC($V$2:$V$633, 0.33), "Low", IF(V157 <= _xlfn.PERCENTILE.INC($V$2:$V$633, 0.67), "Medium", "High")) -> Low | X157: 0.111 | Y157: =IF(X157>30%,AVERAGEIF($X$2:$X$633,"<30%"),X157) -> 0.111 | Z157: =IF(Y157>0.2, "Yes", "No") -> No | AA157: 19 | AB157: =U157*AA157*(1-Y157) -> 8909.6647 | AC157: =T157*AA157 -> 8295.02 | AD157: =AB157-AC157 -> 614.64468 | AE157: =IF(AB157=0, 0, AD157 / AB157) -> 0.068986286 | AF157: =MIN(Y157,'Scenario Modeling'!$B$2) -> 0.111 | AG157: =ROUND(AA157 * (1 + 'Scenario Modeling'!$B$4), 0) -> 19 | AH157: =T157 * (1 + 'Scenario Modeling'!$B$3) -> 436.58 | AI157: =V157 * AG157 * (1 - AF157) -> 8909.6647 | AJ157: =AI157 - (AH157 * AG157) -> 614.64468
A158: ORD-2024-764468 | B158: 45323 | C158: 45323 | D158: ="Q"&ROUNDUP(MONTH(B158)/3,0)&"-"&YEAR(B158) -> Q1-2024 | E158: 45343 | F158: 45343 | G158: =E158-B158 -> 20 | H158: =F158-B158 -> 20 | I158: =IF(H158<=7, "Yes", "No") -> No | J158: =_xlfn.MINIFS($B$2:$B$633, $L$2:$L$633, L158) -> 44936 | K158: Europe | L158: France | M158: Paris | N158: =_xlfn.TEXTJOIN(" - ", TRUE, K158:M158) -> Europe - France - Paris | O158: Small Business | P158: Marketplace | Q158: A. Patel | R158: Networking | S158: NET-8761 | T158: 656.2 | U158: 1467.17 | V158: =ABS(U158) -> 1467.17 | W158: =IF(V158 <= _xlfn.PERCENTILE.INC($V$2:$V$633, 0.33), "Low", IF(V158 <= _xlfn.PERCENTILE.INC($V$2:$V$633, 0.67), "Medium", "High")) -> Medium | X158: 0.018 | Y158: =IF(X158>30%,AVERAGEIF($X$2:$X$633,"<30%"),X158) -> 0.018 | Z158: =IF(Y158>0.2, "Yes", "No") -> No | AA158: 5 | AB158: =U158*AA158*(1-Y158) -> 7203.8047 | AC158: =T158*AA158 -> 3281 | AD158: =AB158-AC158 -> 3922.8047 | AE158: =IF(AB158=0, 0, AD158 / AB158) -> 0.54454623 | AF158: =MIN(Y158,'Scenario Modeling'!$B$2) -> 0.018 | AG158: =ROUND(AA158 * (1 + 'Scenario Modeling'!$B$4), 0) -> 5 | AH158: =T158 * (1 + 'Scenario Modeling'!$B$3) -> 656.2 | AI158: =V158 * AG158 * (1 - AF158) -> 7203.8047 | AJ158: =AI158 - (AH158 * AG158) -> 3922.8047
A159: ORD-2024-553449 | B159: 45531 | C159: 45531 | D159: ="Q"&ROUNDUP(MONTH(B159)/3,0)&"-"&YEAR(B159) -> Q3-2024 | E159: 45553 | F159: 45553 | G159: =E159-B159 -> 22 | H159: =F159-B159 -> 22 | I159: =IF(H159<=7, "Yes", "No") -> No | J159: =_xlfn.MINIFS($B$2:$B$633, $L$2:$L$633, L159) -> 44955 | K159: Asia | L159: India | M159: Delhi | N159: =_xlfn.TEXTJOIN(" - ", TRUE, K159:M159) -> Asia - India - Delhi | O159: Consumer | P159: Direct | Q159: B. Chen | R159: Components | S159: CMP-3875 | T159: 896.75 | U159: 1651.14 | V159: =ABS(U159) -> 1651.14 | W159: =IF(V159 <= _xlfn.PERCENTILE.INC($V$2:$V$633, 0.33), "Low", IF(V159 <= _xlfn.PERCENTILE.INC($V$2:$V$633, 0.67), "Medium", "High")) -> High | X159: 0.025 | Y159: =IF(X159>30%,AVERAGEIF($X$2:$X$633,"<30%"),X159) -> 0.025 | Z159: =IF(Y159>0.2, "Yes", "No") -> No | AA159: 15 | AB159: =U159*AA159*(1-Y159) -> 24147.923 | AC159: =T159*AA159 -> 13451.25 | AD159: =AB159-AC159 -> 10696.673 | AE159: =IF(AB159=0, 0, AD159 / AB159) -> 0.4429645 | AF159: =MIN(Y159,'Scenario Modeling'!$B$2) -> 0.025 | AG159: =ROUND(AA159 * (1 + 'Scenario Modeling'!$B$4), 0) -> 15 | AH159: =T159 * (1 + 'Scenario Modeling'!$B$3) -> 896.75 | AI159: =V159 * AG159 * (1 - AF159) -> 24147.923 | AJ159: =AI159 - (AH159 * AG159) -> 10696.673
A160: ORD-2025-766923 | B160: 45703 | C160: 45703 | D160: ="Q"&ROUNDUP(MONTH(B160)/3,0)&"-"&YEAR(B160) -> Q1-2025 | E160: 45703 | F160: 45703 | G160: =E160-B160 -> 0 | H160: =F160-B160 -> 0 | I160: =IF(H160<=7, "Yes", "No") -> Yes | J160: =_xlfn.MINIFS($B$2:$B$633, $L$2:$L$633, L160) -> 44948 | K160: Europe | L160: Germany | M160: Frankfurt | N160: =_xlfn.TEXTJOIN(" - ", TRUE, K160:M160) -> Europe - Germany - Frankfurt | O160: Small Business | P160: Marketplace | Q160: L. Okafor | R160: Accessories | S160: ACC-3989 | T160: 815.83 | U160: 1982.18 | V160: =ABS(U160) -> 1982.18 | W160: =IF(V160 <= _xlfn.PERCENTILE.INC($V$2:$V$633, 0.33), "Low", IF(V160 <= _xlfn.PERCENTILE.INC($V$2:$V$633, 0.67), "Medium", "High")) -> High | X160: 0.127 | Y160: =IF(X160>30%,AVERAGEIF($X$2:$X$633,"<30%"),X160) -> 0.127 | Z160: =IF(Y160>0.2, "Yes", "No") -> No | AA160: 6 | AB160: =U160*AA160*(1-Y160) -> 10382.659 | AC160: =T160*AA160 -> 4894.98 | AD160: =AB160-AC160 -> 5487.6788 | AE160: =IF(AB160=0, 0, AD160 / AB160) -> 0.52854273 | AF160: =MIN(Y160,'Scenario Modeling'!$B$2) -> 0.127 | AG160: =ROUND(AA160 * (1 + 'Scenario Modeling'!$B$4), 0) -> 6 | AH160: =T160 * (1 + 'Scenario Modeling'!$B$3) -> 815.83 | AI160: =V160 * AG160 * (1 - AF160) -> 10382.659 | AJ160: =AI160 - (AH160 * AG160) -> 5487.6788
...

Sheet Brief
A1: Assignment
A2: Excel Mastery Assignment: Sales Operations & Analytics
A4: Overview:
A5: You are an analyst for a multi-regional electronics distributor. The 'Data' sheet contains 632 rows and 15 columns of transactional data with intentional data-quality issues.
A6: Your job is to clean, enrich, analyze, and present insights via a dynamic dashboard.
A8: Part A — Data Cleaning & Preparation:
A9: 1) Create a staging table where you:
A10: • Remove exact duplicate rows (define and document your duplicate criteria).
A11: • Fix data types (dates as Dates, numeric fields as numbers).
A12: • Handle missing values for City, Salesperson, and Channel using reasonable business logic (document your approach).
A13: • Flag and correct suspicious UnitPrice values (e.g., negative prices) and discounts (e.g., > 30%).
A14: • Ensure RequiredDate is not earlier than OrderDate; where it is, impute a corrected RequiredDate (explain your rule).
... A67: 15) Ensure your dashboard responds to slicers without broken references.

Sheet Dashboard

Sheet Dashboard Charts
A1: OrderDate (mmm-yyyy) | B1: (All)
A3: Row Labels | B3: Sum of GrossRevenue | E3: Sum of GrossProfit | F3: Column Labels
A4: 2023 | B4: 3723944.4 | E4: Row Labels | F4: Direct | G4: Distributor | H4: Marketplace | I4: Online | J4: Retail | K4: Grand Total | O4: Salesperson | P4: Average Discount
A5: Jan | B5: 178642.74 | E5: Africa | F5: 186715.22 | G5: 227456.27 | H5: 164839.3 | I5: 145453.95 | J5: 140531.64 | K5: 864996.38 | O5: A. Patel | P5: 0.1292003
A6: Feb | B6: 433149.2 | E6: Americas | F6: 258674.93 | G6: 177464.67 | H6: 97387.608 | I6: 261943.84 | J6: 69035.709 | K6: 864506.76 | O6: B. Chen | P6: 0.10938
A7: Mar | B7: 215576.67 | E7: Asia | F7: 233003.93 | G7: 155163.87 | H7: 151470.01 | I7: 149042.39 | J7: 169788.98 | K7: 858469.19 | O7: C. Otieno | P7: 0.12038456
A8: Apr | B8: 371604.58 | E8: Europe | F8: 300745.66 | G8: 105550.85 | H8: 111146.84 | I8: 200067.16 | J8: 150086.48 | K8: 867596.99 | O8: D. Smith | P8: 0.12628205
A9: May | B9: 471414.64 | E9: Grand Total | F9: 979139.74 | G9: 665635.66 | H9: 524843.76 | I9: 756507.34 | J9: 529442.81 | K9: 3455569.3 | O9: E. Garcia | P9: 0.10520588
A10: Jun | B10: 236474.06 | O10: F. Müller | P10: 0.10307547
A11: Jul | B11: 567977.52 | O11: G. Dubois | P11: 0.1172
A12: Aug | B12: 339044.67 | O12: H. Kim | P12: 0.12093842
A13: Sep | B13: 141266.51 | E13: Row Labels | F13: Sum of GrossRevenue | O13: I. Johnson | P13: 0.13473684
A14: Oct | B14: 259682.91 | E14: CMP-3938 | F14: 84136.12 | O14: J. Njeri | P14: 0.1172
A15: Nov | B15: 127009.51 | E15: CMP-8851 | F15: 139277.83 | O15: K. Singh | P15: 0.11825
A16: Dec | B16: 382101.37 | E16: LAP-3904 | F16: 82514.712 | O16: L. Okafor | P16: 0.12064379
A17: 2024 | B17: 4480268.4 | E17: LAP-8910 | F17: 102122.94 | O17: M. Rossi | P17: 0.1189105
A18: Jan | B18: 299100.37 | E18: MON-2266 | F18: 87404.93 | O18: N. Brown | P18: 0.11159375
A19: Feb | B19: 307793.71 | E19: MON-6699 | F19: 85637.74 | O19: O. Wang | P19: 0.12935135
A20: Mar | B20: 374300.11 | E20: MON-6962 | F20: 92715.25
A21: Apr | B21: 239506.83 | E21: NET-2365 | F21: 109244
A22: May | B22: 416985.77 | E22: NET-5523 | F22: 79548.756
A23: Jun | B23: 634490.72 | E23: NET-5987 | F23: 82141.34
A24: Jul | B24: 275628.62 | E24: Grand Total | F24: 944743.62
A25: Aug | B25: 389348.62
A26: Sep | B26: 347613.19
A27: Oct | B27: 425869.99
A28: Nov | B28: 416944.19
A29: Dec | B29: 352686.24
A30: 2025 | B30: 2779104.3
A31: Jan | B31: 223498.2
A32: Feb | B32: 221608.5
A33: Mar | B33: 212887.98
A34: Apr | B34: 336135.17
A35: May | B35: 377451.77
A36: Jun | B36: 381463.4
... A40: Grand Total | B40: 10983317

Sheet ReadMe
A1: Run Remove Dublicates across all 15 columns to find exact matches. No exact dublicates were found.
A2: Formatted columns involving dates as short date, converted DicountPc column as percentage, and quantity as number.
A3: Filled blanks for City column using the logic of most Orders placed in the associated country i.e. City with most orders (Mode) for associated country.
A4: Filled blanks for Salesperson by logic of most number of orders for each salesperson for associated country. Where country tied, salesperson with most orders in the Region was selected.
A5: Filled blanks for Channel by logic of most number of orders in associated country and customer segment. Where orders tied for a particular customer segmennt in associated country, the most channel with most orders for that segment was selected.
A6: Flagged negative Unit prices by applying conditional formating to the column and highlighting cells with values less than 0. Introduced a new column called cleaned UnitPrice and applied the ABS() formula to convert negative numbers to positive.
A7: Flagged Discounts that were greater than 30% by applying conditional formatting to highlight cells with values greater than 30%. Introduced a new column called cleaned DiscountPct and applied IF formula together with AVERAGEIF to find cells with greater than 30% discounts in flagged column and replace them with the Average of the values in the flagged column that are less than 30%. ("=IF(O4>30%,AVERAGEIF($O$2:$O$633,"<30%"),O4)")
A8: Identified where RequiredDate was earlier than OrderDate but using LeadTimeDays (RequiredDate-OrderDate) column to find days that were less than 0 and used conditional formatting to highlight them. Introduced a new column, (Cleaned RequiredDate) and replaced dates with associated LeadTimeDays being less than 0, with the Average LeadTimeDays for the associated Country, City and Channel.
A9: Introduced a Cleaned LeadTimeDays column involing the corrected RequiredDate and OrderDate(Cleaned RequiredDate - OrderDate).
A10: Created Standardized dimentions for Order date, as (MMM-YYYY), buy formatting the column as custom and selecting mmm-yyyy as the prefered format.
A11: Created Standardized dimentions for Order date, as Quarters, (Q1-YYYY) by applying the formula ="Q"&ROUNDUP(MONTH(B2)/3,0)&"-"&YEAR(B2)
A12: Created Standardized dimentions for Region hierarchy as Region - Country - City by using TEXTJOIN
... A20: Created a Scenario Modeling worksheet to serve as an interactive control panel and applied Data Validation to limit the inputs for Global Discount Cap (0-25%), Unit Cost Inflation (0-15%), and Quantity Uplift (0-20%). Introduced new columns (Scenario columns) to my the dataset and applyed scenario calculations into the new columns, by using MIN() function to cap discounts against the control panel, a ROUND function to calculate whole-unit quantity growth, and multiplication to get unit cost inflation. Calculated scenario Gross Revenue and scenario Gross Profit using the newly adjusted variables. Built a summary table using SUM functions to compare original baselines directly against the scenario totals.

Sheet City order count
A3: Row Labels | B3: Count of OrderID
A4: Brazil | B4: 62
A5: Brasília | B5: 26
A6: Rio de Janeiro | B6: 18
A7: São Paulo | B7: 18
A8: Canada | B8: 44
A9: Montreal | B9: 11
A10: Toronto | B10: 15
A11: Vancouver | B11: 18
A12: China | B12: 51
A13: Beijing | B13: 15
A14: Shanghai | B14: 20
A15: Shenzhen | B15: 16
... A55: Grand Total | B55: 632

Sheet Salesperson order count
A3: Row Labels | B3: Count of OrderID
A4: Africa | B4: 145
A5: Kenya | B5: 56
A6: A. Patel | B6: 3
A7: B. Chen | B7: 5
A8: C. Otieno | B8: 6
A9: D. Smith | B9: 4
A10: E. Garcia | B10: 1
A11: F. Müller | B11: 4
A12: H. Kim | B12: 4
A13: I. Johnson | B13: 2
A14: J. Njeri | B14: 6
A15: K. Singh | B15: 3
... A182: Grand Total | B182: 632

Sheet Channel order count
A3: Count of OrderID | B3: Column Labels
A4: Row Labels | B4: Direct | C4: Distributor | D4: Marketplace | E4: Online | F4: Retail | G4: Grand Total
A5: Brazil | B5: 21 | C5: 12 | D5: 9 | E5: 10 | F5: 10 | G5: 62
A6: Consumer | B6: 2 | C6: 3 | D6: 1 | E6: 2 | G6: 8
A7: Corporate | B7: 2 | C7: 4 | D7: 2 | F7: 1 | G7: 9
A8: Education | B8: 3 | D8: 1 | E8: 3 | F8: 3 | G8: 10
A9: Enterprise | B9: 4 | C9: 1 | D9: 3 | F9: 1 | G9: 9
A10: Non-Profit | B10: 8 | C10: 2 | D10: 1 | E10: 5 | F10: 2 | G10: 18
A11: Small Business | B11: 2 | C11: 2 | D11: 1 | F11: 3 | G11: 8
A12: Canada | B12: 9 | C12: 14 | D12: 6 | E12: 10 | F12: 5 | G12: 44
A13: Consumer | B13: 1 | C13: 5 | E13: 4 | G13: 10
A14: Corporate | B14: 1 | C14: 2 | E14: 2 | G14: 5
A15: Education | B15: 5 | C15: 2 | D15: 1 | G15: 8
A16: Enterprise | C16: 3 | D16: 2 | E16: 2 | F16: 2 | G16: 9
A17: Non-Profit | B17: 1 | C17: 2 | D17: 1 | E17: 1 | F17: 2 | G17: 7
A18: Small Business | B18: 1 | D18: 2 | E18: 1 | F18: 1 | G18: 5
A19: China | B19: 9 | C19: 12 | D19: 5 | E19: 13 | F19: 12 | G19: 51
A20: Consumer | B20: 1 | C20: 4 | D20: 1 | E20: 1 | G20: 7
A21: Corporate | B21: 1 | C21: 4 | E21: 1 | F21: 4 | G21: 10
A22: Education | C22: 1 | D22: 1 | E22: 2 | F22: 2 | G22: 6
A23: Enterprise | B23: 2 | D23: 1 | E23: 3 | F23: 1 | G23: 7
A24: Non-Profit | B24: 3 | C24: 2 | D24: 1 | E24: 2 | F24: 3 | G24: 11
A25: Small Business | B25: 2 | C25: 1 | D25: 1 | E25: 4 | F25: 2 | G25: 10
A26: France | B26: 17 | C26: 6 | D26: 14 | E26: 8 | F26: 9 | G26: 54
A27: Consumer | B27: 2 | C27: 1 | D27: 3 | E27: 1 | G27: 7
A28: Corporate | B28: 6 | C28: 1 | D28: 1 | E28: 2 | F28: 4 | G28: 14
A29: Education | C29: 1 | E29: 1 | F29: 2 | G29: 4
A30: Enterprise | B30: 1 | C30: 1 | D30: 3 | F30: 1 | G30: 6
A31: Non-Profit | B31: 6 | D31: 2 | G31: 8
A32: Small Business | B32: 2 | C32: 2 | D32: 5 | E32: 4 | F32: 2 | G32: 15
A33: Germany | B33: 19 | C33: 5 | D33: 8 | E33: 11 | F33: 8 | G33: 51
A34: Consumer | B34: 1 | C34: 1 | D34: 1 | E34: 2 | F34: 2 | G34: 7
A35: Corporate | B35: 6 | C35: 1 | D35: 1 | E35: 2 | F35: 1 | G35: 11
A36: Education | B36: 4 | E36: 1 | F36: 3 | G36: 8
A37: Enterprise | B37: 2 | C37: 1 | D37: 2 | E37: 1 | G37: 6
A38: Non-Profit | B38: 1 | C38: 1 | D38: 1 | E38: 1 | F38: 2 | G38: 6
A39: Small Business | B39: 5 | C39: 1 | D39: 3 | E39: 4 | G39: 13
A40: India | B40: 14 | C40: 12 | D40: 16 | E40: 3 | F40: 16 | G40: 61
A41: Consumer | B41: 2 | C41: 2 | D41: 2 | F41: 3 | G41: 9
A42: Corporate | B42: 2 | C42: 2 | D42: 2 | E42: 1 | F42: 3 | G42: 10
A43: Education | B43: 2 | C43: 1 | D43: 2 | F43: 1 | G43: 6
A44: Enterprise | B44: 3 | C44: 2 | D44: 3 | F44: 1 | G44: 9
A45: Non-Profit | C45: 3 | D45: 3 | E45: 1 | F45: 3 | G45: 10
A46: Small Business | B46: 5 | C46: 2 | D46: 4 | E46: 1 | F46: 5 | G46: 17
A47: Japan | B47: 13 | C47: 13 | D47: 13 | E47: 11 | F47: 9 | G47: 59
A48: Consumer | B48: 1 | D48: 3 | E48: 2 | F48: 2 | G48: 8
A49: Corporate | B49: 3 | C49: 3 | D49: 1 | F49: 2 | G49: 9
A50: Education | B50: 2 | C50: 2 | D50: 2 | E50: 3 | G50: 9
A51: Enterprise | B51: 1 | C51: 3 | D51: 1 | E51: 2 | F51: 3 | G51: 10
A52: Non-Profit | B52: 3 | D52: 2 | E52: 1 | G52: 6
A53: Small Business | B53: 3 | C53: 5 | D53: 4 | E53: 3 | F53: 2 | G53: 17
A54: Kenya | B54: 16 | C54: 7 | D54: 8 | E54: 11 | F54: 14 | G54: 56
A55: Consumer | B55: 1 | C55: 1 | D55: 4 | E55: 1 | F55: 2 | G55: 9
A56: Corporate | B56: 7 | C56: 2 | D56: 1 | E56: 3 | F56: 3 | G56: 16
A57: Education | B57: 4 | D57: 1 | E57: 1 | F57: 2 | G57: 8
A58: Enterprise | B58: 1 | C58: 1 | D58: 1 | E58: 2 | G58: 5
A59: Non-Profit | B59: 1 | C59: 2 | E59: 2 | G59: 5
A60: Small Business | B60: 2 | C60: 1 | D60: 1 | E60: 2 | F60: 7 | G60: 13
A61: Nigeria | B61: 7 | C61: 10 | D61: 14 | E61: 9 | F61: 4 | G61: 44
A62: Consumer | C62: 2 | D62: 2 | E62: 2 | G62: 6
A63: Corporate | B63: 1 | C63: 3 | D63: 3 | F63: 2 | G63: 9
A64: Education | C64: 1 | D64: 1 | E64: 2 | F64: 1 | G64: 5
A65: Enterprise | B65: 2 | C65: 2 | D65: 2 | E65: 2 | G65: 8
A66: Non-Profit | B66: 3 | C66: 1 | D66: 3 | E66: 1 | G66: 8
A67: Small Business | B67: 1 | C67: 1 | D67: 3 | E67: 2 | F67: 1 | G67: 8
A68: South Africa | B68: 6 | C68: 16 | D68: 11 | E68: 5 | F68: 7 | G68: 45
A69: Consumer | B69: 1 | C69: 1 | D69: 1 | E69: 2 | G69: 5
A70: Corporate | B70: 2 | C70: 1 | D70: 2 | G70: 5
A71: Education | C71: 4 | D71: 1 | F71: 1 | G71: 6
A72: Enterprise | B72: 1 | C72: 4 | D72: 3 | F72: 3 | G72: 11
A73: Non-Profit | B73: 1 | C73: 2 | D73: 1 | E73: 3 | F73: 1 | G73: 8
A74: Small Business | B74: 1 | C74: 4 | D74: 3 | F74: 2 | G74: 10
A75: United Kingdom | B75: 17 | C75: 8 | D75: 9 | E75: 9 | F75: 11 | G75: 54
A76: Consumer | B76: 1 | C76: 1 | D76: 2 | E76: 1 | F76: 4 | G76: 9
A77: Corporate | B77: 2 | D77: 1 | E77: 1 | F77: 3 | G77: 7
A78: Education | B78: 2 | C78: 1 | D78: 1 | E78: 1 | G78: 5
A79: Enterprise | C79: 3 | D79: 2 | E79: 4 | F79: 2 | G79: 11
A80: Non-Profit | B80: 9 | C80: 2 | D80: 1 | E80: 2 | G80: 14
A81: Small Business | B81: 3 | C81: 1 | D81: 2 | F81: 2 | G81: 8
A82: USA | B82: 9 | C82: 11 | D82: 13 | E82: 10 | F82: 8 | G82: 51
A83: Consumer | B83: 2 | C83: 4 | D83: 2 | F83: 3 | G83: 11
A84: Corporate | B84: 3 | C84: 3 | D84: 3 | F84: 3 | G84: 12
A85: Education | B85: 1 | C85: 1 | D85: 5 | G85: 7
A86: Enterprise | E86: 5 | F86: 1 | G86: 6
A87: Non-Profit | B87: 2 | C87: 2 | D87: 1 | E87: 3 | G87: 8
A88: Small Business | B88: 1 | C88: 1 | D88: 2 | E88: 2 | F88: 1 | G88: 7
A89: Grand Total | B89: 157 | C89: 126 | D89: 126 | E89: 110 | F89: 113 | G89: 632

Sheet Average LeadTimeDays
A3: Row Labels | B3: Average of LeadTimeDays
A4: Africa | B4: 12.855172
A5: Kenya | B5: 13.982143
A6: Kisumu | B6: 13.611111
A7: Direct | B7: 10.75
A8: Marketplace | B8: 12
A9: Online | B9: 19.5
A10: Retail | B10: 12.5
A11: Mombasa | B11: 15.142857
A12: Direct | B12: 10.8
A13: Distributor | B13: 19.333333
A14: Marketplace | B14: 6
A15: Online | B15: 17.333333
... A243: Grand Total | B243: 14.262658

Sheet First Time sales
A3: Sum of GrossRevenue | B3: Column Labels
B4: 2023 | C4: 2024 | D4: 2025
A6: Row Labels
A7: 44928 | B7: 249507.27 | C7: 356412.15 | D7: 276703.56
A8: Canada | B8: 249507.27 | C8: 356412.15 | D8: 276703.56
A9: 44933 | B9: 365913.61 | C9: 191518.51 | D9: 223717.69
A10: South Africa | B10: 365913.61 | C10: 191518.51 | D10: 223717.69
A11: 44936 | B11: 269344.22 | C11: 332686.45 | D11: 155704.27
A12: France | B12: 269344.22 | C12: 332686.45 | D12: 155704.27
A13: 44938 | B13: 296031.05 | C13: 431317.1 | D13: 185274.03
A14: China | B14: 296031.05 | C14: 431317.1 | D14: 185274.03
A15: 44939 | B15: 288079.89 | C15: 396688.46 | D15: 83926.237
A16: USA | B16: 288079.89 | C16: 396688.46 | D16: 83926.237
A17: 44941 | B17: 263244.54 | C17: 276445.2 | D17: 342148.93
A18: Nigeria | B18: 263244.54 | C18: 276445.2 | D18: 342148.93
A19: 44945 | B19: 276400.41 | C19: 506208.72 | D19: 328980.3
A20: United Kingdom | B20: 276400.41 | C20: 506208.72 | D20: 328980.3
A21: 44946 | B21: 256981.3 | C21: 558465.3 | D21: 146533.28
A22: Kenya | B22: 256981.3 | C22: 558465.3 | D22: 146533.28
A23: 44948 | B23: 369878.67 | C23: 383309.25 | D23: 176236.96
A24: Germany | B24: 369878.67 | C24: 383309.25 | D24: 176236.96
A25: 44955 | B25: 892100.48 | C25: 676815.25 | D25: 568208.55
A26: Brazil | B26: 377332.38 | C26: 306190.49 | D26: 356075.57
A27: India | B27: 514768.1 | C27: 370624.77 | D27: 212132.98
A28: 44988 | B28: 196462.92 | C28: 370401.94 | D28: 291670.48
A29: Japan | B29: 196462.92 | C29: 370401.94 | D29: 291670.48

Sheet ABC Analysis
A3: Row Labels | B3: Sum of GrossRevenue | C3: Cumulative Revenue % | D3: ABC Analysis
A4: Accessories | B4: 1348617.6
A5: ACC-6626 | B5: 79082.507 | C5: 0.058639681 | D5: =IF(C5<=0.8, "A", IF(C5<=0.95, "B", "C")) -> A
A6: ACC-2988 | B6: 53034.364 | C6: 0.097964664 | D6: =IF(C6<=0.8, "A", IF(C6<=0.95, "B", "C")) -> A
A7: ACC-9283 | B7: 46450.26 | C7: 0.13240753 | D7: =IF(C7<=0.8, "A", IF(C7<=0.95, "B", "C")) -> A
A8: ACC-9533 | B8: 43084.872 | C8: 0.16435497 | D8: =IF(C8<=0.8, "A", IF(C8<=0.95, "B", "C")) -> A
A9: ACC-8098 | B9: 38096.184 | C9: 0.19260329 | D9: =IF(C9<=0.8, "A", IF(C9<=0.95, "B", "C")) -> A
A10: ACC-4490 | B10: 35396.278 | C10: 0.21884963 | D10: =IF(C10<=0.8, "A", IF(C10<=0.95, "B", "C")) -> A
A11: ACC-7838 | B11: 35167.745 | C11: 0.24492651 | D11: =IF(C11<=0.8, "A", IF(C11<=0.95, "B", "C")) -> A
A12: ACC-1238 | B12: 34582.609 | C12: 0.27056952 | D12: =IF(C12<=0.8, "A", IF(C12<=0.95, "B", "C")) -> A
A13: ACC-5177 | B13: 34139.16 | C13: 0.29588371 | D13: =IF(C13<=0.8, "A", IF(C13<=0.95, "B", "C")) -> A
A14: ACC-9162 | B14: 33062.236 | C14: 0.32039936 | D14: =IF(C14<=0.8, "A", IF(C14<=0.95, "B", "C")) -> A
A15: ACC-7078 | B15: 32086.376 | C15: 0.3441914 | D15: =IF(C15<=0.8, "A", IF(C15<=0.95, "B", "C")) -> A
A16: ACC-1375 | B16: 31513.085 | C16: 0.36755836 | D16: =IF(C16<=0.8, "A", IF(C16<=0.95, "B", "C")) -> A
... A92: ACC-1770 | B92: -272.986 | C92: 1 | D92: =IF(C92<=0.8, "A", IF(C92<=0.95, "B", "C")) -> C
A93: Components | B93: 1564991.1 | D93: =IF(C93<=0.8, "A", IF(C93<=0.95, "B", "C")) -> A
A94: CMP-8851 | B94: 139277.83 | C94: 0.088995927 | D94: =IF(C94<=0.8, "A", IF(C94<=0.95, "B", "C")) -> A
A95: CMP-3938 | B95: 84136.12 | C95: 0.14275733 | D95: =IF(C95<=0.8, "A", IF(C95<=0.95, "B", "C")) -> A
A96: CMP-2096 | B96: 65929.714 | C96: 0.18488519 | D96: =IF(C96<=0.8, "A", IF(C96<=0.95, "B", "C")) -> A
A97: CMP-2040 | B97: 65111.386 | C97: 0.22649014 | D97: =IF(C97<=0.8, "A", IF(C97<=0.95, "B", "C")) -> A
A98: CMP-3731 | B98: 60928.502 | C98: 0.26542231 | D98: =IF(C98<=0.8, "A", IF(C98<=0.95, "B", "C")) -> A
A99: CMP-8127 | B99: 50296.415 | C99: 0.29756078 | D99: =IF(C99<=0.8, "A", IF(C99<=0.95, "B", "C")) -> A
A100: CMP-5006 | B100: 41419.524 | C100: 0.32402708 | D100: =IF(C100<=0.8, "A", IF(C100<=0.95, "B", "C")) -> A
A101: CMP-1940 | B101: 40476.013 | C101: 0.3498905 | D101: =IF(C101<=0.8, "A", IF(C101<=0.95, "B", "C")) -> A
A102: CMP-8002 | B102: 33687.502 | C102: 0.37141618 | D102: =IF(C102<=0.8, "A", IF(C102<=0.95, "B", "C")) -> A
A103: CMP-1156 | B103: 33308.55 | C103: 0.39269972 | D103: =IF(C103<=0.8, "A", IF(C103<=0.95, "B", "C")) -> A
A104: CMP-6529 | B104: 32335.218 | C104: 0.41336132 | D104: =IF(C104<=0.8, "A", IF(C104<=0.95, "B", "C")) -> A
A105: CMP-6971 | B105: 27701.57 | C105: 0.43106211 | D105: =IF(C105<=0.8, "A", IF(C105<=0.95, "B", "C")) -> A
... A183: CMP-1632 | B183: 97.0154 | C183: 1 | D183: =IF(C183<=0.8, "A", IF(C183<=0.95, "B", "C")) -> C
A184: Laptops | B184: 1711094.4 | D184: =IF(C184<=0.8, "A", IF(C184<=0.95, "B", "C")) -> A
A185: LAP-8910 | B185: 102122.94 | C185: 0.059682823 | D185: =IF(C185<=0.8, "A", IF(C185<=0.95, "B", "C")) -> A
A186: LAP-3904 | B186: 82514.712 | C186: 0.10790618 | D186: =IF(C186<=0.8, "A", IF(C186<=0.95, "B", "C")) -> A
A187: LAP-8214 | B187: 65119.33 | C187: 0.1459633 | D187: =IF(C187<=0.8, "A", IF(C187<=0.95, "B", "C")) -> A
A188: LAP-5763 | B188: 65066.934 | C188: 0.1839898 | D188: =IF(C188<=0.8, "A", IF(C188<=0.95, "B", "C")) -> A
A189: LAP-6499 | B189: 64192.977 | C189: 0.22150555 | D189: =IF(C189<=0.8, "A", IF(C189<=0.95, "B", "C")) -> A
A190: LAP-1739 | B190: 58526.831 | C190: 0.25570987 | D190: =IF(C190<=0.8, "A", IF(C190<=0.95, "B", "C")) -> A
A191: LAP-8825 | B191: 58057.65 | C191: 0.28964 | D191: =IF(C191<=0.8, "A", IF(C191<=0.95, "B", "C")) -> A
A192: LAP-7523 | B192: 44173.628 | C192: 0.31545601 | D192: =IF(C192<=0.8, "A", IF(C192<=0.95, "B", "C")) -> A
A193: LAP-1308 | B193: 42433.254 | C193: 0.34025491 | D193: =IF(C193<=0.8, "A", IF(C193<=0.95, "B", "C")) -> A
A194: LAP-1178 | B194: 41914.216 | C194: 0.36475047 | D194: =IF(C194<=0.8, "A", IF(C194<=0.95, "B", "C")) -> A
A195: LAP-4483 | B195: 40563.322 | C195: 0.38845654 | D195: =IF(C195<=0.8, "A", IF(C195<=0.95, "B", "C")) -> A
A196: LAP-3490 | B196: 40139.875 | C196: 0.41191513 | D196: =IF(C196<=0.8, "A", IF(C196<=0.95, "B", "C")) -> A
... A265: LAP-3017 | B265: 266.17822 | C265: 1 | D265: =IF(C265<=0.8, "A", IF(C265<=0.95, "B", "C")) -> C
A266: Monitors | B266: 1551626 | D266: =IF(C266<=0.8, "A", IF(C266<=0.95, "B", "C")) -> A
A267: MON-6962 | B267: 92715.25 | C267: 0.059753607 | D267: =IF(C267<=0.8, "A", IF(C267<=0.95, "B", "C")) -> A
A268: MON-2266 | B268: 87404.93 | C268: 0.11608479 | D268: =IF(C268<=0.8, "A", IF(C268<=0.95, "B", "C")) -> A
A269: MON-6699 | B269: 85637.74 | C269: 0.17127705 | D269: =IF(C269<=0.8, "A", IF(C269<=0.95, "B", "C")) -> A
A270: MON-5188 | B270: 72665.817 | C270: 0.21810909 | D270: =IF(C270<=0.8, "A", IF(C270<=0.95, "B", "C")) -> A
A271: MON-9662 | B271: 56176.778 | C271: 0.2543142 | D271: =IF(C271<=0.8, "A", IF(C271<=0.95, "B", "C")) -> A
A272: MON-5386 | B272: 45547.183 | C272: 0.28366868 | D272: =IF(C272<=0.8, "A", IF(C272<=0.95, "B", "C")) -> A
A273: MON-9967 | B273: 41106.801 | C273: 0.31016141 | D273: =IF(C273<=0.8, "A", IF(C273<=0.95, "B", "C")) -> A
A274: MON-9733 | B274: 38818.76 | C274: 0.33517952 | D274: =IF(C274<=0.8, "A", IF(C274<=0.95, "B", "C")) -> A
A275: MON-8651 | B275: 34632.106 | C275: 0.3574994 | D275: =IF(C275<=0.8, "A", IF(C275<=0.95, "B", "C")) -> A
A276: MON-4373 | B276: 32280.325 | C276: 0.3783036 | D276: =IF(C276<=0.8, "A", IF(C276<=0.95, "B", "C")) -> A
A277: MON-4925 | B277: 31680.795 | C277: 0.3987214 | D277: =IF(C277<=0.8, "A", IF(C277<=0.95, "B", "C")) -> A
A278: MON-6341 | B278: 31191.647 | C278: 0.41882395 | D278: =IF(C278<=0.8, "A", IF(C278<=0.95, "B", "C")) -> A
... A360: MON-4215 | B360: -846.34704 | C360: 1 | D360: =IF(C360<=0.8, "A", IF(C360<=0.95, "B", "C")) -> C
A361: Networking | B361: 1777505.6 | D361: =IF(C361<=0.8, "A", IF(C361<=0.95, "B", "C")) -> A
A362: NET-2365 | B362: 109244 | C362: 0.061459159 | D362: =IF(C362<=0.8, "A", IF(C362<=0.95, "B", "C")) -> A
A363: NET-5987 | B363: 82141.34 | C363: 0.10767074 | D363: =IF(C363<=0.8, "A", IF(C363<=0.95, "B", "C")) -> A
A364: NET-5523 | B364: 79548.756 | C364: 0.15242376 | D364: =IF(C364<=0.8, "A", IF(C364<=0.95, "B", "C")) -> A
A365: NET-1612 | B365: 66988.771 | C365: 0.19011072 | D365: =IF(C365<=0.8, "A", IF(C365<=0.95, "B", "C")) -> A
A366: NET-5018 | B366: 60292.805 | C366: 0.22403061 | D366: =IF(C366<=0.8, "A", IF(C366<=0.95, "B", "C")) -> A
A367: NET-1282 | B367: 51768.182 | C367: 0.25315467 | D367: =IF(C367<=0.8, "A", IF(C367<=0.95, "B", "C")) -> A
A368: NET-4735 | B368: 50090.397 | C368: 0.28133483 | D368: =IF(C368<=0.8, "A", IF(C368<=0.95, "B", "C")) -> A
A369: NET-3850 | B369: 49336.511 | C369: 0.30909087 | D369: =IF(C369<=0.8, "A", IF(C369<=0.95, "B", "C")) -> A
A370: NET-6036 | B370: 47962.718 | C370: 0.33607403 | D370: =IF(C370<=0.8, "A", IF(C370<=0.95, "B", "C")) -> A
A371: NET-3828 | B371: 47693.373 | C371: 0.36290566 | D371: =IF(C371<=0.8, "A", IF(C371<=0.95, "B", "C")) -> A
A372: NET-3535 | B372: 43553.493 | C372: 0.38740825 | D372: =IF(C372<=0.8, "A", IF(C372<=0.95, "B", "C")) -> A
A373: NET-1893 | B373: 40488.793 | C373: 0.41018668 | D373: =IF(C373<=0.8, "A", IF(C373<=0.95, "B", "C")) -> A
... A447: NET-9666 | B447: -319.72248 | C447: 1 | D447: =IF(C447<=0.8, "A", IF(C447<=0.95, "B", "C")) -> C
A448: Phones | B448: 1404434.7 | D448: =IF(C448<=0.8, "A", IF(C448<=0.95, "B", "C")) -> A
A449: PHN-9677 | B449: 68665.574 | C449: 0.048891968 | D449: =IF(C449<=0.8, "A", IF(C449<=0.95, "B", "C")) -> A
A450: PHN-8368 | B450: 52780.07 | C450: 0.086472976 | D450: =IF(C450<=0.8, "A", IF(C450<=0.95, "B", "C")) -> A
A451: PHN-4568 | B451: 42495.805 | C451: 0.11673128 | D451: =IF(C451<=0.8, "A", IF(C451<=0.95, "B", "C")) -> A
A452: PHN-7488 | B452: 41352.246 | C452: 0.14617533 | D452: =IF(C452<=0.8, "A", IF(C452<=0.95, "B", "C")) -> A
A453: PHN-5683 | B453: 41138.262 | C453: 0.17546702 | D453: =IF(C453<=0.8, "A", IF(C453<=0.95, "B", "C")) -> A
A454: PHN-4915 | B454: 38422.022 | C454: 0.20282466 | D454: =IF(C454<=0.8, "A", IF(C454<=0.95, "B", "C")) -> A
A455: PHN-8804 | B455: 37038.582 | C455: 0.22919725 | D455: =IF(C455<=0.8, "A", IF(C455<=0.95, "B", "C")) -> A
A456: PHN-1197 | B456: 35367.211 | C456: 0.25437978 | D456: =IF(C456<=0.8, "A", IF(C456<=0.95, "B", "C")) -> A
A457: PHN-6832 | B457: 34840.344 | C457: 0.27918716 | D457: =IF(C457<=0.8, "A", IF(C457<=0.95, "B", "C")) -> A
A458: PHN-8776 | B458: 34800.431 | C458: 0.30396612 | D458: =IF(C458<=0.8, "A", IF(C458<=0.95, "B", "C")) -> A
A459: PHN-6111 | B459: 33551.927 | C459: 0.32785611 | D459: =IF(C459<=0.8, "A", IF(C459<=0.95, "B", "C")) -> A
A460: PHN-1919 | B460: 33071.315 | C460: 0.35140388 | D460: =IF(C460<=0.8, "A", IF(C460<=0.95, "B", "C")) -> A
... A536: PHN-3803 | B536: 76.13872 | C536: 1 | D536: =IF(C536<=0.8, "A", IF(C536<=0.95, "B", "C")) -> C
A537: Printers | B537: 1625047.7 | D537: =IF(C537<=0.8, "A", IF(C537<=0.95, "B", "C")) -> A
A538: PRN-1654 | B538: 66260.314 | C538: 0.040774381 | D538: =IF(C538<=0.8, "A", IF(C538<=0.95, "B", "C")) -> A
A539: PRN-6308 | B539: 58091.635 | C539: 0.076522031 | D539: =IF(C539<=0.8, "A", IF(C539<=0.95, "B", "C")) -> A
A540: PRN-7019 | B540: 55880.484 | C540: 0.11090901 | D540: =IF(C540<=0.8, "A", IF(C540<=0.95, "B", "C")) -> A
A541: PRN-2407 | B541: 50545.319 | C541: 0.14201291 | D541: =IF(C541<=0.8, "A", IF(C541<=0.95, "B", "C")) -> A
A542: PRN-9490 | B542: 43907.94 | C542: 0.16903239 | D542: =IF(C542<=0.8, "A", IF(C542<=0.95, "B", "C")) -> A
A543: PRN-8970 | B543: 43209.006 | C543: 0.19562177 | D543: =IF(C543<=0.8, "A", IF(C543<=0.95, "B", "C")) -> A
A544: PRN-2293 | B544: 40325.31 | C544: 0.22043661 | D544: =IF(C544<=0.8, "A", IF(C544<=0.95, "B", "C")) -> A
A545: PRN-6131 | B545: 39810.328 | C545: 0.24493456 | D545: =IF(C545<=0.8, "A", IF(C545<=0.95, "B", "C")) -> A
A546: PRN-3143 | B546: 39541.602 | C546: 0.26926714 | D546: =IF(C546<=0.8, "A", IF(C546<=0.95, "B", "C")) -> A
A547: PRN-5384 | B547: 38535.955 | C547: 0.29298087 | D547: =IF(C547<=0.8, "A", IF(C547<=0.95, "B", "C")) -> A
A548: PRN-5876 | B548: 37562.28 | C548: 0.31609545 | D548: =IF(C548<=0.8, "A", IF(C548<=0.95, "B", "C")) -> A
A549: PRN-7079 | B549: 36549.429 | C549: 0.33858674 | D549: =IF(C549<=0.8, "A", IF(C549<=0.95, "B", "C")) -> A
... A640: PRN-6276 | B640: 685.06776 | C640: 1 | D640: =IF(C640<=0.8, "A", IF(C640<=0.95, "B", "C")) -> C
A641: Grand Total | B641: 10983317 | D641: =IF(C641<=0.8, "A", IF(C641<=0.95, "B", "C")) -> A

Sheet Salesperson productivity
I1: Total No. of months
I2: =((YEAR(MAX(Clean!B:B))-YEAR(MIN(Clean!B:B)))*12)+MONTH(MAX(Clean!B:B))-MONTH(MIN(Clean!B:B))+1 -> 33
A3: Row Labels | B3: Sum of GrossRevenue | C3: Sum of GrossProfit | D3: Count of OrderID | E3: Revenue/Order | F3: Profit/Order | G3: Orders/month
A4: A. Patel | B4: 1006901.3 | C4: 339146.98 | D4: 48 | E4: =B4/D4 -> 20977.111 | F4: =C4/D4 -> 7065.562 | G4: =D4/$I$2 -> 1.4545455
A5: B. Chen | B5: 923864.85 | C5: 323552.44 | D5: 50 | E5: =B5/D5 -> 18477.297 | F5: =C5/D5 -> 6471.0489 | G5: =D5/$I$2 -> 1.5151515
A6: C. Otieno | B6: 708536.86 | C6: 249120.02 | D6: 37 | E6: =B6/D6 -> 19149.645 | F6: =C6/D6 -> 6732.9736 | G6: =D6/$I$2 -> 1.1212121
A7: D. Smith | B7: 614644.3 | C7: 170472.52 | D7: 39 | E7: =B7/D7 -> 15760.11 | F7: =C7/D7 -> 4371.0903 | G7: =D7/$I$2 -> 1.1818182
A8: E. Garcia | B8: 543846.44 | C8: 204981.34 | D8: 34 | E8: =B8/D8 -> 15995.484 | F8: =C8/D8 -> 6028.863 | G8: =D8/$I$2 -> 1.030303
A9: F. Müller | B9: 828392.19 | C9: 250204.19 | D9: 53 | E9: =B9/D9 -> 15630.041 | F9: =C9/D9 -> 4720.8338 | G9: =D9/$I$2 -> 1.6060606
A10: G. Dubois | B10: 510653.71 | C10: 172441.87 | D10: 30 | E10: =B10/D10 -> 17021.79 | F10: =C10/D10 -> 5748.0624 | G10: =D10/$I$2 -> 0.90909091
A11: H. Kim | B11: 709753.82 | C11: 149206.33 | D11: 45 | E11: =B11/D11 -> 15772.307 | F11: =C11/D11 -> 3315.6962 | G11: =D11/$I$2 -> 1.3636364
A12: I. Johnson | B12: 540526.23 | C12: 139382.25 | D12: 38 | E12: =B12/D12 -> 14224.374 | F12: =C12/D12 -> 3667.9539 | G12: =D12/$I$2 -> 1.1515152
A13: J. Njeri | B13: 802384.66 | C13: 273113.11 | D13: 50 | E13: =B13/D13 -> 16047.693 | F13: =C13/D13 -> 5462.2622 | G13: =D13/$I$2 -> 1.5151515
A14: K. Singh | B14: 883348.13 | C14: 278762.27 | D14: 44 | E14: =B14/D14 -> 20076.094 | F14: =C14/D14 -> 6335.5061 | G14: =D14/$I$2 -> 1.3333333
A15: L. Okafor | B15: 855204.51 | C15: 271882.54 | D15: 46 | E15: =B15/D15 -> 18591.402 | F15: =C15/D15 -> 5910.49 | G15: =D15/$I$2 -> 1.3939394
... A18: O. Wang | B18: 647724.9 | C18: 185219.44 | D18: 37 | E18: =B18/D18 -> 17506.078 | F18: =C18/D18 -> 5005.9307 | G18: =D18/$I$2 -> 1.1212121
A19: Grand Total | B19: 10983317 | C19: 3455569.3 | D19: 632

Sheet Channel cannibalization
A3: Sum of GrossRevenue | B3: Column Labels
A4: Row Labels | B4: Direct | C4: Distributor | D4: Marketplace | E4: Online | F4: Retail | G4: Grand Total
A5: Africa | B5: 0.1798227 | C5: 0.25675855 | D5: 0.20094256 | E5: 0.16510917 | F5: 0.19736702 | G5: 1
A6: Americas | B6: 0.279417 | C6: 0.21204349 | D6: 0.13959264 | E6: 0.25640022 | F6: 0.11254665 | G6: 1
A7: Asia | B7: 0.22526545 | C7: 0.18101862 | D7: 0.19690801 | E7: 0.14419908 | F7: 0.25260883 | G7: 1
A8: Europe | B8: 0.30751769 | C8: 0.1138854 | D8: 0.20335175 | E8: 0.20916726 | F8: 0.16607791 | G8: 1
A9: Grand Total | B9: 0.24863133 | C9: 0.18961449 | D9: 0.18547195 | E9: 0.1932409 | F9: 0.18304133 | G9: 1

Sheet 7 Day target
A3: Count of OrderID | B3: Column Labels
A4: Row Labels | B4: No | C4: Yes | D4: Grand Total
A5: Brazil | B5: 0.74193548 | C5: 0.25806452 | D5: 1
A6: Accessories | B6: 0.6 | C6: 0.4 | D6: 1
A7: Components | B7: 0.85714286 | C7: 0.14285714 | D7: 1
A8: Laptops | B8: 0.8 | C8: 0.2 | D8: 1
A9: Monitors | B9: 0.75 | C9: 0.25 | D9: 1
A10: Networking | B10: 0.83333333 | C10: 0.16666667 | D10: 1
A11: Phones | B11: 0.55555556 | C11: 0.44444444 | D11: 1
A12: Printers | B12: 0.85714286 | C12: 0.14285714 | D12: 1
A13: Canada | B13: 0.79545455 | C13: 0.20454545 | D13: 1
A14: Accessories | B14: 0.66666667 | C14: 0.33333333 | D14: 1
A15: Components | B15: 0.5 | C15: 0.5 | D15: 1
A16: Laptops | B16: 0.66666667 | C16: 0.33333333 | D16: 1
... A101: Grand Total | B101: 0.76265823 | C101: 0.23734177 | D101: 1

Sheet Discount Compliance
A3: Count of OrderID | B3: Column Labels
A4: Row Labels | B4: No | C4: Yes | D4: Grand Total
A5: Africa | B5: 0.86896552 | C5: 0.13103448 | D5: 1
A6: A. Patel | B6: 0.83333333 | C6: 0.16666667 | D6: 1
A7: B. Chen | B7: 1 | C7: 0 | D7: 1
A8: C. Otieno | B8: 0.75 | C8: 0.25 | D8: 1
A9: D. Smith | B9: 0.8 | C9: 0.2 | D9: 1
A10: E. Garcia | B10: 0.8 | C10: 0.2 | D10: 1
A11: F. Müller | B11: 1 | C11: 0 | D11: 1
A12: G. Dubois | B12: 1 | C12: 0 | D12: 1
A13: H. Kim | B13: 1 | C13: 0 | D13: 1
A14: I. Johnson | B14: 0.75 | C14: 0.25 | D14: 1
A15: J. Njeri | B15: 0.75 | C15: 0.25 | D15: 1
A16: K. Singh | B16: 1 | C16: 0 | D16: 1
... A69: Grand Total | B69: 0.86867089 | C69: 0.13132911 | D69: 1

Sheet Scenario Modeling
E1: Baseline | F1: Scenario | G1: Variance | H1: % Change
A2: Global Discount Cap (0% - 25%) | B2: 0.25 | D2: Total Revenue | E2: =SUM(Clean!AB2:AB633) -> 10983317 | F2: =SUM(Clean!AI2:AI633) -> 10994485 | G2: =F2-E2 -> 11167.627 | H2: =G2/E2*(100) -> 0.10167809
A3: UnitCost inflation factor (0% - 15%) | B3: 0 | D3: Total Gross Profit | E3: =SUM(Clean!AD2:AD633) -> 3455569.3 | F3: =SUM(Clean!AJ2:AJ633) -> 3466736.9 | G3: =F3-E3 -> 11167.627 | H3: =G3/E3*(100) -> 0.32317764
A4: Quantity uplift (0% - 20%) | B4: 0
